lab4/yju_basic/Q2/q2.v
`timescale 1ns/1ps

//`define 3'b000 3'b000;
//`define 3'b001 3'b001;
//`define 3'b010 3'b010;
//`define 3'b011 3'b011;
//`define 3'b100 3'b100;
//`define 3'b101 3'b101;

module mealy_machine(clk, rst_n, in, state, out);

    input rst_n, clk, in;
    output reg [3-1:0] state
    output reg out;

    always @(*) begin
        case ({state, in})
            {3'b000, 1'b0}: out = 1'b0;
            {3'b000, 1'b1}: out = 1'b1;
            {3'b001, 1'b0}: out = 1'b1;
            {3'b001, 1'b1}: out = 1'b1;
            {3'b010, 1'b0}: out = 1'b1;
            {3'b010, 1'b1}: out = 1'b0;
            {3'b011, 1'b0}: out = 1'b1;
            {3'b011, 1'b1}: out = 1'b0;
            {3'b100, 1'b0}: out = 1'b1;
            {3'b100, 1'b1}: out = 1'b1;
            {3'b101, 1'b0}: out = 1'b0;
            {3'b101, 1'b1}: out = 1'b0;
        endcase
    end

    always @(posedge clk) begin
        if (~rst_n) begin
            state <= 3'b000;
        end else begin
            case (state)
                3'b000: state <= (~in ? 3'b000 : 3'b010);
                3'b001: state <= (~in ? 3'b000 : 3'b100);
                3'b010: state <= (~in ? 3'b101 : 3'b001);
                3'b011: state <= (~in ? 3'b011 : 3'b010);
                3'b100: state <= (~in ? 3'b010 : 3'b100);
                3'b101: state <= (~in ? 3'b011 : 3'b100);
            endcase
        end
    end

    always #(5) begin
        $display("state: %b, out: %b, in: %b",state, out, in);
    end

endmodule

lab4/yju_basic/Q2/q2_t.v
`timescale 1ns/1ps

module mealy_machine_t();

    reg clk = 0;
    reg rst_n = 0;
    reg in = 0;
    wire [3-1:0] state;
    wire out;

    parameter cyc = 10;
    always #(cyc/2) clk = ~clk;

    mealy_machine M1(
        .clk(clk),
        .rst_n(rst_n),
        .in(in),
        .state(state),
        .out(out)
    );

    initial begin
        $dumpfile("q2.vcd");
        $dumpvars("+all");
    end

    initial begin
        #1
        @(negedge clk)
        rst_n = 1;
        @(negedge clk)
        in = $random;
        @(negedge clk)
        in = $random;
        @(negedge clk)
        in = $random;
        @(negedge clk)
        in = $random;
        @(negedge clk)
        in = $random;
        @(negedge clk)
        in = $random;
        @(negedge clk)
        in = $random;
        @(negedge clk)
        in = $random;
        @(negedge clk)
        in = $random;
        @(negedge clk)
        in = $random;
        @(negedge clk)
        in = $random;
        @(negedge clk)
        in = $random;
        @(negedge clk)
        in = $random;
        @(negedge clk)
        in = $random;
        @(negedge clk)
        in = $random;
        @(negedge clk)
        in = $random;
        @(negedge clk)
        in = $random;
        @(negedge clk)
        in = $random;
        @(negedge clk)
        in = $random;
        @(negedge clk)
        in = $random;
        @(negedge clk)
        in = $random;
        @(negedge clk)
        in = $random;
        @(negedge clk)
        in = $random;
        @(negedge clk)
        in = $random;
        $finish;
    end
endmodule

lab4/yju_basic/Q2/q2.vcd
$date
    Nov  3, 2022  09:50:10
$end
$version
    TOOL:	ncsim	15.20-s039
$end
$timescale
    1 ps
$end

$scope module mealy_machine_t $end
$var reg       1 !    clk  $end
$var reg       1 "    rst_n  $end
$var reg       1 #    in  $end
$var wire      3 $    state [2:0] $end
$var wire      1 %    out  $end
$var parameter 32 &    cyc  $end

$scope module M1 $end
$var wire      1 '    rst_n  $end
$var wire      1 (    clk  $end
$var wire      1 )    in  $end
$var reg       3 *    state [2:0] $end
$var reg       1 +    out  $end
$upscope $end

$upscope $end

$enddefinitions $end
$dumpvars
b1010 &
0!
0"
0#
bx $
x%
0'
0(
0)
bx *
x+
$end
#5000
1!
1(
b0 *
0+
0%
b0 $
#10000
0!
1"
1'
0(
#15000
1!
1(
#20000
0!
0(
#25000
1!
1(
#30000
0!
1#
1)
0(
1+
1%
#35000
1!
1(
b10 *
0+
0%
b10 $
#40000
0!
0(
#45000
1!
1(
b1 *
1+
1%
b1 $
#50000
0!
0(
#55000
1!
1(
b100 *
b100 $
#60000
0!
0(
#65000
1!
1(
#70000
0!
0(
#75000
1!
1(
#80000
0!
0(
#85000
1!
1(
#90000
0!
0#
0)
0(
#95000
1!
1(
b10 *
b10 $
#100000
0!
1#
1)
0(
0+
0%
#105000
1!
1(
b1 *
1+
1%
b1 $
#110000
0!
0(
#115000
1!
1(
b100 *
b100 $
#120000
0!
0#
0)
0(
#125000
1!
1(
b10 *
b10 $
#130000
0!
1#
1)
0(
0+
0%
#135000
1!
1(
b1 *
1+
1%
b1 $
#140000
0!
0(
#145000
1!
1(
b100 *
b100 $
#150000
0!
0#
0)
0(
#155000
1!
1(
b10 *
b10 $
#160000
0!
1#
1)
0(
0+
0%
#165000
1!
1(
b1 *
1+
1%
b1 $
#170000
0!
0#
0)
0(
#175000
1!
1(
b0 *
0+
0%
b0 $
#180000
0!
1#
1)
0(
1+
1%
#185000
1!
1(
b10 *
0+
0%
b10 $
#190000
0!
0#
0)
0(
1+
1%
#195000
1!
1(
b101 *
0+
0%
b101 $
#200000
0!
1#
1)
0(
#205000
1!
1(
b100 *
1+
1%
b100 $
#210000
0!
0(
#215000
1!
1(
#220000
0!
0#
0)
0(
#225000
1!
1(
b10 *
b10 $
#230000
0!
1#
1)
0(
0+
0%
#235000
1!
1(
b1 *
1+
1%
b1 $
#240000
0!
0#
0)
0(
#245000
1!
1(
b0 *
0+
0%
b0 $
