lab2/Lab2_tb_testing/RCA.v
`timescale 1ns/1ps

module half_adder(a, b, cout, sum);
    input a, b;
    output cout, sum;

    xor X(sum, a, b);
    and A(cout, a, b);

endmodule

module Full_Adder(a, b, cin, cout, sum);
    input a, b, cin;
    output cout, sum;

    wire w1, w2, w3;

    half_adder H0(a, b, w1, w2);
    half_adder H1(w2, cin, w3, sum);
    or O0(cout, w3, w1);

endmodule

module Ripple_Carry_Adder(a, b, cin, cout, sum);
    input [4-1:0] a, b;
    input cin;
    output cout;
    output [4-1:0] sum;

    wire tmp[3-1:0];

    Full_Adder F0(a[0], b[0], cin, tmp[0], sum[0]);
    Full_Adder F1(a[1], b[1], tmp[0], tmp[1], sum[1]);
    Full_Adder F2(a[2], b[2], tmp[1], tmp[2], sum[2]);
    Full_Adder F3(a[3], b[3], tmp[2], cout, sum[3]);

endmodule

lab2/Lab2_tb_testing/Lab2_Team25_Exhausted_Testing.v
`timescale 1ns/1ps

module Exhausted_Testing(a, b, cin, error, done);
    output [4-1:0] a, b;
    output cin;
    output error;
    output done;

    // input signal to the test instance.
    reg [4-1:0] a = 4'b0000;
    reg [4-1:0] b = 4'b0000;
    reg cin = 1'b0;

    // initial value for the done and error indicator: not done, no error
    reg done = 1'b0;
    reg error = 1'b0;

    // output from the test instance.
    wire [4-1:0] sum;
    wire cout;

    // instantiate the test instance.
    Ripple_Carry_Adder rcs(
        .a (a), 
        .b (b),
        .cin (cin),
        .cout (cout),
        .sum (sum)
    );

    initial begin
        $dumpfile("test.vcd");
        $dumpvars("+all");
    end

    initial begin
        // design your test pattern here.
        // Remember to set the input pattern to the test instance every
        // 5 nanosecond.
        // Check the output and set the `error` signal accordingly
        // 1 nanosecond after new input is set.
        // Also set the done signal to 1'b1 5 nanoseconds after the test is
        // finished.
        // Example:
        // setting the input
        // a = 4'b0000;
        // b = 4'b0000;
        // cin = 1'b0;
        // check the output 
        // #1
        // check the output;
        // #4
        // setting another input 
        // a = 4'b0001;
        // b = 4'b0000;
        // cin = 1'b0;
        // .....
        // #4
        // The last input pattern
        // a = 4'b1111;
        // b = 4'b1111;
        // cin = 1'b1;
        // #1
        // check_output;
        // #4
        // setting the done signal 
        // done = 1'b1;
        repeat (2 ** 9) begin
            #1 if ((a + b + cin) === {cout, sum}) begin
                error = 1'b0;
            end
            else begin
                error = 1'b1;
            end
            #4;
            {a, b, cin} = {a, b, cin} + 1'b1;
        end
        done = 1'b1;
        #5 done = 1'b0;
    end

endmodule

lab2/Lab2_tb_testing/test.vcd
$date
    Oct 11, 2022  16:17:25
$end
$version
    TOOL:	ncsim	15.20-s039
$end
$timescale
    1 ps
$end

$scope module Exhausted_Testing $end
$var reg       4 !    a [3:0] $end
$var reg       4 "    b [3:0] $end
$var reg       1 #    cin  $end
$var reg       1 $    error  $end
$var reg       1 %    done  $end
$var wire      1 &    sum [3] $end
$var wire      1 '    sum [2] $end
$var wire      1 (    sum [1] $end
$var wire      1 )    sum [0] $end
$var wire      1 *    cout  $end

$scope module rcs $end
$var wire      1 +    a [3] $end
$var wire      1 ,    a [2] $end
$var wire      1 -    a [1] $end
$var wire      1 .    a [0] $end
$var wire      1 /    b [3] $end
$var wire      1 0    b [2] $end
$var wire      1 1    b [1] $end
$var wire      1 2    b [0] $end
$var wire      1 3    cin  $end
$var wire      1 *    cout  $end
$var wire      1 &    sum [3] $end
$var wire      1 '    sum [2] $end
$var wire      1 (    sum [1] $end
$var wire      1 )    sum [0] $end
$var wire      1 4    tmp [2] $end
$var wire      1 5    tmp [1] $end
$var wire      1 6    tmp [0] $end

$scope module F0 $end
$var wire      1 .    a  $end
$var wire      1 2    b  $end
$var wire      1 3    cin  $end
$var wire      1 6    cout  $end
$var wire      1 )    sum  $end
$var wire      1 7    w1  $end
$var wire      1 8    w2  $end
$var wire      1 9    w3  $end

$scope module H0 $end
$var wire      1 .    a  $end
$var wire      1 2    b  $end
$var wire      1 7    cout  $end
$var wire      1 8    sum  $end
$upscope $end


$scope module H1 $end
$var wire      1 8    a  $end
$var wire      1 3    b  $end
$var wire      1 9    cout  $end
$var wire      1 )    sum  $end
$upscope $end

$upscope $end


$scope module F1 $end
$var wire      1 -    a  $end
$var wire      1 1    b  $end
$var wire      1 6    cin  $end
$var wire      1 5    cout  $end
$var wire      1 (    sum  $end
$var wire      1 :    w1  $end
$var wire      1 ;    w2  $end
$var wire      1 <    w3  $end

$scope module H0 $end
$var wire      1 -    a  $end
$var wire      1 1    b  $end
$var wire      1 :    cout  $end
$var wire      1 ;    sum  $end
$upscope $end


$scope module H1 $end
$var wire      1 ;    a  $end
$var wire      1 6    b  $end
$var wire      1 <    cout  $end
$var wire      1 (    sum  $end
$upscope $end

$upscope $end


$scope module F2 $end
$var wire      1 ,    a  $end
$var wire      1 0    b  $end
$var wire      1 5    cin  $end
$var wire      1 4    cout  $end
$var wire      1 '    sum  $end
$var wire      1 =    w1  $end
$var wire      1 >    w2  $end
$var wire      1 ?    w3  $end

$scope module H0 $end
$var wire      1 ,    a  $end
$var wire      1 0    b  $end
$var wire      1 =    cout  $end
$var wire      1 >    sum  $end
$upscope $end


$scope module H1 $end
$var wire      1 >    a  $end
$var wire      1 5    b  $end
$var wire      1 ?    cout  $end
$var wire      1 '    sum  $end
$upscope $end

$upscope $end


$scope module F3 $end
$var wire      1 +    a  $end
$var wire      1 /    b  $end
$var wire      1 4    cin  $end
$var wire      1 *    cout  $end
$var wire      1 &    sum  $end
$var wire      1 @    w1  $end
$var wire      1 A    w2  $end
$var wire      1 B    w3  $end

$scope module H0 $end
$var wire      1 +    a  $end
$var wire      1 /    b  $end
$var wire      1 @    cout  $end
$var wire      1 A    sum  $end
$upscope $end


$scope module H1 $end
$var wire      1 A    a  $end
$var wire      1 4    b  $end
$var wire      1 B    cout  $end
$var wire      1 &    sum  $end
$upscope $end

$upscope $end

$upscope $end

$upscope $end

$enddefinitions $end
$dumpvars
b0 !
b0 "
0#
0$
0%
0&
0'
0(
0)
0*
0+
0,
0-
0.
0/
00
01
02
03
04
05
06
07
08
09
0:
0;
0<
0=
0>
0?
0@
0A
0B
$end
#5000
1#
13
1)
#10000
0#
b1 "
12
03
1)
18
#15000
1#
13
0)
19
16
1(
#20000
0#
b10 "
11
02
03
0)
09
08
1;
1(
0<
06
#25000
1#
13
1)
#30000
0#
b11 "
12
03
1)
18
#35000
1#
13
0)
19
16
0(
1<
15
1'
#40000
0#
b100 "
10
01
02
03
0)
09
08
0;
1>
1'
0?
0(
0<
06
05
04
0&
#45000
1#
13
1)
#50000
0#
b101 "
12
03
1)
18
#55000
1#
13
0)
19
16
1(
#60000
0#
b110 "
11
02
03
0)
09
08
1;
1(
0<
06
#65000
1#
13
1)
#70000
0#
b111 "
12
03
1)
18
#75000
1#
13
0)
19
16
0(
1<
15
0'
1?
14
1&
#80000
0#
b1000 "
1/
00
01
02
03
0)
09
08
0;
0>
1A
1&
0B
0'
0?
0(
0<
06
05
04
0*
#85000
1#
13
1)
#90000
0#
b1001 "
12
03
1)
18
#95000
1#
13
0)
19
16
1(
#100000
0#
b1010 "
11
02
03
0)
09
08
1;
1(
0<
06
#105000
1#
13
1)
#110000
0#
b1011 "
12
03
1)
18
#115000
1#
13
0)
19
16
0(
1<
15
1'
#120000
0#
b1100 "
10
01
02
03
0)
09
08
0;
1>
1'
0?
0(
0<
06
05
04
1&
0B
0*
#125000
1#
13
1)
#130000
0#
b1101 "
12
03
1)
18
#135000
1#
13
0)
19
16
1(
#140000
0#
b1110 "
11
02
03
0)
09
08
1;
1(
0<
06
#145000
1#
13
1)
#150000
0#
b1111 "
12
03
1)
18
#155000
1#
13
0)
19
16
0(
1<
15
0'
1?
14
0&
1B
1*
#160000
0#
b0 "
b1 !
1.
0/
00
01
02
03
1)
09
0;
0>
0A
0&
0B
0'
0?
0(
0<
06
05
04
0*
#165000
1#
13
0)
19
16
1(
#170000
0#
b1 "
12
03
0)
09
08
17
#175000
1#
13
1)
#180000
0#
b10 "
11
02
03
1)
18
07
1;
1(
0<
06
#185000
1#
13
0)
19
16
0(
1<
15
1'
#190000
0#
b11 "
12
03
0)
09
08
17
#195000
1#
13
1)
#200000
0#
b100 "
10
01
02
03
1)
18
07
0;
1>
1'
0?
0(
0<
06
05
04
0&
#205000
1#
13
0)
19
16
1(
#210000
0#
b101 "
12
03
0)
09
08
17
#215000
1#
13
1)
#220000
0#
b110 "
11
02
03
1)
18
07
1;
1(
0<
06
#225000
1#
13
0)
19
16
0(
1<
15
0'
1?
14
1&
#230000
0#
b111 "
12
03
0)
09
08
17
#235000
1#
13
1)
#240000
0#
b1000 "
1/
00
01
02
03
1)
18
07
0;
0>
1A
1&
0B
0'
0?
0(
0<
06
05
04
0*
#245000
1#
13
0)
19
16
1(
#250000
0#
b1001 "
12
03
0)
09
08
17
#255000
1#
13
1)
#260000
0#
b1010 "
11
02
03
1)
18
07
1;
1(
0<
06
#265000
1#
13
0)
19
16
0(
1<
15
1'
#270000
0#
b1011 "
12
03
0)
09
08
17
#275000
1#
13
1)
#280000
0#
b1100 "
10
01
02
03
1)
18
07
0;
1>
1'
0?
0(
0<
06
05
04
1&
0B
0*
#285000
1#
13
0)
19
16
1(
#290000
0#
b1101 "
12
03
0)
09
08
17
#295000
1#
13
1)
#300000
0#
b1110 "
11
02
03
1)
18
07
1;
1(
0<
06
#305000
1#
13
0)
19
16
0(
1<
15
0'
1?
14
0&
1B
1*
#310000
0#
b1111 "
12
03
0)
09
08
17
#315000
1#
13
1)
#320000
0#
b0 "
b10 !
1-
0.
0/
00
01
02
03
0)
0>
0A
07
06
0&
0B
0'
0?
04
0*
1(
0<
05
#325000
1#
13
1)
#330000
0#
b1 "
12
03
1)
18
#335000
1#
13
0)
19
16
0(
1<
15
1'
#340000
0#
b10 "
11
02
03
0)
09
08
0;
1:
0(
0<
06
#345000
1#
13
1)
#350000
0#
b11 "
12
03
1)
18
#355000
1#
13
0)
19
16
1(
#360000
0#
b100 "
10
01
02
03
0)
09
08
1;
0:
1>
1'
0?
05
1(
0<
06
#365000
1#
13
1)
#370000
0#
b101 "
12
03
1)
18
#375000
1#
13
0)
19
16
0(
1<
15
0'
1?
14
1&
#380000
0#
b110 "
11
02
03
0)
09
08
0;
1:
0(
0<
06
#385000
1#
13
1)
#390000
0#
b111 "
12
03
1)
18
#395000
1#
13
0)
19
16
1(
#400000
0#
b1000 "
1/
00
01
02
03
0)
09
08
1;
0:
0>
1A
1&
0B
0'
0?
05
1(
0<
06
04
0*
#405000
1#
13
1)
#410000
0#
b1001 "
12
03
1)
18
#415000
1#
13
0)
19
16
0(
1<
15
1'
#420000
0#
b1010 "
11
02
03
0)
09
08
0;
1:
0(
0<
06
#425000
1#
13
1)
#430000
0#
b1011 "
12
03
1)
18
#435000
1#
13
0)
19
16
1(
#440000
0#
b1100 "
10
01
02
03
0)
09
08
1;
0:
1>
1'
0?
05
1(
0<
06
#445000
1#
13
1)
#450000
0#
b1101 "
12
03
1)
18
#455000
1#
13
0)
19
16
0(
1<
15
0'
1?
14
0&
1B
1*
#460000
0#
b1110 "
11
02
03
0)
09
08
0;
1:
0(
0<
06
#465000
1#
13
1)
#470000
0#
b1111 "
12
03
1)
18
#475000
1#
13
0)
19
16
1(
#480000
0#
b0 "
b11 !
1.
0/
00
01
02
03
1)
09
1;
0:
0>
0A
0&
0B
0'
0?
05
1(
0<
06
04
0*
#485000
1#
13
0)
19
16
0(
1<
15
1'
#490000
0#
b1 "
12
03
0)
09
08
17
#495000
1#
13
1)
#500000
0#
b10 "
11
02
03
1)
18
07
0;
1:
0(
0<
06
#505000
1#
13
0)
19
16
1(
#510000
0#
b11 "
12
03
0)
09
08
17
#515000
1#
13
1)
#520000
0#
b100 "
10
01
02
03
1)
18
07
1;
0:
1>
1'
0?
05
1(
0<
06
#525000
1#
13
0)
19
16
0(
1<
15
0'
1?
14
1&
#530000
0#
b101 "
12
03
0)
09
08
17
#535000
1#
13
1)
#540000
0#
b110 "
11
02
03
1)
18
07
0;
1:
0(
0<
06
#545000
1#
13
0)
19
16
1(
#550000
0#
b111 "
12
03
0)
09
08
17
#555000
1#
13
1)
#560000
0#
b1000 "
1/
00
01
02
03
1)
18
07
1;
0:
0>
1A
1&
0B
0'
0?
05
1(
0<
06
04
0*
#565000
1#
13
0)
19
16
0(
1<
15
1'
#570000
0#
b1001 "
12
03
0)
09
08
17
#575000
1#
13
1)
#580000
0#
b1010 "
11
02
03
1)
18
07
0;
1:
0(
0<
06
#585000
1#
13
0)
19
16
1(
#590000
0#
b1011 "
12
03
0)
09
08
17
#595000
1#
13
1)
#600000
0#
b1100 "
10
01
02
03
1)
18
07
1;
0:
1>
1'
0?
05
1(
0<
06
#605000
1#
13
0)
19
16
0(
1<
15
0'
1?
14
0&
1B
1*
#610000
0#
b1101 "
12
03
0)
09
08
17
#615000
1#
13
1)
#620000
0#
b1110 "
11
02
03
1)
18
07
0;
1:
0(
0<
06
#625000
1#
13
0)
19
16
1(
#630000
0#
b1111 "
12
03
0)
09
08
17
#635000
1#
13
1)
#640000
0#
b0 "
b100 !
1,
0-
0.
0/
00
01
02
03
0)
0A
07
0:
05
06
0&
0B
0*
0(
1'
0?
04
#645000
1#
13
1)
#650000
0#
b1 "
12
03
1)
18
#655000
1#
13
0)
19
16
1(
#660000
0#
b10 "
11
02
03
0)
09
08
1;
1(
0<
06
#665000
1#
13
1)
#670000
0#
b11 "
12
03
1)
18
#675000
1#
13
0)
19
16
0(
1<
15
0'
1?
14
1&
#680000
0#
b100 "
10
01
02
03
0)
09
08
0;
0>
1=
0'
0?
0(
0<
06
05
#685000
1#
13
1)
#690000
0#
b101 "
12
03
1)
18
#695000
1#
13
0)
19
16
1(
#700000
0#
b110 "
11
02
03
0)
09
08
1;
1(
0<
06
#705000
1#
13
1)
#710000
0#
b111 "
12
03
1)
18
#715000
1#
13
0)
19
16
0(
1<
15
1'
#720000
0#
b1000 "
1/
00
01
02
03
0)
09
08
0;
1>
0=
1A
1&
0B
04
1'
0?
0(
0<
06
05
0*
#725000
1#
13
1)
#730000
0#
b1001 "
12
03
1)
18
#735000
1#
13
0)
19
16
1(
#740000
0#
b1010 "
11
02
03
0)
09
08
1;
1(
0<
06
#745000
1#
13
1)
#750000
0#
b1011 "
12
03
1)
18
#755000
1#
13
0)
19
16
0(
1<
15
0'
1?
14
0&
1B
1*
#760000
0#
b1100 "
10
01
02
03
0)
09
08
0;
0>
1=
0'
0?
0(
0<
06
05
#765000
1#
13
1)
#770000
0#
b1101 "
12
03
1)
18
#775000
1#
13
0)
19
16
1(
#780000
0#
b1110 "
11
02
03
0)
09
08
1;
1(
0<
06
#785000
1#
13
1)
#790000
0#
b1111 "
12
03
1)
18
#795000
1#
13
0)
19
16
0(
1<
15
1'
#800000
0#
b0 "
b101 !
1.
0/
00
01
02
03
1)
09
0;
1>
0=
0A
0&
0B
04
1'
0?
0(
0<
06
05
0*
#805000
1#
13
0)
19
16
1(
#810000
0#
b1 "
12
03
0)
09
08
17
#815000
1#
13
1)
#820000
0#
b10 "
11
02
03
1)
18
07
1;
1(
0<
06
#825000
1#
13
0)
19
16
0(
1<
15
0'
1?
14
1&
#830000
0#
b11 "
12
03
0)
09
08
17
#835000
1#
13
1)
#840000
0#
b100 "
10
01
02
03
1)
18
07
0;
0>
1=
0'
0?
0(
0<
06
05
#845000
1#
13
0)
19
16
1(
#850000
0#
b101 "
12
03
0)
09
08
17
#855000
1#
13
1)
#860000
0#
b110 "
11
02
03
1)
18
07
1;
1(
0<
06
#865000
1#
13
0)
19
16
0(
1<
15
1'
#870000
0#
b111 "
12
03
0)
09
08
17
#875000
1#
13
1)
#880000
0#
b1000 "
1/
00
01
02
03
1)
18
07
0;
1>
0=
1A
1&
0B
04
1'
0?
0(
0<
06
05
0*
#885000
1#
13
0)
19
16
1(
#890000
0#
b1001 "
12
03
0)
09
08
17
#895000
1#
13
1)
#900000
0#
b1010 "
11
02
03
1)
18
07
1;
1(
0<
06
#905000
1#
13
0)
19
16
0(
1<
15
0'
1?
14
0&
1B
1*
#910000
0#
b1011 "
12
03
0)
09
08
17
#915000
1#
13
1)
#920000
0#
b1100 "
10
01
02
03
1)
18
07
0;
0>
1=
0'
0?
0(
0<
06
05
#925000
1#
13
0)
19
16
1(
#930000
0#
b1101 "
12
03
0)
09
08
17
#935000
1#
13
1)
#940000
0#
b1110 "
11
02
03
1)
18
07
1;
1(
0<
06
#945000
1#
13
0)
19
16
0(
1<
15
1'
#950000
0#
b1111 "
12
03
0)
09
08
17
#955000
1#
13
1)
#960000
0#
b0 "
b110 !
1-
0.
0/
00
01
02
03
0)
1>
0=
0A
07
06
0&
0B
04
1'
0?
0*
1(
0<
05
#965000
1#
13
1)
#970000
0#
b1 "
12
03
1)
18
#975000
1#
13
0)
19
16
0(
1<
15
0'
1?
14
1&
#980000
0#
b10 "
11
02
03
0)
09
08
0;
1:
0(
0<
06
#985000
1#
13
1)
#990000
0#
b11 "
12
03
1)
18
#995000
1#
13
0)
19
16
1(
#1000000
0#
b100 "
10
01
02
03
0)
09
08
1;
0:
0>
1=
0'
0?
05
1(
0<
06
#1005000
1#
13
1)
#1010000
0#
b101 "
12
03
1)
18
#1015000
1#
13
0)
19
16
0(
1<
15
1'
#1020000
0#
b110 "
11
02
03
0)
09
08
0;
1:
0(
0<
06
#1025000
1#
13
1)
#1030000
0#
b111 "
12
03
1)
18
#1035000
1#
13
0)
19
16
1(
#1040000
0#
b1000 "
1/
00
01
02
03
0)
09
08
1;
0:
1>
0=
1A
1&
0B
04
1'
0?
05
1(
0<
06
#1045000
1#
13
1)
#1050000
0#
b1001 "
12
03
1)
18
#1055000
1#
13
0)
19
16
0(
1<
15
0'
1?
14
0&
1B
1*
#1060000
0#
b1010 "
11
02
03
0)
09
08
0;
1:
0(
0<
06
#1065000
1#
13
1)
#1070000
0#
b1011 "
12
03
1)
18
#1075000
1#
13
0)
19
16
1(
#1080000
0#
b1100 "
10
01
02
03
0)
09
08
1;
0:
0>
1=
0'
0?
05
1(
0<
06
#1085000
1#
13
1)
#1090000
0#
b1101 "
12
03
1)
18
#1095000
1#
13
0)
19
16
0(
1<
15
1'
#1100000
0#
b1110 "
11
02
03
0)
09
08
0;
1:
0(
0<
06
#1105000
1#
13
1)
#1110000
0#
b1111 "
12
03
1)
18
#1115000
1#
13
0)
19
16
1(
#1120000
0#
b0 "
b111 !
1.
0/
00
01
02
03
1)
09
1;
0:
1>
0=
0A
0&
0B
04
1'
0?
05
1(
0<
06
0*
#1125000
1#
13
0)
19
16
0(
1<
15
0'
1?
14
1&
#1130000
0#
b1 "
12
03
0)
09
08
17
#1135000
1#
13
1)
#1140000
0#
b10 "
11
02
03
1)
18
07
0;
1:
0(
0<
06
#1145000
1#
13
0)
19
16
1(
#1150000
0#
b11 "
12
03
0)
09
08
17
#1155000
1#
13
1)
#1160000
0#
b100 "
10
01
02
03
1)
18
07
1;
0:
0>
1=
0'
0?
05
1(
0<
06
#1165000
1#
13
0)
19
16
0(
1<
15
1'
#1170000
0#
b101 "
12
03
0)
09
08
17
#1175000
1#
13
1)
#1180000
0#
b110 "
11
02
03
1)
18
07
0;
1:
0(
0<
06
#1185000
1#
13
0)
19
16
1(
#1190000
0#
b111 "
12
03
0)
09
08
17
#1195000
1#
13
1)
#1200000
0#
b1000 "
1/
00
01
02
03
1)
18
07
1;
0:
1>
0=
1A
1&
0B
04
1'
0?
05
1(
0<
06
#1205000
1#
13
0)
19
16
0(
1<
15
0'
1?
14
0&
1B
1*
#1210000
0#
b1001 "
12
03
0)
09
08
17
#1215000
1#
13
1)
#1220000
0#
b1010 "
11
02
03
1)
18
07
0;
1:
0(
0<
06
#1225000
1#
13
0)
19
16
1(
#1230000
0#
b1011 "
12
03
0)
09
08
17
#1235000
1#
13
1)
#1240000
0#
b1100 "
10
01
02
03
1)
18
07
1;
0:
0>
1=
0'
0?
05
1(
0<
06
#1245000
1#
13
0)
19
16
0(
1<
15
1'
#1250000
0#
b1101 "
12
03
0)
09
08
17
#1255000
1#
13
1)
#1260000
0#
b1110 "
11
02
03
1)
18
07
0;
1:
0(
0<
06
#1265000
1#
13
0)
19
16
1(
#1270000
0#
b1111 "
12
03
0)
09
08
17
#1275000
1#
13
1)
#1280000
0#
b0 "
b1000 !
1+
0,
0-
0.
0/
00
01
02
03
0)
07
0:
0=
04
05
06
0(
0'
1&
0B
0*
#1285000
1#
13
1)
#1290000
0#
b1 "
12
03
1)
18
#1295000
1#
13
0)
19
16
1(
#1300000
0#
b10 "
11
02
03
0)
09
08
1;
1(
0<
06
#1305000
1#
13
1)
#1310000
0#
b11 "
12
03
1)
18
#1315000
1#
13
0)
19
16
0(
1<
15
1'
#1320000
0#
b100 "
10
01
02
03
0)
09
08
0;
1>
1'
0?
0(
0<
06
05
04
1&
0B
0*
#1325000
1#
13
1)
#1330000
0#
b101 "
12
03
1)
18
#1335000
1#
13
0)
19
16
1(
#1340000
0#
b110 "
11
02
03
0)
09
08
1;
1(
0<
06
#1345000
1#
13
1)
#1350000
0#
b111 "
12
03
1)
18
#1355000
1#
13
0)
19
16
0(
1<
15
0'
1?
14
0&
1B
1*
#1360000
0#
b1000 "
1/
00
01
02
03
0)
09
08
0;
0>
0A
1@
0&
0B
0'
0?
0(
0<
06
05
04
#1365000
1#
13
1)
#1370000
0#
b1001 "
12
03
1)
18
#1375000
1#
13
0)
19
16
1(
#1380000
0#
b1010 "
11
02
03
0)
09
08
1;
1(
0<
06
#1385000
1#
13
1)
#1390000
0#
b1011 "
12
03
1)
18
#1395000
1#
13
0)
19
16
0(
1<
15
1'
#1400000
0#
b1100 "
10
01
02
03
0)
09
08
0;
1>
1'
0?
0(
0<
06
05
04
0&
#1405000
1#
13
1)
#1410000
0#
b1101 "
12
03
1)
18
#1415000
1#
13
0)
19
16
1(
#1420000
0#
b1110 "
11
02
03
0)
09
08
1;
1(
0<
06
#1425000
1#
13
1)
#1430000
0#
b1111 "
12
03
1)
18
#1435000
1#
13
0)
19
16
0(
1<
15
0'
1?
14
1&
#1440000
0#
b0 "
b1001 !
1.
0/
00
01
02
03
1)
09
0;
0>
1A
0@
0*
1&
0B
0'
0?
0(
0<
06
05
04
#1445000
1#
13
0)
19
16
1(
#1450000
0#
b1 "
12
03
0)
09
08
17
#1455000
1#
13
1)
#1460000
0#
b10 "
11
02
03
1)
18
07
1;
1(
0<
06
#1465000
1#
13
0)
19
16
0(
1<
15
1'
#1470000
0#
b11 "
12
03
0)
09
08
17
#1475000
1#
13
1)
#1480000
0#
b100 "
10
01
02
03
1)
18
07
0;
1>
1'
0?
0(
0<
06
05
04
1&
0B
0*
#1485000
1#
13
0)
19
16
1(
#1490000
0#
b101 "
12
03
0)
09
08
17
#1495000
1#
13
1)
#1500000
0#
b110 "
11
02
03
1)
18
07
1;
1(
0<
06
#1505000
1#
13
0)
19
16
0(
1<
15
0'
1?
14
0&
1B
1*
#1510000
0#
b111 "
12
03
0)
09
08
17
#1515000
1#
13
1)
#1520000
0#
b1000 "
1/
00
01
02
03
1)
18
07
0;
0>
0A
1@
0&
0B
0'
0?
0(
0<
06
05
04
#1525000
1#
13
0)
19
16
1(
#1530000
0#
b1001 "
12
03
0)
09
08
17
#1535000
1#
13
1)
#1540000
0#
b1010 "
11
02
03
1)
18
07
1;
1(
0<
06
#1545000
1#
13
0)
19
16
0(
1<
15
1'
#1550000
0#
b1011 "
12
03
0)
09
08
17
#1555000
1#
13
1)
#1560000
0#
b1100 "
10
01
02
03
1)
18
07
0;
1>
1'
0?
0(
0<
06
05
04
0&
#1565000
1#
13
0)
19
16
1(
#1570000
0#
b1101 "
12
03
0)
09
08
17
#1575000
1#
13
1)
#1580000
0#
b1110 "
11
02
03
1)
18
07
1;
1(
0<
06
#1585000
1#
13
0)
19
16
0(
1<
15
0'
1?
14
1&
#1590000
0#
b1111 "
12
03
0)
09
08
17
#1595000
1#
13
1)
#1600000
0#
b0 "
b1010 !
1-
0.
0/
00
01
02
03
0)
0>
1A
0@
07
06
0*
1&
0B
0'
0?
04
1(
0<
05
#1605000
1#
13
1)
#1610000
0#
b1 "
12
03
1)
18
#1615000
1#
13
0)
19
16
0(
1<
15
1'
#1620000
0#
b10 "
11
02
03
0)
09
08
0;
1:
0(
0<
06
#1625000
1#
13
1)
#1630000
0#
b11 "
12
03
1)
18
#1635000
1#
13
0)
19
16
1(
#1640000
0#
b100 "
10
01
02
03
0)
09
08
1;
0:
1>
1'
0?
05
1(
0<
06
#1645000
1#
13
1)
#1650000
0#
b101 "
12
03
1)
18
#1655000
1#
13
0)
19
16
0(
1<
15
0'
1?
14
0&
1B
1*
#1660000
0#
b110 "
11
02
03
0)
09
08
0;
1:
0(
0<
06
#1665000
1#
13
1)
#1670000
0#
b111 "
12
03
1)
18
#1675000
1#
13
0)
19
16
1(
#1680000
0#
b1000 "
1/
00
01
02
03
0)
09
08
1;
0:
0>
0A
1@
0&
0B
0'
0?
05
1(
0<
06
04
#1685000
1#
13
1)
#1690000
0#
b1001 "
12
03
1)
18
#1695000
1#
13
0)
19
16
0(
1<
15
1'
#1700000
0#
b1010 "
11
02
03
0)
09
08
0;
1:
0(
0<
06
#1705000
1#
13
1)
#1710000
0#
b1011 "
12
03
1)
18
#1715000
1#
13
0)
19
16
1(
#1720000
0#
b1100 "
10
01
02
03
0)
09
08
1;
0:
1>
1'
0?
05
1(
0<
06
#1725000
1#
13
1)
#1730000
0#
b1101 "
12
03
1)
18
#1735000
1#
13
0)
19
16
0(
1<
15
0'
1?
14
1&
#1740000
0#
b1110 "
11
02
03
0)
09
08
0;
1:
0(
0<
06
#1745000
1#
13
1)
#1750000
0#
b1111 "
12
03
1)
18
#1755000
1#
13
0)
19
16
1(
#1760000
0#
b0 "
b1011 !
1.
0/
00
01
02
03
1)
09
1;
0:
0>
1A
0@
0*
1&
0B
0'
0?
05
1(
0<
06
04
#1765000
1#
13
0)
19
16
0(
1<
15
1'
#1770000
0#
b1 "
12
03
0)
09
08
17
#1775000
1#
13
1)
#1780000
0#
b10 "
11
02
03
1)
18
07
0;
1:
0(
0<
06
#1785000
1#
13
0)
19
16
1(
#1790000
0#
b11 "
12
03
0)
09
08
17
#1795000
1#
13
1)
#1800000
0#
b100 "
10
01
02
03
1)
18
07
1;
0:
1>
1'
0?
05
1(
0<
06
#1805000
1#
13
0)
19
16
0(
1<
15
0'
1?
14
0&
1B
1*
#1810000
0#
b101 "
12
03
0)
09
08
17
#1815000
1#
13
1)
#1820000
0#
b110 "
11
02
03
1)
18
07
0;
1:
0(
0<
06
#1825000
1#
13
0)
19
16
1(
#1830000
0#
b111 "
12
03
0)
09
08
17
#1835000
1#
13
1)
#1840000
0#
b1000 "
1/
00
01
02
03
1)
18
07
1;
0:
0>
0A
1@
0&
0B
0'
0?
05
1(
0<
06
04
#1845000
1#
13
0)
19
16
0(
1<
15
1'
#1850000
0#
b1001 "
12
03
0)
09
08
17
#1855000
1#
13
1)
#1860000
0#
b1010 "
11
02
03
1)
18
07
0;
1:
0(
0<
06
#1865000
1#
13
0)
19
16
1(
#1870000
0#
b1011 "
12
03
0)
09
08
17
#1875000
1#
13
1)
#1880000
0#
b1100 "
10
01
02
03
1)
18
07
1;
0:
1>
1'
0?
05
1(
0<
06
#1885000
1#
13
0)
19
16
0(
1<
15
0'
1?
14
1&
#1890000
0#
b1101 "
12
03
0)
09
08
17
#1895000
1#
13
1)
#1900000
0#
b1110 "
11
02
03
1)
18
07
0;
1:
0(
0<
06
#1905000
1#
13
0)
19
16
1(
#1910000
0#
b1111 "
12
03
0)
09
08
17
#1915000
1#
13
1)
#1920000
0#
b0 "
b1100 !
1,
0-
0.
0/
00
01
02
03
0)
1A
0@
07
0:
05
06
0*
1&
0B
0(
1'
0?
04
#1925000
1#
13
1)
#1930000
0#
b1 "
12
03
1)
18
#1935000
1#
13
0)
19
16
1(
#1940000
0#
b10 "
11
02
03
0)
09
08
1;
1(
0<
06
#1945000
1#
13
1)
#1950000
0#
b11 "
12
03
1)
18
#1955000
1#
13
0)
19
16
0(
1<
15
0'
1?
14
0&
1B
1*
#1960000
0#
b100 "
10
01
02
03
0)
09
08
0;
0>
1=
0'
0?
0(
0<
06
05
#1965000
1#
13
1)
#1970000
0#
b101 "
12
03
1)
18
#1975000
1#
13
0)
19
16
1(
#1980000
0#
b110 "
11
02
03
0)
09
08
1;
1(
0<
06
#1985000
1#
13
1)
#1990000
0#
b111 "
12
03
1)
18
#1995000
1#
13
0)
19
16
0(
1<
15
1'
#2000000
0#
b1000 "
1/
00
01
02
03
0)
09
08
0;
1>
0=
0A
1@
0&
0B
04
1'
0?
0(
0<
06
05
#2005000
1#
13
1)
#2010000
0#
b1001 "
12
03
1)
18
#2015000
1#
13
0)
19
16
1(
#2020000
0#
b1010 "
11
02
03
0)
09
08
1;
1(
0<
06
#2025000
1#
13
1)
#2030000
0#
b1011 "
12
03
1)
18
#2035000
1#
13
0)
19
16
0(
1<
15
0'
1?
14
1&
#2040000
0#
b1100 "
10
01
02
03
0)
09
08
0;
0>
1=
0'
0?
0(
0<
06
05
#2045000
1#
13
1)
#2050000
0#
b1101 "
12
03
1)
18
#2055000
1#
13
0)
19
16
1(
#2060000
0#
b1110 "
11
02
03
0)
09
08
1;
1(
0<
06
#2065000
1#
13
1)
#2070000
0#
b1111 "
12
03
1)
18
#2075000
1#
13
0)
19
16
0(
1<
15
1'
#2080000
0#
b0 "
b1101 !
1.
0/
00
01
02
03
1)
09
0;
1>
0=
1A
0@
0*
1&
0B
04
1'
0?
0(
0<
06
05
#2085000
1#
13
0)
19
16
1(
#2090000
0#
b1 "
12
03
0)
09
08
17
#2095000
1#
13
1)
