lab4/lsc_basic/4-3/Lab4_Many_To_One_LFSR.v
`timescale 1ns/1ps

module Many_To_One_LFSR(clk, rst_n, out);

    input clk;
    input rst_n;
    output reg [8-1:0] out;

    wire tmp1, tmp2, in;

    xor x0(tmp1, out[7], out[3]);
    xor x1(tmp2, out[1], out[2]);
    xor x2(in, tmp1, tmp2);

    always @(posedge clk) begin
        if (!rst_n) begin
            out <= 8'b10111101;
        end else begin
            out[0] <= in;
            out[1] <= out[0];
            out[2] <= out[1];
            out[3] <= out[2];
            out[4] <= out[3];
            out[5] <= out[4];
            out[6] <= out[5];
            out[7] <= out[6];
        end
    end

endmodule

lab4/lsc_basic/4-3/Many_To_One_LFSR_t.v
`timescale 1ns/1ps

module Many_To_One_LFSR_t;
reg clk = 0;
reg rst_n = 1;
wire [7:0] out;

// specify duration of a clock cycle.
parameter cyc = 10;

// generate clock.
always#(cyc/2)clk = !clk;

Many_To_One_LFSR m21lfsr(
    .clk(clk),
    .rst_n(rst_n),
    .out(out)
);

// uncommment and add "+access+r" to your nverilog command to dump fsdb waveform on NTHUCAD
 initial begin
     $dumpfile("Many_To_One_LFSR.vcd");
     $dumpvars("+all");
 end

initial begin
    @(negedge clk)
    rst_n = 1'b0;
    @(negedge clk)
    rst_n = 1'b1;
    #(cyc * 16)
    $finish;
end
endmodule

lab4/lsc_basic/4-3/Many_To_One_LFSR.vcd
$date
    Nov  1, 2022  20:45:00
$end
$version
    TOOL:	ncsim	15.20-s039
$end
$timescale
    1 ps
$end

$scope module Many_To_One_LFSR_t $end
$var reg       1 !    clk  $end
$var reg       1 "    rst_n  $end
$var wire      8 #    out [7:0] $end
$var parameter 32 $    cyc  $end

$scope module m21lfsr $end
$var wire      1 %    clk  $end
$var wire      1 &    rst_n  $end
$var reg       8 '    out [7:0] $end
$var wire      1 (    tmp1  $end
$var wire      1 )    tmp2  $end
$var wire      1 *    in  $end
$upscope $end

$upscope $end

$enddefinitions $end
$dumpvars
b1010 $
0!
1"
bx #
0%
1&
bx '
x(
x)
x*
$end
#5000
1!
1%
#10000
0!
0"
0&
0%
#15000
1!
1%
b10111101 '
b10111101 #
1)
0(
1*
#20000
0!
1"
1&
0%
#25000
1!
1%
b10111111 '
b10111011 '
b11111011 '
b1111011 '
b1111011 #
1(
0*
#30000
0!
0%
#35000
1!
1%
b1111010 '
b1111110 '
b1110110 '
b11110110 '
b11110110 #
0)
1*
#40000
0!
0%
#45000
1!
1%
b11110111 '
b11110101 '
b11111101 '
b11101101 '
b11101101 #
1)
0(
#50000
0!
0%
#55000
1!
1%
b11101111 '
b11101011 '
b11111011 '
b11011011 '
b11011011 #
#60000
0!
0%
#65000
1!
1%
b11011111 '
b11010111 '
b11110111 '
b10110111 '
b10110111 #
0)
1(
#70000
0!
0%
#75000
1!
1%
b10111111 '
b10101111 '
b11101111 '
b1101111 '
b1101111 #
#80000
0!
0%
#85000
1!
1%
b1111111 '
b1011111 '
b11011111 '
b11011111 #
0(
0*
#90000
0!
0%
#95000
1!
1%
b11011110 '
b11111110 '
b10111110 '
b10111110 #
#100000
0!
0%
#105000
1!
1%
b10111100 '
b11111100 '
b1111100 '
b1111100 #
1)
1(
#110000
0!
0%
#115000
1!
1%
b1111000 '
b11111000 '
b11111000 #
0)
0(
#120000
0!
0%
#125000
1!
1%
b11110000 '
b11110000 #
1(
1*
#130000
0!
0%
#135000
1!
1%
b11110001 '
b11100001 '
b11100001 #
#140000
0!
0%
#145000
1!
1%
b11100011 '
b11000011 '
b11000011 #
1)
0*
#150000
0!
0%
#155000
1!
1%
b11000010 '
b11000110 '
b10000110 '
b10000110 #
0)
1*
#160000
0!
0%
#165000
1!
1%
b10000111 '
b10000101 '
b10001101 '
b1101 '
b1101 #
1)
0*
#170000
0!
0%
#175000
1!
1%
b1100 '
b1110 '
b1010 '
b11010 '
b11010 #
