lab4/lsc_basic/4-2/Lab4_Mealy.v
`timescale 1ns/1ps

module Mealy (clk, rst_n, in, out, state);

    input clk, rst_n;
    input in;
    output out;
    output [3-1:0] state;

    parameter S0 = 3'b000;
    parameter S1 = 3'b001;
    parameter S2 = 3'b010;
    parameter S3 = 3'b011;
    parameter S4 = 3'b100;
    parameter S5 = 3'b101;

    reg [3-1:0] next_state, state;
    reg out;

    always @(posedge clk) begin
        if (!rst_n) begin
            state <= S0;
        end else begin
            state <= next_state;
        end
    end

    always @(*) begin
        case (state)
            S0 : begin
                if (in) begin
                    out = 1;
                    next_state = S2;
                end else begin
                    out = 0;
                    next_state = S0;
                end
            end
            S1 : begin
                if (in) begin
                    out = 1;
                    next_state = S4;
                end else begin
                    out = 1;
                    next_state = S0;
                end
            end
            S2 : begin
                if (in) begin
                    out = 0;
                    next_state = S1;
                end else begin
                    out = 1;
                    next_state = S5;
                end
            end
            S3 : begin
                if (in) begin
                    out = 0;
                    next_state = S2;
                end else begin
                    out = 1;
                    next_state = S3;
                end
            end
            S4 : begin
                if (in) begin
                    out = 1;
                    next_state = S4;
                end else begin
                    out = 1;
                    next_state = S2;
                end
            end
            S5 : begin
                if (in) begin
                    out = 0;
                    next_state = S4;
                end else begin
                    out = 0;
                    next_state = S3;
                end
            end
        endcase
    end
endmodule

lab4/lsc_basic/4-2/Mealy_t.v
`timescale 1ns/1ps

module Mealy_t;
reg clk = 1'b1;
reg rst_n = 1'b1;
reg in = 1'b0;
wire out;
wire [2:0] state;

// specify duration of a clock cycle.
parameter cyc = 10;

// generate clock.
always #(cyc/2) clk = ~clk;

Mealy m (
    .clk (clk),
    .rst_n (rst_n),
    .in (in),
    .out (out),
    .state (state)
);

// uncommment and add "+access+r" to your nverilog command to dump fsdb waveform on NTHUCAD
 initial begin
     $dumpfile("Mealy.vcd");
     $dumpvars("+all");
 end

initial begin
    @ (negedge clk) rst_n = 1'b0;
    @ (posedge clk) // reset to S0
    @ (negedge clk) rst_n = 1'b1;
    @ (posedge clk) // S0 -0-> S0
    @ (negedge clk) in = 1'b1;
    @ (posedge clk) // S0 -1-> S2
    @ (negedge clk) in = 1'b0;
    @ (posedge clk) // S2 -0-> S5
    @ (negedge clk) in = 1'b1;
    @ (posedge clk) // S5 -1-> S4
    @ (posedge clk) // S4 -1-> S4
    @ (negedge clk) in = 1'b0;
    @ (posedge clk) // S4 -1-> S2
    @ (posedge clk) // S2 -0-> S5
    @ (negedge clk) in = 1'b0;
    @ (posedge clk) // S5-0->S3
    @ (posedge clk) // S3-0->S3
    @ (negedge clk) in = 1'b1;
    @ (posedge clk) // S3-1->S2
    @ (posedge clk) // S2-1->S1
    @ (negedge clk) $finish;
end

endmodule

lab4/lsc_basic/4-2/Mealy.vcd
$date
    Nov  1, 2022  20:29:42
$end
$version
    TOOL:	ncsim	15.20-s039
$end
$timescale
    1 ps
$end

$scope module Mealy_t $end
$var reg       1 !    clk  $end
$var reg       1 "    rst_n  $end
$var reg       1 #    in  $end
$var wire      1 $    out  $end
$var wire      3 %    state [2:0] $end
$var parameter 32 &    cyc  $end

$scope module m $end
$var wire      1 '    clk  $end
$var wire      1 (    rst_n  $end
$var wire      1 )    in  $end
$var reg       1 *    out  $end
$var reg       3 +    state [2:0] $end
$var parameter  3 ,    S0  $end
$var parameter  3 -    S1  $end
$var parameter  3 .    S2  $end
$var parameter  3 /    S3  $end
$var parameter  3 0    S4  $end
$var parameter  3 1    S5  $end
$var reg       3 2    next_state [2:0] $end
$upscope $end

$upscope $end

$enddefinitions $end
$dumpvars
b101 1
b100 0
b11 /
b10 .
b1 -
b0 ,
b1010 &
1!
1"
0#
x$
bx %
1'
1(
0)
x*
bx +
bx 2
$end
#5000
0!
0"
0(
0'
#10000
1!
1'
b0 +
0*
b0 2
0$
b0 %
#15000
0!
1"
1(
0'
#20000
1!
1'
#25000
0!
1#
1)
0'
1*
b10 2
1$
#30000
1!
1'
b10 +
0*
b1 2
0$
b10 %
#35000
0!
0#
0)
0'
1*
b101 2
1$
#40000
1!
1'
b101 +
0*
b11 2
0$
b101 %
#45000
0!
1#
1)
0'
b100 2
#50000
1!
1'
b100 +
1*
1$
b100 %
#55000
0!
0'
#60000
1!
1'
#65000
0!
0#
0)
0'
b10 2
#70000
1!
1'
b10 +
b101 2
b10 %
#75000
0!
0'
#80000
1!
1'
b101 +
0*
b11 2
0$
b101 %
#85000
0!
0'
#90000
1!
1'
b11 +
1*
1$
b11 %
#95000
0!
0'
#100000
1!
1'
#105000
0!
1#
1)
0'
0*
b10 2
0$
#110000
1!
1'
b10 +
b1 2
b10 %
#115000
0!
0'
#120000
1!
1'
b1 +
1*
b100 2
1$
b1 %
