lab5/Lab5_Team25_Sliding_Window_Sequence_Detector/Lab5_Team25_Sliding_Window_Sequence_Detector.v
`timescale 1ns/1ps

module Sliding_Window_Sequence_Detector (clk, rst_n, in, dec);

    input clk, rst_n;
    input in;
    output dec;

    reg [3:0] state, next_state;

    parameter S0 = 4'b0000;
    parameter S1 = 4'b0001;
    parameter S2 = 4'b0010;
    parameter S3 = 4'b0011;
    parameter S4 = 4'b0100;
    parameter S5 = 4'b0101;
    parameter S6 = 4'b0110;
    parameter S7 = 4'b0111;
    parameter S8 = 4'b1000;

    always @(*) begin
        case (state) 
            S0 : begin
                if (in) next_state = S1;
                else next_state = S0;
            end
            S1 : begin
                if (in) next_state = S2;
                else next_state = S0;
            end
            S2 : begin
                if (in) next_state = S3;
                else next_state = S0;
            end
            S3 : begin
                if (in) next_state = S3;
                else next_state = S4;
            end
            S4 : begin
                if (in) next_state = S1;
                else next_state = S5;
            end
            S5 : begin
                if (in) next_state = S6;
                else next_state = S0;
            end
            S6 : begin
                if (in) next_state = S7;
                else next_state = S5;
            end
            S7 : begin
                if (in) next_state = S8;
                else next_state = S0;
            end
            S8 : begin
                if (in) next_state = S3;
                else next_state = S0;
            end
            default : begin
                next_state = S0;
            end
        endcase
    end

    always @(*) begin
        if (state == S7 && in) begin
            dec = 1;
        end else dec = 0;
    end

    always @(posedge clk) begin
        if (!rst_n) begin
            state <= S0;
        end else begin
            state <= next_state;
        end
    end

endmodule

lab5/Lab5_Team25_Sliding_Window_Sequence_Detector/Lab5_Team25_Sliding_Window_Sequence_Detector_t.v
`timescale 1ns/1ps

module q1_t;
    
    reg clk = 0;
    reg rst_n = 0;
    reg in = 0;
    wire dec;

    parameter cyc = 10;
    always # (cyc / 2) clk = ~clk;

    Sliding_Window_Sequence_Detector S1(
        .clk(clk),
        .rst_n(rst_n),
        .in(in),
        .dec(dec)
    );

    initial begin
        $dumpfile("sliding_window.vcd");
        $dumpvars("+all");
    end

    initial begin
        @(negedge clk) 
        rst_n = 0;
        in = 0;
        @(negedge clk) 
        rst_n = 1;
        in = 1;
        @(negedge clk) in = 1;
        @(negedge clk) in = 1;
        @(negedge clk) in = 0;
        @(negedge clk) in = 0;
        @(negedge clk) in = 1;
        @(negedge clk) in = 1;
        @(negedge clk) in = 1;
        @(negedge clk) in = 1;
        @(negedge clk) in = 0;
        @(negedge clk) in = 0;
        @(negedge clk) in = 1;
        @(negedge clk) in = 0;
        @(negedge clk) in = 1;
        @(negedge clk) in = 1;
        @(negedge clk) in = 1;
        @(negedge clk) in = 0;
        @(negedge clk) rst_n = 0;
        @(negedge clk)
        rst_n = 1;
        in = 0;
        @(negedge clk) in = 1;
        @(negedge clk) in = 1;
        @(negedge clk) in = 1;
        @(negedge clk) in = 0;
        @(negedge clk) in = 1;
        @(negedge clk) in = 1;
        @(negedge clk) in = 1;
        @(negedge clk) in = 0;
        @(negedge clk) in = 0;
        @(negedge clk) in = 1;
        @(negedge clk) in = 0;
        @(negedge clk) in = 0;
        @(negedge clk) in = 0;
        @(negedge clk) in = 0;
        @(negedge clk);
        $finish;
    end

endmodule

lab5/Lab5_Team25_Sliding_Window_Sequence_Detector/sliding_window.vcd
$date
    Nov 24, 2022  22:57:10
$end
$version
    TOOL:	ncsim	15.20-s039
$end
$timescale
    1 ps
$end

$scope module q1_t $end
$var reg       1 !    clk  $end
$var reg       1 "    rst_n  $end
$var reg       1 #    in  $end
$var wire      1 $    dec  $end
$var parameter 32 %    cyc  $end

$scope module S1 $end
$var wire      1 &    clk  $end
$var wire      1 '    rst_n  $end
$var wire      1 (    in  $end
$var reg       1 )    dec  $end
$var reg       4 *    state [3:0] $end
$var reg       4 +    next_state [3:0] $end
$var parameter  4 ,    S0  $end
$var parameter  4 -    S1  $end
$var parameter  4 .    S2  $end
$var parameter  4 /    S3  $end
$var parameter  4 0    S4  $end
$var parameter  4 1    S5  $end
$var parameter  4 2    S6  $end
$var parameter  4 3    S7  $end
$var parameter  4 4    S8  $end
$upscope $end

$upscope $end

$enddefinitions $end
$dumpvars
b1000 4
b111 3
b110 2
b101 1
b100 0
b11 /
b10 .
b1 -
b0 ,
b1010 %
0!
0"
0#
0$
0&
0'
0(
0)
bx *
b0 +
$end
#5000
1!
1&
b0 *
#10000
0!
0&
#15000
1!
1&
#20000
0!
1"
1#
1(
1'
0&
b1 +
#25000
1!
1&
b1 *
b10 +
#30000
0!
0&
#35000
1!
1&
b10 *
b11 +
#40000
0!
0&
#45000
1!
1&
b11 *
#50000
0!
0#
0(
0&
b100 +
#55000
1!
1&
b100 *
b101 +
#60000
0!
0&
#65000
1!
1&
b101 *
b0 +
#70000
0!
1#
1(
0&
b110 +
#75000
1!
1&
b110 *
b111 +
#80000
0!
0&
#85000
1!
1&
b111 *
b1000 +
1)
1$
#90000
0!
0&
#95000
1!
1&
b1000 *
b11 +
0)
0$
#100000
0!
0&
#105000
1!
1&
b11 *
#110000
0!
0#
0(
0&
b100 +
#115000
1!
1&
b100 *
b101 +
#120000
0!
0&
#125000
1!
1&
b101 *
b0 +
#130000
0!
1#
1(
0&
b110 +
#135000
1!
1&
b110 *
b111 +
#140000
0!
0#
0(
0&
b101 +
#145000
1!
1&
b101 *
b0 +
#150000
0!
1#
1(
0&
b110 +
#155000
1!
1&
b110 *
b111 +
#160000
0!
0&
#165000
1!
1&
b111 *
b1000 +
1)
1$
#170000
0!
0&
#175000
1!
1&
b1000 *
b11 +
0)
0$
#180000
0!
0&
#185000
1!
1&
b11 *
#190000
0!
0"
0#
0(
0'
0&
b100 +
#195000
1!
1&
b0 *
b0 +
#200000
0!
1"
1'
0&
#205000
1!
1&
#210000
0!
1#
1(
0&
b1 +
#215000
1!
1&
b1 *
b10 +
#220000
0!
0&
#225000
1!
1&
b10 *
b11 +
#230000
0!
0&
#235000
1!
1&
b11 *
#240000
0!
0#
0(
0&
b100 +
#245000
1!
1&
b100 *
b101 +
#250000
0!
1#
1(
0&
b1 +
#255000
1!
1&
b1 *
b10 +
#260000
0!
0&
#265000
1!
1&
b10 *
b11 +
#270000
0!
0&
#275000
1!
1&
b11 *
#280000
0!
0#
0(
0&
b100 +
#285000
1!
1&
b100 *
b101 +
#290000
0!
0&
#295000
1!
1&
b101 *
b0 +
#300000
0!
1#
1(
0&
b110 +
#305000
1!
1&
b110 *
b111 +
#310000
0!
0#
0(
0&
b101 +
#315000
1!
1&
b101 *
b0 +
#320000
0!
0&
#325000
1!
1&
b0 *
#330000
0!
0&
#335000
1!
1&
#340000
0!
1#
1(
0&
b1 +
#345000
1!
1&
b1 *
b10 +
#350000
0!
0&
#355000
1!
1&
b10 *
b11 +
#360000
0!
0&
#365000
1!
1&
b11 *
#370000
0!
0#
0(
0&
b100 +
#375000
1!
1&
b100 *
b101 +
#380000
0!
0&
#385000
1!
1&
b101 *
b0 +
#390000
0!
1#
1(
0&
b110 +
#395000
1!
1&
b110 *
b111 +
#400000
0!
0#
0(
0&
b101 +
#405000
1!
1&
b101 *
b0 +
#410000
0!
1#
1(
0&
b110 +
#415000
1!
1&
b110 *
b111 +
#420000
0!
0#
0(
0&
b101 +
#425000
1!
1&
b101 *
b0 +
#430000
0!
1#
1(
0&
b110 +
#435000
1!
1&
b110 *
b111 +
#440000
0!
0&
#445000
1!
1&
b111 *
b1000 +
1)
1$
#450000
0!
0&
#455000
1!
1&
b1000 *
b11 +
0)
0$
#460000
0!
0&
#465000
1!
1&
b11 *
#470000
0!
0&
#475000
1!
1&
#480000
0!
0&
#485000
1!
1&
#490000
0!
0#
0(
0&
b100 +
#495000
1!
1&
b100 *
b101 +
#500000
0!
0&
#505000
1!
1&
b101 *
b0 +
#510000
0!
1#
1(
0&
b110 +
#515000
1!
1&
b110 *
b111 +
#520000
0!
0#
0(
0&
b101 +
#525000
1!
1&
b101 *
b0 +
#530000
0!
1#
1(
0&
b110 +
#535000
1!
1&
b110 *
b111 +
#540000
0!
0&
#545000
1!
1&
b111 *
b1000 +
1)
1$
#550000
0!
0&
#555000
1!
1&
b1000 *
b11 +
0)
0$
#560000
0!
0#
0(
0&
b100 +
#565000
1!
1&
b100 *
b101 +
#570000
0!
0&
#575000
1!
1&
b101 *
b0 +
#580000
0!
1#
1(
0&
b110 +
#585000
1!
1&
b110 *
b111 +
#590000
0!
0#
0(
0&
b101 +
#595000
1!
1&
b101 *
b0 +
#600000
0!
1#
1(
0&
b110 +
#605000
1!
1&
b110 *
b111 +
#610000
0!
0&
#615000
1!
1&
b111 *
b1000 +
1)
1$
#620000
0!
0#
0(
0&
b0 +
0)
0$
#625000
1!
1&
b0 *
#630000
0!
1#
1(
0&
b1 +
#635000
1!
1&
b1 *
b10 +
#640000
0!
0&
#645000
1!
1&
b10 *
b11 +
#650000
0!
0#
0(
0&
b0 +
#655000
1!
1&
b0 *
#660000
0!
1#
1(
0&
b1 +
#665000
1!
1&
b1 *
b10 +
#670000
0!
0&
#675000
1!
1&
b10 *
b11 +
