lab4/Lab4_Team25_Content_Addressable_Memory.v/Lab4_Team25_Content_Addressable_Memory.v
`timescale 1ns/1ps

module Content_Addressable_Memory(clk, wen, ren, din, addr, dout, hit);

    input clk;
    input wen, ren;
    input [7:0] din;
    input [3:0] addr;
    output [3:0] dout;
    output hit;

    reg [4-1:0] dout, tmp_out;
    reg hit, found, next_hit;
    reg [8-1:0] memory [16-1:0];
    wire [4-1:0] next_dout;
    integer i;

    always @(posedge clk) begin
        if (ren) begin
            if (next_hit) begin
                dout <= tmp_out;  
            end else begin
                dout <= 4'b0;
            end
        end else if (wen) begin
            memory[addr] <= din;
            dout <= 4'b0;
        end else begin
            dout <= 4'b0;
        end
    end

    always @(posedge clk) begin
        hit <= next_hit;
    end

    always @(*) begin
        next_hit = 0;
        found = 0;
        if (ren) begin
            if (memory[0] == din && !found) begin
                next_hit = 1'b1;
                found = 1'b1;
                tmp_out = 0;
            end else if (memory[1] == din && !found) begin
                next_hit = 1'b1;
                found = 1'b1;
                tmp_out = 1;
            end else if (memory[2] == din && !found) begin
                next_hit = 1'b1;
                found = 1'b1;
                tmp_out = 2;
            end else if (memory[3] == din && !found) begin
                next_hit = 1'b1;
                found = 1'b1;
                tmp_out = 3;
            end else if (memory[4] == din && !found) begin
                next_hit = 1'b1;
                found = 1'b1;
                tmp_out = 4;
            end else if (memory[5] == din && !found) begin
                next_hit = 1'b1;
                found = 1'b1;
                tmp_out = 5;
            end else if (memory[6] == din && !found) begin
                next_hit = 1'b1;
                found = 1'b1;
                tmp_out = 6;
            end else if (memory[7] == din && !found) begin
                next_hit = 1'b1;
                found = 1'b1;
                tmp_out = 7;
            end else if (memory[8] == din && !found) begin
                next_hit = 1'b1;
                found = 1'b1;
                tmp_out = 8;
            end else if (memory[9] == din && !found) begin
                next_hit = 1'b1;
                found = 1'b1;
                tmp_out = 9;
            end else if (memory[10] == din && !found) begin
                next_hit = 1'b1;
                found = 1'b1;
                tmp_out = 10;
            end else if (memory[11] == din && !found) begin
                next_hit = 1'b1;
                found = 1'b1;
                tmp_out = 11;
            end else if (memory[12] == din && !found) begin
                next_hit = 1'b1;
                found = 1'b1;
                tmp_out = 12;
            end else if (memory[13] == din && !found) begin
                next_hit = 1'b1;
                found = 1'b1;
                tmp_out = 13;
            end else if (memory[14] == din && !found) begin
                next_hit = 1'b1;
                found = 1'b1;
                tmp_out = 14;
            end else if (memory[15] == din && !found) begin
                next_hit = 1'b1;
                found = 1'b1;
                tmp_out = 15;
            end else begin
                next_hit = next_hit;
                found = found;
                tmp_out = tmp_out;
            end
        end else begin
            next_hit = 1'b0;
            found = 1'b0;
            tmp_out = 4'b0;
        end
    end

endmodule

lab4/Lab4_Team25_Content_Addressable_Memory.v/Lab4_Team25_Content_Addressable_Memory_t.v
`timescale 1ns/1ps

module cam_t;
    
    reg clk = 0;
    reg wen = 0, ren = 0;
    reg [8-1:0] din;
    reg [4-1:0] addr;
    wire [4-1:0] dout;
    wire hit;

    parameter cyc = 10;
    always#(cyc/2)clk = ~clk;

    Content_Addressable_Memory mq(
        .clk(clk),
        .wen(wen),
        .ren(ren),
        .din(din),
        .addr(addr),
        .dout(dout),
        .hit(hit)
    );

    initial begin
        $dumpfile("cam.vcd");
        $dumpvars("+all");
    end

    initial begin
        @(negedge clk)
        wen = 0;
        ren = 0;
        din = 0;
        addr = 0;
        @(negedge clk)
        ren = 0;
        wen = 1;
        din = 4;
        addr = 0;
        @(negedge clk)
        ren = 0;
        wen = 1;
        din = 8;
        addr = 7;
        @(negedge clk)
        ren = 0;
        wen = 1;
        din = 35;
        addr = 15;
        @(negedge clk)
        ren = 0;
        wen = 1;
        din = 8;
        addr = 9;
        @(negedge clk)
        ren = 0;
        wen = 0;
        din = 0;
        addr = 0;
        @(negedge clk)
        ren = 0;
        wen = 0;
        din = 0;
        addr = 0;
        @(negedge clk)
        ren = 1;
        wen = 0;
        din = 4;
        addr = 0;
        @(negedge clk)
        ren = 1;
        wen = 1;
        din = 8;
        addr = 0;
        @(negedge clk)
        ren = 1;
        wen = 1;
        din = 35;
        addr = 0;
        @(negedge clk)
        ren = 1;
        wen = 1;
        din = 87;
        addr = 0;
        @(negedge clk)
        ren = 1;
        wen = 1;
        din = 45;
        addr = 0;
        @(negedge clk)
        ren = 0;
        wen = 0;
        @(negedge clk);
        @(negedge clk);
        @(negedge clk) $finish;
    end
endmodule

lab4/Lab4_Team25_Content_Addressable_Memory.v/cam.vcd
$date
    Nov  7, 2022  14:16:12
$end
$version
    TOOL:	ncsim	15.20-s039
$end
$timescale
    1 ps
$end

$scope module cam_t $end
$var reg       1 !    clk  $end
$var reg       1 "    wen  $end
$var reg       1 #    ren  $end
$var reg       8 $    din [7:0] $end
$var reg       4 %    addr [3:0] $end
$var wire      4 &    dout [3:0] $end
$var wire      1 '    hit  $end
$var parameter 32 (    cyc  $end

$scope module mq $end
$var wire      1 )    clk  $end
$var wire      1 *    wen  $end
$var wire      1 +    ren  $end
$var wire      8 ,    din [7:0] $end
$var wire      4 -    addr [3:0] $end
$var reg       4 .    dout [3:0] $end
$var reg       1 /    hit  $end
$var reg       4 0    tmp_out [3:0] $end
$var reg       1 1    found  $end
$var reg       1 2    next_hit  $end
$var wire      4 3    next_dout [3:0] $end
$var integer  32 4    i  $end
$upscope $end

$upscope $end

$enddefinitions $end
$dumpvars
b1010 (
0!
0"
0#
bx $
bx %
bx &
x'
0)
0*
0+
bx ,
bx -
bx .
x/
b0 0
01
02
bz 3
bx 4
$end
#5000
1!
1)
0/
0'
#10000
0!
b0 $
b0 %
b0 -
b0 ,
0)
#15000
1!
1)
#20000
0!
1"
b100 $
b100 ,
1*
0)
#25000
1!
1)
b0 .
b0 &
#30000
0!
b1000 $
b111 %
b111 -
b1000 ,
0)
#35000
1!
1)
#40000
0!
b100011 $
b1111 %
b1111 -
b100011 ,
0)
#45000
1!
1)
#50000
0!
b1000 $
b1001 %
b1001 -
b1000 ,
0)
#55000
1!
1)
#60000
0!
0"
b0 $
b0 %
b0 -
b0 ,
0*
0)
#65000
1!
1)
#70000
0!
0)
#75000
1!
1)
#80000
0!
1#
b100 $
b100 ,
1+
0)
12
11
#85000
1!
1)
1/
1'
#90000
0!
1"
b1000 $
b1000 ,
1*
0)
02
01
12
11
b111 0
#95000
1!
1)
b111 .
b111 &
#100000
0!
b100011 $
b100011 ,
0)
02
01
12
11
b1111 0
#105000
1!
1)
b1111 .
b1111 &
#110000
0!
b1010111 $
b1010111 ,
0)
02
01
#115000
1!
1)
0/
b0 .
b0 &
0'
#120000
0!
b101101 $
b101101 ,
0)
#125000
1!
1)
#130000
0!
0#
0"
0*
0+
0)
b0 0
