lab5/Lab5_Team25_Traffic_Light_Controller/Lab5_Team25_Traffic_Light_Controller.v
`timescale 1ns/1ps

module Traffic_Light_Controller(clk, rst_n, lr_has_car, hw_light, lr_light);

    input clk, rst_n;
    input lr_has_car;
    output [2:0] hw_light;
    output [2:0] lr_light;

    reg [2:0] state, next_state;
    reg [6:0] hg, hg_next, lg, lg_next;
    reg [4:0] hy, hy_next, ly, ly_next;
    reg [2:0] hw_light, lr_light;

    parameter HGLR = 3'b000;
    parameter HYLR = 3'b001;
    parameter HRLR = 3'b010;
    parameter HRLG = 3'b011;
    parameter HRLY = 3'b100;
    parameter HRLR2 = 3'b101;
    parameter RED = 3'b001;
    parameter YEL = 3'b010;
    parameter GRE = 3'b100;
    
    always @(*) begin
        case (state)
            HGLR : begin
                hw_light = GRE;
                lr_light = RED;
            end
            HYLR : begin
                hw_light = YEL;
                lr_light = RED;
            end
            HRLR : begin
                hw_light = RED;
                lr_light = RED;
            end
            HRLG : begin
                hw_light = RED;
                lr_light = GRE;
            end
            HRLY : begin
                hw_light = RED;
                lr_light = YEL;
            end
            HRLR2 : begin
                hw_light = RED;
                lr_light = RED;
            end
            default : begin
                hw_light = GRE;
                lr_light = RED;
            end
        endcase
    end

    always @(*) begin
        case (state)
            HGLR : begin
                hg_next = (hg + 1 > 70) ? 70 : (hg + 1); 
                lg_next = 0;
                hy_next = 0; ly_next = 0;
            end
            HYLR : begin
                hy_next = hy + 1; ly_next = 0;
                hg_next = 0; lg_next = 0;
            end
            HRLG : begin
                lg_next = (lg + 1 > 70) ? 70 : (lg + 1); 
                hg_next = 0;
                ly_next = 0; hy_next = 0;
            end
            HRLY : begin
                ly_next = ly + 1; hy_next = 0;
                lg_next = 0; hg_next = 0;
            end
            default : begin
                hg_next = 0; lg_next = 0;
                hy_next = 0; hy_next = 0;
            end
        endcase
    end

    always @(*) begin
        case (state)
            HGLR : begin
                if (lr_has_car && hg >= 69) begin
                    next_state = HYLR;
                end else next_state = HGLR;
            end
            HYLR : begin
                if (hy == 24) begin
                    next_state = HRLR;
                end else next_state = HYLR;
            end
            HRLR : begin
                next_state = HRLG;
            end
            HRLG : begin
                if (lg == 24) begin
                    next_state = HRLY;
                end else next_state = HRLG;
            end
            HRLY : begin
                if (ly == 1) begin
                    next_state = HRLR2;
                end else next_state = HRLY;
            end
            HRLR2 : begin
                next_state = HGLR;
            end
            default : begin
                next_state = state;
            end
        endcase
    end

    always @(posedge clk) begin
        if (!rst_n) begin
            state <= HGLR;
            hy <= 0; hg <= 0;
            ly <= 0; lg <= 0;
            hw_light <= GRE;
            lr_light <= RED;
        end else begin
            state <= next_state;
            hy <= hy_next; hg <= hg_next;
            ly <= ly_next; lg <= lg_next;
        end
    end

endmodule

lab5/Lab5_Team25_Traffic_Light_Controller/Lab5_Team25_Traffic_Light_Controller_t.v
`timescale 1ns/1ps

module q2_t;
    
    reg clk = 0;
    reg rst_n = 0;
    reg lr_has_car = 0;
    wire [2:0] hw_light, lr_light;

    parameter cyc = 10;

    always # (cyc/2) clk = ~clk;

    Traffic_Light_Controller T1(
        .clk(clk),
        .rst_n(rst_n),
        .lr_has_car(lr_has_car),
        .hw_light(hw_light),
        .lr_light(lr_light)
    );

    initial begin
        $dumpfile("Traffic.vcd");
        $dumpvars("+all");
    end

    initial begin
        @(negedge clk)
        rst_n = 0;
        @(negedge clk)
        rst_n = 1;
        @(negedge clk);
        @(negedge clk);
        @(negedge clk);
        @(negedge clk);
        @(negedge clk);
        @(negedge clk);
        @(negedge clk);
        @(negedge clk);
        @(negedge clk);
        @(negedge clk);
        lr_has_car = 1;
        @(negedge clk);
        @(negedge clk);
        @(negedge clk);
        @(negedge clk);
        @(negedge clk);
        @(negedge clk);
        @(negedge clk);
        @(negedge clk);
        @(negedge clk);
        @(negedge clk);
        @(negedge clk);
        @(negedge clk);
        @(negedge clk);
        @(negedge clk);
        @(negedge clk); 
        @(negedge clk);
        @(negedge clk);
        @(negedge clk);
        @(negedge clk);
        @(negedge clk);
        @(negedge clk);
        @(negedge clk);
        @(negedge clk);
        @(negedge clk);
        @(negedge clk);
        @(negedge clk);
        @(negedge clk);
        @(negedge clk);
        @(negedge clk);
        @(negedge clk);
        @(negedge clk);
        @(negedge clk);
        @(negedge clk);
        @(negedge clk);
        @(negedge clk);
        @(negedge clk);
        @(negedge clk);
        @(negedge clk);
        @(negedge clk);
        lr_has_car = 0;
        @(negedge clk);
        @(negedge clk);
        @(negedge clk);
        @(negedge clk);
        @(negedge clk);
        @(negedge clk);
        @(negedge clk);
        @(negedge clk);
        @(negedge clk);
        @(negedge clk); 
        @(negedge clk);
        @(negedge clk);
        @(negedge clk);
        @(negedge clk);
        @(negedge clk);
        @(negedge clk);
        @(negedge clk);
        @(negedge clk);
        @(negedge clk);  
        @(negedge clk);
        @(negedge clk);
        @(negedge clk);
        @(negedge clk);
        @(negedge clk);
        @(negedge clk);
        @(negedge clk);
        @(negedge clk);
        @(negedge clk);
        @(negedge clk);
        @(negedge clk);
        @(negedge clk);
        @(negedge clk);
        @(negedge clk);
        @(negedge clk);
        @(negedge clk);
        @(negedge clk);
        @(negedge clk);
        @(negedge clk);
        @(negedge clk);
        @(negedge clk);
        @(negedge clk);
        @(negedge clk);
        @(negedge clk);
        @(negedge clk); 
        @(negedge clk);
        @(negedge clk);
        @(negedge clk);
        @(negedge clk);
        @(negedge clk);
        @(negedge clk);
        @(negedge clk);
        @(negedge clk);
        @(negedge clk);
        @(negedge clk);
        @(negedge clk);
        @(negedge clk);
        @(negedge clk);
        @(negedge clk);
        @(negedge clk);
        @(negedge clk);
        @(negedge clk);
        @(negedge clk);
        @(negedge clk);
        @(negedge clk);
        @(negedge clk);
        @(negedge clk);
        @(negedge clk);
        @(negedge clk);
        @(negedge clk);
        @(negedge clk);
        @(negedge clk);
        @(negedge clk);
        @(negedge clk);
        @(negedge clk);
        @(negedge clk);
        @(negedge clk);
        @(negedge clk);
        @(negedge clk); 
        @(negedge clk);
        @(negedge clk);
        @(negedge clk);
        @(negedge clk);
        @(negedge clk);
        @(negedge clk);
        @(negedge clk);
        @(negedge clk);
        @(negedge clk);
        @(negedge clk);
        @(negedge clk);
        @(negedge clk);
        @(negedge clk);
        @(negedge clk);
        @(negedge clk);
        @(negedge clk);
        @(negedge clk);
        @(negedge clk);
        @(negedge clk);
        @(negedge clk);
        @(negedge clk);
        @(negedge clk);
        @(negedge clk);
        @(negedge clk);
        @(negedge clk);
        @(negedge clk);
        @(negedge clk);
        @(negedge clk);
        @(negedge clk);
        @(negedge clk);
        @(negedge clk);
        @(negedge clk);
        @(negedge clk);
        @(negedge clk); 
        @(negedge clk);
        @(negedge clk);
        @(negedge clk);
        @(negedge clk);
        @(negedge clk);
        @(negedge clk);
        @(negedge clk);
        @(negedge clk);
        @(negedge clk);
        @(negedge clk);
        @(negedge clk);
        @(negedge clk);
        @(negedge clk);
        @(negedge clk);
        @(negedge clk);
        @(negedge clk);
        @(negedge clk);
        @(negedge clk);
        $finish;
    end

endmodule

lab5/Lab5_Team25_Traffic_Light_Controller/Traffic.vcd
$date
    Nov 20, 2022  15:00:35
$end
$version
    TOOL:	ncsim	15.20-s039
$end
$timescale
    1 ps
$end

$scope module q2_t $end
$var reg       1 !    clk  $end
$var reg       1 "    rst_n  $end
$var reg       1 #    lr_has_car  $end
$var wire      3 $    hw_light [2:0] $end
$var wire      3 %    lr_light [2:0] $end
$var parameter 32 &    cyc  $end

$scope module T1 $end
$var wire      1 '    clk  $end
$var wire      1 (    rst_n  $end
$var wire      1 )    lr_has_car  $end
$var reg       3 *    hw_light [2:0] $end
$var reg       3 +    lr_light [2:0] $end
$var reg       3 ,    state [2:0] $end
$var reg       3 -    next_state [2:0] $end
$var reg       7 .    hg [6:0] $end
$var reg       7 /    hg_next [6:0] $end
$var reg       7 0    lg [6:0] $end
$var reg       7 1    lg_next [6:0] $end
$var reg       5 2    hy [4:0] $end
$var reg       5 3    hy_next [4:0] $end
$var reg       5 4    ly [4:0] $end
$var reg       5 5    ly_next [4:0] $end
$var parameter  3 6    HGLR  $end
$var parameter  3 7    HYLR  $end
$var parameter  3 8    HRLR  $end
$var parameter  3 9    HRLG  $end
$var parameter  3 :    HRLY  $end
$var parameter  3 ;    HRLR2  $end
$var parameter  3 <    RED  $end
$var parameter  3 =    YEL  $end
$var parameter  3 >    GRE  $end
$upscope $end

$upscope $end

$enddefinitions $end
$dumpvars
b100 >
b10 =
b1 <
b101 ;
b100 :
b11 9
b10 8
b1 7
b0 6
b1010 &
0!
0"
0#
bx $
bx %
0'
0(
0)
bx *
bx +
bx ,
bx -
bx .
bx /
bx 0
bx 1
bx 2
bx 3
bx 4
bx 5
$end
#5000
1!
1'
b0 ,
b0 2
b0 .
b0 4
b0 0
b100 *
b1 +
b1 /
b0 1
b0 3
b0 5
b0 -
b1 %
b100 $
#10000
0!
0'
#15000
1!
1'
#20000
0!
1"
1(
0'
#25000
1!
1'
b1 .
b10 /
#30000
0!
0'
#35000
1!
1'
b10 .
b11 /
#40000
0!
0'
#45000
1!
1'
b11 .
#50000
0!
0'
#55000
1!
1'
#60000
0!
0'
#65000
1!
1'
#70000
0!
0'
#75000
1!
1'
#80000
0!
0'
#85000
1!
1'
#90000
0!
0'
#95000
1!
1'
#100000
0!
0'
#105000
1!
1'
#110000
0!
0'
#115000
1!
1'
#120000
0!
1#
1)
0'
b1 -
#125000
1!
1'
b1 ,
b10 *
b1 3
b0 /
b10 $
#130000
0!
0'
#135000
1!
1'
b1 2
b0 .
b10 3
b10 -
#140000
0!
0'
#145000
1!
1'
b10 ,
b10 2
b1 *
b0 3
b11 -
b1 $
#150000
0!
0'
#155000
1!
1'
b11 ,
b0 2
b100 +
b1 1
b100 %
#160000
0!
0'
#165000
1!
1'
b1 0
b10 1
#170000
0!
0'
#175000
1!
1'
b10 0
b11 1
b100 -
#180000
0!
0'
#185000
1!
1'
b100 ,
b11 0
b10 +
b1 5
b0 1
b10 %
#190000
0!
0'
#195000
1!
1'
b1 4
b0 0
b10 5
b101 -
#200000
0!
0'
#205000
1!
1'
b101 ,
b10 4
b1 +
b0 -
b1 %
#210000
0!
0'
#215000
1!
1'
b0 ,
b100 *
b1 /
b0 5
b100 $
#220000
0!
0'
#225000
1!
1'
b1 .
b0 4
b10 /
#230000
0!
0'
#235000
1!
1'
b10 .
b11 /
b1 -
#240000
0!
0'
#245000
1!
1'
b1 ,
b11 .
b10 *
b1 3
b0 /
b10 $
#250000
0!
0'
#255000
1!
1'
b1 2
b0 .
b10 3
b10 -
#260000
0!
0'
#265000
1!
1'
b10 ,
b10 2
b1 *
b0 3
b11 -
b1 $
#270000
0!
0'
#275000
1!
1'
b11 ,
b0 2
b100 +
b1 1
b100 %
#280000
0!
0'
#285000
1!
1'
b1 0
b10 1
#290000
0!
0'
#295000
1!
1'
b10 0
b11 1
b100 -
#300000
0!
0'
#305000
1!
1'
b100 ,
b11 0
b10 +
b1 5
b0 1
b10 %
#310000
0!
0'
#315000
1!
1'
b1 4
b0 0
b10 5
b101 -
#320000
0!
0'
#325000
1!
1'
b101 ,
b10 4
b1 +
b0 -
b1 %
#330000
0!
0'
#335000
1!
1'
b0 ,
b100 *
b1 /
b0 5
b100 $
#340000
0!
0'
#345000
1!
1'
b1 .
b0 4
b10 /
#350000
0!
0'
#355000
1!
1'
b10 .
b11 /
b1 -
#360000
0!
0'
#365000
1!
1'
b1 ,
b11 .
b10 *
b1 3
b0 /
b10 $
#370000
0!
0'
#375000
1!
1'
b1 2
b0 .
b10 3
b10 -
#380000
0!
0'
#385000
1!
1'
b10 ,
b10 2
b1 *
b0 3
b11 -
b1 $
#390000
0!
0'
#395000
1!
1'
b11 ,
b0 2
b100 +
b1 1
b100 %
#400000
0!
0'
#405000
1!
1'
b1 0
b10 1
#410000
0!
0'
#415000
1!
1'
b10 0
b11 1
b100 -
#420000
0!
0'
#425000
1!
1'
b100 ,
b11 0
b10 +
b1 5
b0 1
b10 %
#430000
0!
0'
#435000
1!
1'
b1 4
b0 0
b10 5
b101 -
#440000
0!
0'
#445000
1!
1'
b101 ,
b10 4
b1 +
b0 -
b1 %
#450000
0!
0'
#455000
1!
1'
b0 ,
b100 *
b1 /
b0 5
b100 $
#460000
0!
0'
#465000
1!
1'
b1 .
b0 4
b10 /
#470000
0!
0'
#475000
1!
1'
b10 .
b11 /
b1 -
#480000
0!
0'
#485000
1!
1'
b1 ,
b11 .
b10 *
b1 3
b0 /
b10 $
#490000
0!
0'
#495000
1!
1'
b1 2
b0 .
b10 3
b10 -
#500000
0!
0'
#505000
1!
1'
b10 ,
b10 2
b1 *
b0 3
b11 -
b1 $
#510000
0!
0#
0)
0'
#515000
1!
1'
b11 ,
b0 2
b100 +
b1 1
b100 %
#520000
0!
0'
#525000
1!
1'
b1 0
b10 1
#530000
0!
0'
#535000
1!
1'
b10 0
b11 1
b100 -
#540000
0!
0'
#545000
1!
1'
b100 ,
b11 0
b10 +
b1 5
b0 1
b10 %
#550000
0!
0'
#555000
1!
1'
b1 4
b0 0
b10 5
b101 -
#560000
0!
0'
#565000
1!
1'
b101 ,
b10 4
b1 +
b0 -
b1 %
#570000
0!
0'
#575000
1!
1'
b0 ,
b100 *
b1 /
b0 5
b100 $
#580000
0!
0'
#585000
1!
1'
b1 .
b0 4
b10 /
#590000
0!
0'
#595000
1!
1'
b10 .
b11 /
#600000
0!
0'
#605000
1!
1'
b11 .
