lab3/Lab3_Team25_Parameterized_Ping_Pong_Counter/Lab3_Team25_Parameterized_Ping_Pong_Counter.v
`timescale 1ns/1ps

module Parameterized_Ping_Pong_Counter (clk, rst_n, enable, flip, max, min, direction, out);
input clk, rst_n;
input enable;
input flip;
input [4-1:0] max;
input [4-1:0] min;
output direction;
output [4-1:0] out;

reg [4-1:0] out;
reg direction;

reg [4-1:0] next_out;
reg next_direction;

always @(*) begin
    if (enable) begin
        if (out > max || out < min || max <= min) begin
            next_out = out;
            next_direction = direction;
        end else begin
            if (out === max && direction === 1'b1) begin
                next_out = out-4'b1;
                next_directoin = ~direction;
            end else if (out === min && direction === 1'b0) begin
                next_out = out+4'b1;
                next_direction = ~direction;
            end else begin
                next_out = direction ? out+4'b1 : out-4'b1;
                if (flip && out > min && out < max) begin
                    next_direction = ~direction;
                end else begin
                    next_direction = direction;
                end
            end
        end
    end else begin
        next_out = out;
        next_direction = direction;
    end
end

always @(posedge clk) begin
    if (~rst_n) begin
        out <= min;
        direction <= 1;
    end 
    else begin
        out <= next_out;
        direction <= next_direction;
    end
end

endmodule

lab3/Lab3_Team25_Parameterized_Ping_Pong_Counter/Lab3_Team31_Parameterized_Ping_Pong_Counter_t.v
`timescale 1ns/1ps
module Parameterized_Ping_Pong_Counter_t;
reg clk = 1'b0;
reg rst_n = 1'b0;
reg enable = 1'b1;
reg flip = 1'b0;
reg [4-1:0] max = 4'd4;
reg [4-1:0] min = 4'd0;
wire direction;
wire [4-1:0] out;
// wire hold;

always#5 clk = ~clk;

Parameterized_Ping_Pong_Counter ppc(
    .clk(clk),
    .rst_n(rst_n),
    .enable(enable),
    .flip(flip),
    .max(max),
    .min(min),
    .direction(direction),
    .out(out)
    // .hold(hold)
);

initial begin
	$dumpfile("tmp.vcd");
	$dumpvars("+all");
end

initial begin
    #10 rst_n = 1'b1;
    #30
    repeat(3)begin
        #3
        flip = 1'b1;
        #10 flip = 1'b0;
    end
    #10 min = 4'd3;
    max = 4'd10;
    #20 
    rst_n = 1'b0;
    enable = 1'b0;
    #10 
    rst_n = 1'b1;
    enable = 1'b1;
    repeat(3)begin
        #15 flip = 1'b1;
        #9 flip = 1'b0;
    end
    #66
    min = 4'd9;
    max = 4'd9; 
    #20
    min = 4'd0;
    max = 15;
    #43 enable = 1'b0;
    #10 enable = 1'b1;
    repeat(2)begin
        #20 flip = 1'b1;
        #10 flip = 1'b0;
    end
    #50
    #10 min = 4'd3;
    #3 
    rst_n = 1'b0;
    enable = 1'b0;
    #5 enable = 1'b1;
    #10 rst_n = 1'b1;
    #10 max = 4'd7;
    #20 flip = 1'b1;
    #10 flip = 1'b0;
    #75 
    max = 4'd5;
    min = 4'd10;
    #25
    max = 4'd12;
    #30
    min = 4'd2;
    #10
    flip = 1'b1;
    #10 flip = 1'b0;
    #165
    min = 4'd8;
    #10
    max = 4'd13;
    #5
    rst_n = 1'b0;
    #10
    rst_n = 1'b1;
    #90
    $finish;
end

endmodule

lab3/Lab3_Team25_Parameterized_Ping_Pong_Counter/tmp.vcd
$date
    Nov  3, 2022  09:01:28
$end
$version
    TOOL:	ncsim	15.20-s039
$end
$timescale
    1 ps
$end

$scope module Parameterized_Ping_Pong_Counter_t $end
$var reg       1 !    clk  $end
$var reg       1 "    rst_n  $end
$var reg       1 #    enable  $end
$var reg       1 $    flip  $end
$var reg       4 %    max [3:0] $end
$var reg       4 &    min [3:0] $end
$var wire      1 '    direction  $end
$var wire      4 (    out [3:0] $end

$scope module ppc $end
$var wire      1 )    clk  $end
$var wire      1 *    rst_n  $end
$var wire      1 +    enable  $end
$var wire      1 ,    flip  $end
$var wire      4 -    max [3:0] $end
$var wire      4 .    min [3:0] $end
$var reg       1 /    direction  $end
$var reg       4 0    out [3:0] $end
$var reg       4 1    next_out [3:0] $end
$var reg       1 2    next_direction  $end
$upscope $end

$upscope $end

$enddefinitions $end
$dumpvars
0!
0"
1#
0$
b100 %
b0 &
x'
bx (
0)
0*
1+
0,
b100 -
b0 .
x/
bx 0
bx 1
x2
$end
#5000
1!
1)
b0 0
1/
b1 1
12
1'
b0 (
#10000
1"
0!
0)
1*
#15000
1!
1)
b1 0
b10 1
b1 (
#20000
0!
0)
#25000
1!
1)
b10 0
b11 1
b10 (
#30000
0!
0)
#35000
1!
1)
b11 0
b100 1
b11 (
#40000
0!
0)
#43000
1$
1,
b10 1
02
#45000
1!
1)
b10 0
0/
b11 1
12
0'
b10 (
#50000
0!
0)
#53000
0$
0,
b1 1
02
#55000
1!
1)
b1 0
b0 1
b1 (
#56000
1$
1,
b10 1
12
#60000
0!
0)
#65000
1!
1)
b10 0
1/
b1 1
02
1'
b10 (
#66000
0$
0,
b11 1
12
#69000
1$
1,
b1 1
02
#70000
0!
0)
#75000
1!
1)
b1 0
0/
b10 1
12
0'
b1 (
#79000
0$
0,
b0 1
02
#80000
0!
0)
#85000
1!
1)
b0 0
b1 1
12
b0 (
#89000
b11 &
b1010 %
b1010 -
b11 .
b0 1
02
#90000
0!
0)
#95000
1!
1)
#100000
0!
0)
#105000
1!
1)
#109000
0"
0#
0+
0*
#110000
0!
0)
#115000
1!
1)
b11 0
1/
b11 1
12
1'
b11 (
#119000
1"
1#
1+
1*
b100 1
#120000
0!
0)
#125000
1!
1)
b100 0
b101 1
b100 (
#130000
0!
0)
#134000
1$
1,
b11 1
02
#135000
1!
1)
b11 0
0/
b100 1
12
0'
b11 (
#140000
0!
0)
#143000
0$
0,
#145000
1!
1)
b100 0
1/
b101 1
1'
b100 (
#150000
0!
0)
#155000
1!
1)
b101 0
b110 1
b101 (
#158000
1$
1,
b100 1
02
#160000
0!
0)
#165000
1!
1)
b100 0
0/
b101 1
12
0'
b100 (
#167000
0$
0,
b11 1
02
#170000
0!
0)
#175000
1!
1)
b11 0
b100 1
12
b11 (
#180000
0!
0)
#182000
1$
1,
#185000
1!
1)
b100 0
1/
b11 1
02
1'
b100 (
#190000
0!
0)
#191000
0$
0,
b101 1
12
#195000
1!
1)
b101 0
b110 1
b101 (
#200000
0!
0)
#205000
1!
1)
b110 0
b111 1
b110 (
#210000
0!
0)
#215000
1!
1)
b111 0
b1000 1
b111 (
#220000
0!
0)
#225000
1!
1)
b1000 0
b1001 1
b1000 (
#230000
0!
0)
#235000
1!
1)
b1001 0
b1010 1
b1001 (
#240000
0!
0)
#245000
1!
1)
b1010 0
b1001 1
02
b1010 (
#250000
0!
0)
#255000
1!
1)
b1001 0
0/
b1000 1
0'
b1001 (
#257000
b1001 &
b1001 %
b1001 -
b1001 .
b1001 1
#260000
0!
0)
#265000
1!
1)
#270000
0!
0)
#275000
1!
1)
#277000
b0 &
b1111 %
b1111 -
b0 .
b1000 1
#280000
0!
0)
#285000
1!
1)
b1000 0
b111 1
b1000 (
#290000
0!
0)
#295000
1!
1)
b111 0
b110 1
b111 (
#300000
0!
0)
#305000
1!
1)
b110 0
b101 1
b110 (
#310000
0!
0)
#315000
1!
1)
b101 0
b100 1
b101 (
#320000
0#
0!
0)
0+
b101 1
#325000
1!
1)
#330000
1#
0!
0)
1+
b100 1
#335000
1!
1)
b100 0
b11 1
b100 (
#340000
0!
0)
#345000
1!
1)
b11 0
b10 1
b11 (
#350000
1$
0!
0)
1,
b100 1
12
#355000
1!
1)
b100 0
1/
b11 1
02
1'
b100 (
#360000
0$
0!
0)
0,
b101 1
12
#365000
1!
1)
b101 0
b110 1
b101 (
#370000
0!
0)
#375000
1!
1)
b110 0
b111 1
b110 (
#380000
1$
0!
0)
1,
b101 1
02
#385000
1!
1)
b101 0
0/
b110 1
12
0'
b101 (
#390000
0$
0!
0)
0,
b100 1
02
#395000
1!
1)
b100 0
b11 1
b100 (
#400000
0!
0)
#405000
1!
1)
b11 0
b10 1
b11 (
#410000
0!
0)
#415000
1!
1)
b10 0
b1 1
b10 (
#420000
0!
0)
#425000
1!
1)
b1 0
b0 1
b1 (
#430000
0!
0)
#435000
1!
1)
b0 0
b1 1
12
b0 (
#440000
0!
0)
#445000
1!
1)
b1 0
1/
b10 1
1'
b1 (
#450000
b11 &
0!
0)
b11 .
b1 1
#453000
0"
0#
0+
0*
#455000
1!
1)
b11 0
b11 1
b11 (
#458000
1#
1+
b100 1
#460000
0!
0)
#465000
1!
1)
#468000
1"
1*
#470000
0!
0)
#475000
1!
1)
b100 0
b101 1
b100 (
#478000
b111 %
b111 -
#480000
0!
0)
#485000
1!
1)
b101 0
b110 1
b101 (
#490000
0!
0)
#495000
1!
1)
b110 0
b111 1
b110 (
#498000
1$
1,
b101 1
02
#500000
0!
0)
#505000
1!
1)
b101 0
0/
b110 1
12
0'
b101 (
#508000
0$
0,
b100 1
02
#510000
0!
0)
#515000
1!
1)
b100 0
b11 1
b100 (
#520000
0!
0)
#525000
1!
1)
b11 0
b100 1
12
b11 (
#530000
0!
0)
#535000
1!
1)
b100 0
1/
b101 1
1'
b100 (
#540000
0!
0)
#545000
1!
1)
b101 0
b110 1
b101 (
#550000
0!
0)
#555000
1!
1)
b110 0
b111 1
b110 (
#560000
0!
0)
#565000
1!
1)
b111 0
b110 1
02
b111 (
#570000
0!
0)
#575000
1!
1)
b110 0
0/
b101 1
0'
b110 (
#580000
0!
0)
#583000
b101 %
b1010 &
b1010 .
b101 -
b110 1
#585000
1!
1)
#590000
0!
0)
#595000
1!
1)
#600000
0!
0)
#605000
1!
1)
#608000
b1100 %
b1100 -
#610000
0!
0)
#615000
1!
1)
#620000
0!
0)
#625000
1!
1)
#630000
0!
0)
#635000
1!
1)
#638000
b10 &
b10 .
b101 1
#640000
0!
0)
#645000
1!
1)
b101 0
b100 1
b101 (
#648000
1$
1,
b110 1
12
#650000
0!
0)
#655000
1!
1)
b110 0
1/
b101 1
02
1'
b110 (
#658000
0$
0,
b111 1
12
#660000
0!
0)
#665000
1!
1)
b111 0
b1000 1
b111 (
#670000
0!
0)
#675000
1!
1)
b1000 0
b1001 1
b1000 (
#680000
0!
0)
#685000
1!
1)
b1001 0
b1010 1
b1001 (
#690000
0!
0)
#695000
1!
1)
b1010 0
b1011 1
b1010 (
#700000
0!
0)
#705000
1!
1)
b1011 0
b1100 1
b1011 (
#710000
0!
0)
#715000
1!
1)
b1100 0
b1011 1
02
b1100 (
#720000
0!
0)
#725000
1!
1)
b1011 0
0/
b1010 1
0'
b1011 (
#730000
0!
0)
#735000
1!
1)
b1010 0
b1001 1
b1010 (
#740000
0!
0)
#745000
1!
1)
b1001 0
b1000 1
b1001 (
#750000
0!
0)
#755000
1!
1)
b1000 0
b111 1
b1000 (
#760000
0!
0)
#765000
1!
1)
b111 0
b110 1
b111 (
#770000
0!
0)
#775000
1!
1)
b110 0
b101 1
b110 (
#780000
0!
0)
#785000
1!
1)
b101 0
b100 1
b101 (
#790000
0!
0)
#795000
1!
1)
b100 0
b11 1
b100 (
#800000
0!
0)
#805000
1!
1)
b11 0
b10 1
b11 (
#810000
0!
0)
#815000
1!
1)
b10 0
b11 1
12
b10 (
#820000
0!
0)
#823000
b1000 &
b1000 .
b10 1
02
#825000
1!
1)
#830000
0!
0)
#833000
b1101 %
b1101 -
#835000
1!
1)
#838000
0"
0*
#840000
0!
0)
#845000
1!
1)
b1000 0
1/
b1001 1
12
1'
b1000 (
#848000
1"
1*
#850000
0!
0)
#855000
1!
1)
b1001 0
b1010 1
b1001 (
#860000
0!
0)
#865000
1!
1)
b1010 0
b1011 1
b1010 (
#870000
0!
0)
#875000
1!
1)
b1011 0
b1100 1
b1011 (
#880000
0!
0)
#885000
1!
1)
b1100 0
b1101 1
b1100 (
#890000
0!
0)
#895000
1!
1)
b1101 0
b1100 1
02
b1101 (
#900000
0!
0)
#905000
1!
1)
b1100 0
0/
b1011 1
0'
b1100 (
#910000
0!
0)
#915000
1!
1)
b1011 0
b1010 1
b1011 (
#920000
0!
0)
#925000
1!
1)
b1010 0
b1001 1
b1010 (
#930000
0!
0)
#935000
1!
1)
b1001 0
b1000 1
b1001 (
