lab3/Lab3_Team25_Round_Robin_FIFO_Aribiter/Lab3_Team25_Round_Robin_FIFO_Arbiter_t.v
`timescale 1ns/1ps

module Round_Robin_FIFO_Arbiter_t;

    reg clk = 0;
    reg rst_n = 0;
    reg [4-1:0] wen = 4'b0000;
    reg [8-1:0] a = 0, b = 0, c = 0, d = 0;
    wire [8-1:0] dout;
    wire valid;

    wire [8-1:0] not_found;

    parameter cyc = 10;

      // generate clock.
    always#(cyc/2)clk = !clk;

    Round_Robin_FIFO_Arbiter rrfa(
        .clk (clk),
        .rst_n (rst_n),
        .wen (wen),
        .a (a),
        .b (b),
        .c (c),
        .d (d),
        .dout (dout),
        .valid (valid)
    );

    initial begin
        $dumpfile("round_robin_fifo_arbiter.vcd");
        $dumpvars("+all");
    end

    initial begin
        @(negedge clk)
        rst_n = 1;
        wen = 4'b1111;
        a = 8'd87;
        b = 8'd56;
        c = 8'd9;
        d = 8'd12;
        @(negedge clk)
        rst_n = 1;
        wen = 4'b1000;
        a = not_found;
        b = not_found;
        c = not_found;
        d = 8'd85;
        @(negedge clk)
        rst_n = 1;
        wen = 4'b0100;
        a = not_found;
        b = not_found;
        c = 8'd139;
        d = not_found;
        @(negedge clk)
        rst_n = 1;
        wen = 4'b0000;
        a = not_found;
        b = not_found;
        c = not_found;
        d = not_found;
        @(negedge clk)
        rst_n = 1;
        wen = 4'b0000;
        a = not_found;
        b = not_found;
        c = not_found;
        d = not_found;
        @(negedge clk)
        rst_n = 1;
        wen = 4'b0000;
        a = not_found;
        b = not_found;
        c = not_found;
        d = not_found;
        @(negedge clk)
        rst_n = 1;
        wen = 4'b0001;
        a = 8'd51;
        b = not_found;
        c = not_found;
        c = not_found;
        @(negedge clk)
        rst_n = 1;
        wen = 4'b0000;
        a = not_found;
        b = not_found;
        c = not_found;
        d = not_found;
        @(negedge clk)
        rst_n = 1;
        wen = 4'b0000;
        a = not_found;
        b = not_found;
        c = not_found;
        d = not_found;
        @(negedge clk)
        rst_n = 1;
        wen = 4'b0111;
        a = not_found;
        b = 8'd44;
        c = 8'd22;
        d = 8'd99;
        @(negedge clk)
        rst_n = 0;
        wen = 4'b1111;
        a = 8'd11;
        b = 8'd22;
        c = 8'd33;
        d = 8'd88;
        @(negedge clk)
        rst_n = 1;
        wen = 4'b0000;
        a = not_found;
        b = not_found;
        c = not_found;
        d = not_found;
        @(negedge clk)
        rst_n = 1;
        wen = 4'b0000;
        a = not_found;
        b = not_found;
        c = not_found;
        d = not_found;
        @(negedge clk)
        $finish;
    end
endmodule

lab3/Lab3_Team25_Round_Robin_FIFO_Aribiter/Lab3_Team25_Round_Robin_FIFO_Arbiter.v
`timescale 1ns/1ps

module or_4 (a, b, c, d, out);
    
    input a, b, c, d;
    output out;

    wire tmp1, tmp2;

    or o0(tmp1, a, b);
    or o1(tmp2, c, d);
    or o2(out, tmp1, tmp2);

endmodule

module or_8bit (a, b, c, d, out);
    
    input [8-1:0] a, b, c, d;
    output [8-1:0] out;

    or_4 a0(a[0], b[0], c[0], d[0], out[0]);
    or_4 a1(a[1], b[1], c[1], d[1], out[1]);
    or_4 a2(a[2], b[2], c[2], d[2], out[2]);
    or_4 a3(a[3], b[3], c[3], d[3], out[3]);
    or_4 a4(a[4], b[4], c[4], d[4], out[4]);
    or_4 a5(a[5], b[5], c[5], d[5], out[5]);
    or_4 a6(a[6], b[6], c[6], d[6], out[6]);
    or_4 a7(a[7], b[7], c[7], d[7], out[7]);

endmodule

module FIFO_8(clk, rst_n, wen, ren, din, dout, error);

    input clk;
    input rst_n;
    input wen, ren;
    input [8-1:0] din;
    output [8-1:0] dout;
    output error;

    reg [8-1:0] FIFO [0:128-1];
    reg [8-1:0] dout;
    reg error;
    reg [4-1:0] head, tail;

    reg [4-1:0] next_head, next_tail;

    always @(*) begin
        next_head = head + 1;
        next_tail = tail + 1;
        if (head === 4'b1000) begin
            next_head = 0;
        end
        if (tail === 4'b1000) begin
            next_tail = 0;
        end
    end

    always @(posedge clk) begin
        if (!rst_n) begin
            head <= 0;
            tail <= 0;
            dout <= 0;
            error <= 0;
        end 
        else if (ren) begin
            if ((head === tail)) begin
                head <= head;
                error <= 1;
                tail <= tail;
                dout <= 8'bx;
            end else begin
                error <= 0;
                dout <= FIFO[head];
                head <= next_head;
                tail <= tail;
            end
        end 
        else if (wen) begin
            if (head === next_tail) begin
                head <= head;
                tail <= tail;
                error <= 1;
                dout <= 8'bx;
            end else begin
                error <= 0;
                dout <= 8'bx;
                FIFO[tail] <= din;
                head <= head;
                tail <= next_tail;
            end
        end 
        else begin
            error <= 0;
            dout <= 8'bx;
            head <= head;
            tail <= tail;
        end
    end

endmodule

module Round_Robin_FIFO_Arbiter(clk, rst_n, wen, a, b, c, d, dout, valid);

    input clk;
    input rst_n;
    input [4-1:0] wen;
    input [8-1:0] a, b, c, d;
    output [8-1:0] dout;
    output valid;

    wire era, erb, erc, erd;
    wire [2-1:0] next_counter;
    wire [8-1:0] Aout, Bout, Cout, Dout;

    reg ra = 0, rb = 0, rc = 0, rd = 0;
    reg valid = 0, tmp_valid = 0;
    reg [3-1:0] counter = 0;
    reg [8-1:0] dout = 0;

    assign next_counter = counter + 1;

    always @(wen, counter) begin
        ra = 0; rb = 0; rc = 0; rd = 0;
        if (!wen[0] && (counter == 2'b00)) ra = 1;
        else if (!wen[1] && (counter == 2'b01)) rb = 1;
        else if (!wen[2] && (counter == 2'b10)) rc = 1;
        else if (!wen[3] && (counter == 2'b11)) rd = 1;
        else begin
            ra = 0; rb = 0; rc = 0; rd = 0;
        end
    end

    always @(*) begin
        valid = 0;
        if (rst_n && counter === 2'b01) begin
            valid = (!era && tmp_valid);
        end
        else if (rst_n && counter === 2'b10) begin
            valid = (!erb && tmp_valid);
        end
        else if (rst_n && counter === 2'b11) begin
            valid = (!erc && tmp_valid);
        end
        else if (rst_n && counter === 2'b00) begin
            valid = (!erd && tmp_valid);
        end
        else begin
            valid = 0;
        end
    end

    always @(*) begin
        if (counter === 2'b01 && valid) begin
            dout = Aout;
        end
        else if (counter === 2'b10 && valid) begin
            dout = Bout;
        end
        else if (counter === 2'b11 && valid) begin
            dout = Cout;
        end
        else if (counter === 2'b00 && valid) begin
            dout = Dout;
        end
        else begin
            dout = 0;
        end
    end

    always @(posedge clk) begin
        if (!rst_n) begin
            counter <= 0;
        end
        else begin
            counter <= next_counter;
            if (counter == 2'b00 && !wen[0]) tmp_valid <= 1;
            else if (counter == 2'b01 && !wen[1]) tmp_valid <= 1;
            else if (counter == 2'b10 && !wen[2]) tmp_valid <= 1;
            else if (counter == 2'b11 && !wen[3]) tmp_valid <= 1;
            else tmp_valid <= 0;
        end
    end

    FIFO_8 fa(clk, rst_n, wen[0], ra, a, Aout, era);
    FIFO_8 fb(clk, rst_n, wen[1], rb, b, Bout, erb);
    FIFO_8 fc(clk, rst_n, wen[2], rc, c, Cout, erc);
    FIFO_8 fd(clk, rst_n, wen[3], rd, d, Dout, erd);
    //or_8bit oo(Aout, Bout, Cout, Dout, dout);

endmodule

lab3/Lab3_Team25_Round_Robin_FIFO_Aribiter/round_robin_fifo_arbiter.vcd
$date
    Oct 15, 2022  23:33:58
$end
$version
    TOOL:	ncsim	15.20-s039
$end
$timescale
    1 ps
$end

$scope module or_8bit $end
$var wire      1 !    a [7] $end
$var wire      1 !    a [6] $end
$var wire      1 !    a [5] $end
$var wire      1 !    a [4] $end
$var wire      1 !    a [3] $end
$var wire      1 !    a [2] $end
$var wire      1 !    a [1] $end
$var wire      1 !    a [0] $end
$var wire      1 !    b [7] $end
$var wire      1 !    b [6] $end
$var wire      1 !    b [5] $end
$var wire      1 !    b [4] $end
$var wire      1 !    b [3] $end
$var wire      1 !    b [2] $end
$var wire      1 !    b [1] $end
$var wire      1 !    b [0] $end
$var wire      1 !    c [7] $end
$var wire      1 !    c [6] $end
$var wire      1 !    c [5] $end
$var wire      1 !    c [4] $end
$var wire      1 !    c [3] $end
$var wire      1 !    c [2] $end
$var wire      1 !    c [1] $end
$var wire      1 !    c [0] $end
$var wire      1 !    d [7] $end
$var wire      1 !    d [6] $end
$var wire      1 !    d [5] $end
$var wire      1 !    d [4] $end
$var wire      1 !    d [3] $end
$var wire      1 !    d [2] $end
$var wire      1 !    d [1] $end
$var wire      1 !    d [0] $end
$var wire      1 "    out [7] $end
$var wire      1 "    out [6] $end
$var wire      1 "    out [5] $end
$var wire      1 "    out [4] $end
$var wire      1 "    out [3] $end
$var wire      1 "    out [2] $end
$var wire      1 "    out [1] $end
$var wire      1 "    out [0] $end

$scope module a0 $end
$var wire      1 !    a  $end
$var wire      1 !    b  $end
$var wire      1 !    c  $end
$var wire      1 !    d  $end
$var wire      1 "    out  $end
$var wire      1 #    tmp1  $end
$var wire      1 $    tmp2  $end
$upscope $end


$scope module a1 $end
$var wire      1 !    a  $end
$var wire      1 !    b  $end
$var wire      1 !    c  $end
$var wire      1 !    d  $end
$var wire      1 "    out  $end
$var wire      1 #    tmp1  $end
$var wire      1 $    tmp2  $end
$upscope $end


$scope module a2 $end
$var wire      1 !    a  $end
$var wire      1 !    b  $end
$var wire      1 !    c  $end
$var wire      1 !    d  $end
$var wire      1 "    out  $end
$var wire      1 #    tmp1  $end
$var wire      1 $    tmp2  $end
$upscope $end


$scope module a3 $end
$var wire      1 !    a  $end
$var wire      1 !    b  $end
$var wire      1 !    c  $end
$var wire      1 !    d  $end
$var wire      1 "    out  $end
$var wire      1 #    tmp1  $end
$var wire      1 $    tmp2  $end
$upscope $end


$scope module a4 $end
$var wire      1 !    a  $end
$var wire      1 !    b  $end
$var wire      1 !    c  $end
$var wire      1 !    d  $end
$var wire      1 "    out  $end
$var wire      1 #    tmp1  $end
$var wire      1 $    tmp2  $end
$upscope $end


$scope module a5 $end
$var wire      1 !    a  $end
$var wire      1 !    b  $end
$var wire      1 !    c  $end
$var wire      1 !    d  $end
$var wire      1 "    out  $end
$var wire      1 #    tmp1  $end
$var wire      1 $    tmp2  $end
$upscope $end


$scope module a6 $end
$var wire      1 !    a  $end
$var wire      1 !    b  $end
$var wire      1 !    c  $end
$var wire      1 !    d  $end
$var wire      1 "    out  $end
$var wire      1 #    tmp1  $end
$var wire      1 $    tmp2  $end
$upscope $end


$scope module a7 $end
$var wire      1 !    a  $end
$var wire      1 !    b  $end
$var wire      1 !    c  $end
$var wire      1 !    d  $end
$var wire      1 "    out  $end
$var wire      1 #    tmp1  $end
$var wire      1 $    tmp2  $end
$upscope $end

$upscope $end


$scope module Round_Robin_FIFO_Arbiter_t $end
$var reg       1 %    clk  $end
$var reg       1 &    rst_n  $end
$var reg       4 '    wen [3:0] $end
$var reg       8 (    a [7:0] $end
$var reg       8 )    b [7:0] $end
$var reg       8 *    c [7:0] $end
$var reg       8 +    d [7:0] $end
$var wire      8 ,    dout [7:0] $end
$var wire      1 -    valid  $end
$var wire      8 .    not_found [7:0] $end
$var parameter 32 /    cyc  $end

$scope module rrfa $end
$var wire      1 0    clk  $end
$var wire      1 1    rst_n  $end
$var wire      1 2    wen [3] $end
$var wire      1 3    wen [2] $end
$var wire      1 4    wen [1] $end
$var wire      1 5    wen [0] $end
$var wire      8 6    a [7:0] $end
$var wire      8 7    b [7:0] $end
$var wire      8 8    c [7:0] $end
$var wire      8 9    d [7:0] $end
$var reg       8 :    dout [7:0] $end
$var reg       1 ;    valid  $end
$var wire      1 <    era  $end
$var wire      1 =    erb  $end
$var wire      1 >    erc  $end
$var wire      1 ?    erd  $end
$var wire      2 @    next_counter [1:0] $end
$var wire      8 A    Aout [7:0] $end
$var wire      8 B    Bout [7:0] $end
$var wire      8 C    Cout [7:0] $end
$var wire      8 D    Dout [7:0] $end
$var reg       1 E    ra  $end
$var reg       1 F    rb  $end
$var reg       1 G    rc  $end
$var reg       1 H    rd  $end
$var reg       1 I    tmp_valid  $end
$var reg       3 J    counter [2:0] $end

$scope module fa $end
$var wire      1 0    clk  $end
$var wire      1 1    rst_n  $end
$var wire      1 5    wen  $end
$var wire      1 K    ren  $end
$var wire      8 6    din [7:0] $end
$var reg       8 L    dout [7:0] $end
$var reg       1 M    error  $end
$var reg       4 N    head [3:0] $end
$var reg       4 O    tail [3:0] $end
$var reg       4 P    next_head [3:0] $end
$var reg       4 Q    next_tail [3:0] $end
$upscope $end


$scope module fb $end
$var wire      1 0    clk  $end
$var wire      1 1    rst_n  $end
$var wire      1 4    wen  $end
$var wire      1 R    ren  $end
$var wire      8 7    din [7:0] $end
$var reg       8 S    dout [7:0] $end
$var reg       1 T    error  $end
$var reg       4 U    head [3:0] $end
$var reg       4 V    tail [3:0] $end
$var reg       4 W    next_head [3:0] $end
$var reg       4 X    next_tail [3:0] $end
$upscope $end


$scope module fc $end
$var wire      1 0    clk  $end
$var wire      1 1    rst_n  $end
$var wire      1 3    wen  $end
$var wire      1 Y    ren  $end
$var wire      8 8    din [7:0] $end
$var reg       8 Z    dout [7:0] $end
$var reg       1 [    error  $end
$var reg       4 \    head [3:0] $end
$var reg       4 ]    tail [3:0] $end
$var reg       4 ^    next_head [3:0] $end
$var reg       4 _    next_tail [3:0] $end
$upscope $end


$scope module fd $end
$var wire      1 0    clk  $end
$var wire      1 1    rst_n  $end
$var wire      1 2    wen  $end
$var wire      1 `    ren  $end
$var wire      8 9    din [7:0] $end
$var reg       8 a    dout [7:0] $end
$var reg       1 b    error  $end
$var reg       4 c    head [3:0] $end
$var reg       4 d    tail [3:0] $end
$var reg       4 e    next_head [3:0] $end
$var reg       4 f    next_tail [3:0] $end
$upscope $end

$upscope $end

$upscope $end

$enddefinitions $end
$dumpvars
b1010 /
z!
x"
x#
x$
0%
0&
b0 '
b0 (
b0 )
b0 *
b0 +
b0 ,
0-
bz .
00
01
02
03
04
05
b0 6
b0 7
b0 8
b0 9
b0 :
0;
x<
x=
x>
x?
b1 @
bx A
bx B
bx C
bx D
1E
0F
0G
0H
0I
b0 J
1K
bx L
xM
bx N
bx O
bx P
bx Q
0R
bx S
xT
bx U
bx V
bx W
bx X
0Y
bx Z
x[
bx \
bx ]
bx ^
bx _
0`
bx a
xb
bx c
bx d
bx e
bx f
$end
#5000
1%
10
b0 c
b0 d
b0 a
0b
b0 \
b0 ]
b0 Z
0[
b0 U
b0 V
b0 S
0T
b0 N
b0 O
b0 L
0M
b1 e
b1 f
b1 ^
b1 _
b1 W
b1 X
b1 P
b1 Q
0<
b0 A
0=
b0 B
0>
b0 C
0?
b0 D
#10000
0%
1&
b1111 '
b1010111 (
b111000 )
b1001 *
b1100 +
b1100 9
b1001 8
b111000 7
b1010111 6
12
13
14
15
11
00
0E
0K
#15000
1%
10
bx a
b1 d
bx Z
b1 ]
bx S
b1 V
bx L
b1 O
b1 J
b10 f
b10 _
b10 X
b10 Q
b10 @
bx A
bx B
bx C
bx D
#20000
0%
b1000 '
bz (
bz )
bz *
b1010101 +
b1010101 9
bz 8
bz 7
bz 6
03
04
05
00
1F
1R
#25000
1%
10
b10 d
b111000 S
b1 U
b10 J
1I
b11 f
b10 W
0F
1G
1;
bx :
bx ,
1-
1Y
0R
b11 @
b111000 B
b111000 :
b111000 ,
#30000
0%
b100 '
b10001011 *
bz +
bz 9
b10001011 8
02
13
00
0G
0Y
#35000
1%
10
b10 ]
bx S
b11 J
0I
b11 _
1H
0;
b0 :
b0 ,
0-
1`
b0 @
bx B
#40000
0%
b0 '
bz *
bz 8
03
00
0H
1H
#45000
1%
10
b1100 a
b1 c
b0 J
1I
b10 e
0H
1E
1;
bx :
bx ,
1-
1K
0`
b1 @
b1100 D
b1100 :
b1100 ,
#50000
0%
00
#55000
1%
10
bx a
b1010111 L
b1 N
b1 J
b10 P
0E
1F
0;
1;
bx :
bx ,
1R
0K
b10 @
b1010111 A
bx D
b1010111 :
b1010111 ,
#60000
0%
00
#65000
1%
10
1T
bx L
b10 J
0F
1G
0;
1;
bx :
bx ,
1Y
0R
b11 @
bx A
1=
0;
b0 :
b0 ,
0-
#70000
0%
b1 '
b110011 (
b110011 6
15
00
0G
1G
#75000
1%
10
b1001 Z
b1 \
0T
b10 O
b11 J
b10 ^
b11 Q
0G
1H
1;
bx :
bx ,
1-
1`
0Y
b0 @
0=
b1001 C
0;
1;
b1001 :
b1001 ,
#80000
0%
b0 '
bz (
bz 6
05
00
0H
1H
#85000
1%
10
b1010101 a
b10 c
bx Z
b0 J
b11 e
0H
1E
0;
1;
bx :
bx ,
1K
0`
b1 @
bx C
b1010101 D
b1010101 :
b1010101 ,
#90000
0%
00
#95000
1%
10
bx a
b110011 L
b10 N
b1 J
b11 P
0E
1F
0;
1;
bx :
bx ,
1R
0K
b10 @
b110011 A
bx D
b110011 :
b110011 ,
