lab3/Lab3_Team25_Ping_Pong_Counter/Lab3_Team25_Ping_Pong_Counter.v
`timescale 1ns/1ps

module Ping_Pong_Counter (clk, rst_n, enable, direction, out);

    input clk, rst_n;
    input enable;
    output direction;
    output [4-1:0] out;

    wire [4-1:0] next_counter, pre_counter;

    reg [4-1:0] counter;
    reg direction;

    assign next_counter = counter + 1;
    assign pre_counter = counter - 1;
    assign out = counter;

    always @(posedge clk) begin
        if (!rst_n) begin
            counter <= 0;
            direction <= 1;
        end
        else begin
            if (enable) begin
                if (direction) begin
                    if (counter === 4'b1111) begin
                        direction <= 0;
                        counter <= pre_counter;
                    end
                    else begin
                        counter <= next_counter;
                    end
                end
                else begin
                    if (counter === 4'b0000) begin
                        direction <= 1;
                        counter <= next_counter;
                    end
                    else begin
                        counter <= pre_counter;
                    end
                end
            end
            else begin
                counter <= counter;
                direction <= direction;
            end
        end
    end

endmodule

lab3/Lab3_Team25_Pin_Pong_Counter/Lab3_Team25_Ping_Pong_Counter_t.v
`timescale 1ns/1ps

module Ping_Pong_Counter_t;
    
    reg clk = 1'b0;
    reg rst_n = 1'b1;
    reg enable = 1'b0;
    wire direction;
    wire [4-1:0] out;

    parameter cyc = 10;

    always#(cyc/2)clk = !clk;

    Ping_Pong_Counter pp(
        .clk (clk),
        .rst_n (rst_n),
        .enable (enable),
        .direction (direction),
        .out (out)
    );

    initial begin
        $dumpfile("ping_pong_counter.vcd");
        $dumpvars("+all");
    end

    initial begin
        @(negedge clk)
        rst_n = 0;
        enable = 0;
        @(negedge clk)
        rst_n = 1;
        enable = 1;
        @(negedge clk)
        rst_n = 1;
        enable = 1;
        @(negedge clk)
        rst_n = 1;
        enable = 1;
        @(negedge clk)
        rst_n = 1;
        enable = 1;
        @(negedge clk)
        rst_n = 1;
        enable = 1;
        @(negedge clk)
        rst_n = 1;
        enable = 1;
        @(negedge clk)
        rst_n = 1;
        enable = 1;
        @(negedge clk)
        rst_n = 1;
        enable = 1;
        @(negedge clk)
        rst_n = 1;
        enable = 1;
        @(negedge clk)
        rst_n = 1;
        enable = 1;
        @(negedge clk)
        rst_n = 1;
        enable = 1;
        @(negedge clk)
        rst_n = 1;
        enable = 1;
        @(negedge clk)
        rst_n = 1;
        enable = 1;
        @(negedge clk)
        rst_n = 1;
        enable = 1;
        @(negedge clk)
        rst_n = 1;
        enable = 1;
        @(negedge clk)
        rst_n = 1;
        enable = 1;
        @(negedge clk)
        rst_n = 1;
        enable = 1;
        @(negedge clk)
        rst_n = 1;
        enable = 1;
        @(negedge clk)
        rst_n = 1;
        enable = 1;
        @(negedge clk)
        rst_n = 1;
        enable = 1;
        @(negedge clk)
        rst_n = 1;
        enable = 1;
        @(negedge clk)
        rst_n = 1;
        enable = 1;
        @(negedge clk)
        rst_n = 1;
        enable = 1;
        @(negedge clk)
        rst_n = 1;
        enable = 1;
        @(negedge clk)
        rst_n = 1;
        enable = 1;
        @(negedge clk)
        rst_n = 1;
        enable = 1;
        @(negedge clk)
        rst_n = 1;
        enable = 1;
        @(negedge clk)
        rst_n = 1;
        enable = 1;
        @(negedge clk)
        rst_n = 0;
        enable = 1;
        @(negedge clk)
        rst_n = 1;
        enable = 1;
        @(negedge clk)
        rst_n = 1;
        enable = 1;
        @(negedge clk)
        rst_n = 1;
        enable = 1;
        @(negedge clk)
        rst_n = 1;
        enable = 1;
        @(negedge clk)
        rst_n = 1;
        enable = 1;
        @(negedge clk)
        rst_n = 1;
        enable = 1;
        @(negedge clk)
        rst_n = 1;
        enable = 1;
        @(negedge clk)
        rst_n = 1;
        enable = 1;
        @(negedge clk)
        rst_n = 1;
        enable = 1;
        @(negedge clk)
        rst_n = 1;
        enable = 1;
        @(negedge clk)
        rst_n = 1;
        enable = 1;
        @(negedge clk)
        rst_n = 1;
        enable = 1;
        @(negedge clk)
        rst_n = 1;
        enable = 1;
        @(negedge clk)
        rst_n = 1;
        enable = 1;
        @(negedge clk)
        rst_n = 1;
        enable = 1;
        @(negedge clk)
        rst_n = 1;
        enable = 1;
        @(negedge clk)
        rst_n = 1;
        enable = 1;
        @(negedge clk)
        rst_n = 1;
        enable = 1;
        @(negedge clk)
        rst_n = 1;
        enable = 1;
        @(negedge clk)
        rst_n = 1;
        enable = 1;
        @(negedge clk)
        rst_n = 1;
        enable = 1;
        @(negedge clk)
        rst_n = 1;
        enable = 1;
        @(negedge clk)
        rst_n = 1;
        enable = 1;
        @(negedge clk)
        rst_n = 1;
        enable = 1;
        @(negedge clk)
        rst_n = 1;
        enable = 1;
        @(negedge clk)
        rst_n = 1;
        enable = 1;
        @(negedge clk)
        rst_n = 1;
        enable = 1;
        @(negedge clk)
        $finish;
    end

endmodule

lab3/Lab3_Team25_Ping_Pong_Counter/ping_pong_counter.vcd
$date
    Oct 17, 2022  11:15:51
$end
$version
    TOOL:	ncsim	15.20-s039
$end
$timescale
    1 ps
$end

$scope module Ping_Pong_Counter_t $end
$var reg       1 !    clk  $end
$var reg       1 "    rst_n  $end
$var reg       1 #    enable  $end
$var wire      1 $    direction  $end
$var wire      4 %    out [3:0] $end
$var parameter 32 &    cyc  $end

$scope module pp $end
$var wire      1 '    clk  $end
$var wire      1 (    rst_n  $end
$var wire      1 )    enable  $end
$var reg       1 *    direction  $end
$var wire      4 %    out [3:0] $end
$var wire      4 +    next_counter [3:0] $end
$var wire      4 ,    pre_counter [3:0] $end
$var reg       4 -    counter [3:0] $end
$upscope $end

$upscope $end

$enddefinitions $end
$dumpvars
b1010 &
0!
1"
0#
x$
bx %
0'
1(
0)
x*
bx +
bx ,
bx -
$end
#5000
1!
1'
#10000
0!
0"
0(
0'
#15000
1!
1'
b0 -
1*
b1111 ,
b1 +
1$
b0 %
#20000
0!
1"
1#
1)
1(
0'
#25000
1!
1'
b1 -
b0 ,
b10 +
b1 %
#30000
0!
0'
#35000
1!
1'
b10 -
b1 ,
b11 +
b10 %
#40000
0!
0'
#45000
1!
1'
b11 -
b10 ,
b100 +
b11 %
#50000
0!
0'
#55000
1!
1'
b100 -
b11 ,
b101 +
b100 %
#60000
0!
0'
#65000
1!
1'
b101 -
b100 ,
b110 +
b101 %
#70000
0!
0'
#75000
1!
1'
b110 -
b101 ,
b111 +
b110 %
#80000
0!
0'
#85000
1!
1'
b111 -
b110 ,
b1000 +
b111 %
#90000
0!
0'
#95000
1!
1'
b1000 -
b111 ,
b1001 +
b1000 %
#100000
0!
0'
#105000
1!
1'
b1001 -
b1000 ,
b1010 +
b1001 %
#110000
0!
0'
#115000
1!
1'
b1010 -
b1001 ,
b1011 +
b1010 %
#120000
0!
0'
#125000
1!
1'
b1011 -
b1010 ,
b1100 +
b1011 %
#130000
0!
0'
#135000
1!
1'
b1100 -
b1011 ,
b1101 +
b1100 %
#140000
0!
0'
#145000
1!
1'
b1101 -
b1100 ,
b1110 +
b1101 %
#150000
0!
0'
#155000
1!
1'
b1110 -
b1101 ,
b1111 +
b1110 %
#160000
0!
0'
#165000
1!
1'
b1111 -
b1110 ,
b0 +
b1111 %
#170000
0!
0'
#175000
1!
1'
0*
b1110 -
b1101 ,
b1111 +
b1110 %
0$
#180000
0!
0'
#185000
1!
1'
b1101 -
b1100 ,
b1110 +
b1101 %
#190000
0!
0'
#195000
1!
1'
b1100 -
b1011 ,
b1101 +
b1100 %
#200000
0!
0'
#205000
1!
1'
b1011 -
b1010 ,
b1100 +
b1011 %
#210000
0!
0'
#215000
1!
1'
b1010 -
b1001 ,
b1011 +
b1010 %
#220000
0!
0'
#225000
1!
1'
b1001 -
b1000 ,
b1010 +
b1001 %
#230000
0!
0'
#235000
1!
1'
b1000 -
b111 ,
b1001 +
b1000 %
#240000
0!
0'
#245000
1!
1'
b111 -
b110 ,
b1000 +
b111 %
#250000
0!
0'
#255000
1!
1'
b110 -
b101 ,
b111 +
b110 %
#260000
0!
0'
#265000
1!
1'
b101 -
b100 ,
b110 +
b101 %
#270000
0!
0'
#275000
1!
1'
b100 -
b11 ,
b101 +
b100 %
#280000
0!
0'
#285000
1!
1'
b11 -
b10 ,
b100 +
b11 %
#290000
0!
0'
#295000
1!
1'
b10 -
b1 ,
b11 +
b10 %
#300000
0!
0'
#305000
1!
1'
b1 -
b0 ,
b10 +
b1 %
#310000
0!
0'
#315000
1!
1'
b0 -
b1111 ,
b1 +
b0 %
#320000
0!
0'
#325000
1!
1'
1*
b1 -
b0 ,
b10 +
b1 %
1$
#330000
0!
0'
#335000
1!
1'
b10 -
b1 ,
b11 +
b10 %
#340000
0!
0"
0(
0'
#345000
1!
1'
b0 -
b1111 ,
b1 +
b0 %
#350000
0!
1"
1(
0'
#355000
1!
1'
b1 -
b0 ,
b10 +
b1 %
#360000
0!
0'
#365000
1!
1'
b10 -
b1 ,
b11 +
b10 %
#370000
0!
0'
#375000
1!
1'
b11 -
b10 ,
b100 +
b11 %
#380000
0!
0'
#385000
1!
1'
b100 -
b11 ,
b101 +
b100 %
#390000
0!
0'
#395000
1!
1'
b101 -
b100 ,
b110 +
b101 %
#400000
0!
0'
#405000
1!
1'
b110 -
b101 ,
b111 +
b110 %
#410000
0!
0'
#415000
1!
1'
b111 -
b110 ,
b1000 +
b111 %
#420000
0!
0'
#425000
1!
1'
b1000 -
b111 ,
b1001 +
b1000 %
#430000
0!
0'
#435000
1!
1'
b1001 -
b1000 ,
b1010 +
b1001 %
#440000
0!
0'
#445000
1!
1'
b1010 -
b1001 ,
b1011 +
b1010 %
#450000
0!
0'
#455000
1!
1'
b1011 -
b1010 ,
b1100 +
b1011 %
#460000
0!
0'
#465000
1!
1'
b1100 -
b1011 ,
b1101 +
b1100 %
#470000
0!
0'
#475000
1!
1'
b1101 -
b1100 ,
b1110 +
b1101 %
#480000
0!
0'
#485000
1!
1'
b1110 -
b1101 ,
b1111 +
b1110 %
#490000
0!
0'
#495000
1!
1'
b1111 -
b1110 ,
b0 +
b1111 %
#500000
0!
0'
#505000
1!
1'
0*
b1110 -
b1101 ,
b1111 +
b1110 %
0$
#510000
0!
0'
#515000
1!
1'
b1101 -
b1100 ,
b1110 +
b1101 %
#520000
0!
0'
#525000
1!
1'
b1100 -
b1011 ,
b1101 +
b1100 %
#530000
0!
0'
#535000
1!
1'
b1011 -
b1010 ,
b1100 +
b1011 %
#540000
0!
0'
#545000
1!
1'
b1010 -
b1001 ,
b1011 +
b1010 %
#550000
0!
0'
#555000
1!
1'
b1001 -
b1000 ,
b1010 +
b1001 %
#560000
0!
0'
#565000
1!
1'
b1000 -
b111 ,
b1001 +
b1000 %
#570000
0!
0'
#575000
1!
1'
b111 -
b110 ,
b1000 +
b111 %
#580000
0!
0'
#585000
1!
1'
b110 -
b101 ,
b111 +
b110 %
#590000
0!
0'
#595000
1!
1'
b101 -
b100 ,
b110 +
b101 %
#600000
0!
0'
#605000
1!
1'
b100 -
b11 ,
b101 +
b100 %
#610000
0!
0'
#615000
1!
1'
b11 -
b10 ,
b100 +
b11 %
