lab4/Lab4_Team25_Built_In_Self_Test/Lab4_Team25_Built_In_Self_Test.v
`timescale 1ns/1ps

module Built_In_Self_Test(clk, rst_n, scan_en, scan_in, scan_out);

    input clk;
    input rst_n;
    input scan_en;
    output scan_in;
    output scan_out;

    Q3 M1(
        .clk(clk),
        .rst_n(rst_n),
        .out(scan_in)
    );    
    Scan_Chain_Design M2(
        .clk(clk),
        .rst_n(rst_n),
        .scan_in(scan_in),
        .scan_en(scan_en),
        .scan_out(scan_out)
    );

endmodule

module Q3(clk, rst_n, out);

    input clk, rst_n;
    output reg [8-1:0] out;

    always @(posedge clk) begin
        if (~rst_n) begin
            out <= 8'b10111101;
        end else begin
            out[7] <= out[6];
            out[6] <= out[5];
            out[5] <= out[4];
            out[4] <= out[3];
            out[3] <= out[2];
            out[2] <= out[1];
            out[1] <= out[0];
            out[0] <= (out[1] ^ out[2] ^ out[3] ^ out[7]);
        end
    end
//    always #(5) begin
//        $display("out: %b", out);
//    end
endmodule

module Scan_Chain_Design(clk, rst_n, scan_in, scan_en, scan_out);
    input clk;
    input rst_n;
    input scan_in;
    input scan_en;
    output reg scan_out;

    reg [7:0] p;
    reg [7:0] sdff;

    always @(*) begin
        p = sdff[7:4]*sdff[3:0];
        scan_out = sdff[0];
    end

    always @(posedge clk) begin
        if (!rst_n) begin
            sdff <= 8'b00000000;
        end else begin
            if (scan_en) begin
                sdff <= {scan_in, sdff[7:1]};
            end else begin
                sdff <= p;
            end
        end
    end

	always @(negedge clk) begin
		$display(
			"scan_in: %b | scan_en: %b | a: %d | b: %d | p: %d | sdff: %b",
			scan_in, scan_en, sdff[7:4], sdff[3:0], p, sdff[7:0]
		);
	end

endmodule

lab4/Lab4_Team25_Built_In_Self_Test/Lab4_Team25_Built_In_Self_Test_t.v
`timescale 1ns/1ps

module Built_in_Self_Test_t();

	reg clk = 0;
	reg rst_n = 0;
	reg scan_en = 0;

	wire scan_in;
	wire scan_out;

	always #(5) clk = ~clk;

	Built_In_Self_Test M1(
		.clk(clk),
		.rst_n(rst_n),
		.scan_en(scan_en),
		.scan_in(scan_in),
		.scan_out(scan_out)
	);

	initial begin
		$dumpfile("Build_In_Self_Test.vcd");
		$dumpvars("+all");
	end

	initial begin
		@(negedge clk)
		rst_n = 1;
		@(negedge clk)
		scan_en = 1;

		repeat (100) begin
			@(negedge clk)
			scan_en = $random | $random | $random;
		end
		$finish;
	end



endmodule

lab4/Lab4_Team25_Built_In_Self_Test/Build_In_Self_Test.vcd
$date
    Nov  6, 2022  19:26:40
$end
$version
    TOOL:	ncsim	15.20-s039
$end
$timescale
    1 ps
$end

$scope module Built_in_Self_Test_t $end
$var reg       1 !    clk  $end
$var reg       1 "    rst_n  $end
$var reg       1 #    scan_en  $end
$var wire      1 $    scan_in  $end
$var wire      1 %    scan_out  $end

$scope module M1 $end
$var wire      1 &    clk  $end
$var wire      1 '    rst_n  $end
$var wire      1 (    scan_en  $end
$var wire      1 $    scan_in  $end
$var wire      1 %    scan_out  $end

$scope module M1 $end
$var wire      1 &    clk  $end
$var wire      1 '    rst_n  $end
$var reg       8 )    out [7:0] $end
$upscope $end


$scope module M2 $end
$var wire      1 &    clk  $end
$var wire      1 '    rst_n  $end
$var wire      1 $    scan_in  $end
$var wire      1 (    scan_en  $end
$var reg       1 *    scan_out  $end
$var reg       8 +    p [7:0] $end
$var reg       8 ,    sdff [7:0] $end
$upscope $end

$upscope $end

$upscope $end

$enddefinitions $end
$dumpvars
0!
0"
0#
x$
x%
0&
0'
0(
bx )
x*
bx +
bx ,
$end
#5000
1!
1&
b10111101 )
b0 ,
b0 +
0*
0%
1$
#10000
0!
1"
1'
0&
#15000
1!
1&
b111101 )
b1111101 )
b1111001 )
b1111011 )
#20000
0!
1#
1(
0&
#25000
1!
1&
b11111011 )
b11110011 )
b11110111 )
b11110110 )
b10000000 ,
0$
#30000
0!
0&
#35000
1!
1&
b11100110 )
b11101110 )
b11101100 )
b11101101 )
b1000000 ,
1$
#40000
0!
0&
#45000
1!
1&
b11001101 )
b11011101 )
b11011001 )
b11011011 )
b10100000 ,
#50000
0!
0&
#55000
1!
1&
b10011011 )
b10111011 )
b10110011 )
b10110111 )
b11010000 ,
#60000
0!
0&
#65000
1!
1&
b110111 )
b1110111 )
b1100111 )
b1101111 )
b11101000 ,
b1110000 +
#70000
0!
0&
#75000
1!
1&
b11101111 )
b11001111 )
b11011111 )
b11110100 ,
b111100 +
#80000
0!
0&
#85000
1!
1&
b10011111 )
b10111111 )
b10111110 )
b11111010 ,
b10010110 +
0$
#90000
0!
0&
#95000
1!
1&
b111110 )
b1111110 )
b1111100 )
b1111101 ,
b1011011 +
1*
1%
#100000
0!
0&
#105000
1!
1&
b11111100 )
b11111000 )
b111110 ,
b101010 +
0*
0%
#110000
0!
0&
#115000
1!
1&
b11110000 )
b11111 ,
b1111 +
1*
1%
#120000
0!
0&
#125000
1!
1&
b11100000 )
b11100001 )
b1111 ,
b0 +
1$
#130000
0!
0&
#135000
1!
1&
b11000001 )
b11000011 )
b10000111 ,
b111000 +
#140000
0!
0&
#145000
1!
1&
b10000011 )
b10000111 )
b10000110 )
b11000011 ,
b100100 +
0$
#150000
0!
0&
#155000
1!
1&
b110 )
b1110 )
b1100 )
b1101 )
b1100001 ,
b110 +
1$
#160000
0!
0&
#165000
1!
1&
b11101 )
b11001 )
b11011 )
b11010 )
b10110000 ,
b0 +
0*
0%
0$
#170000
0!
0&
#175000
1!
1&
b111010 )
b110010 )
b110110 )
b110100 )
b1011000 ,
b101000 +
#180000
0!
0&
#185000
1!
1&
b1110100 )
b1100100 )
b1101100 )
b1101000 )
b1101001 )
b101100 ,
b11000 +
1$
#190000
0!
0#
0(
0&
#195000
1!
1&
b11101001 )
b11001001 )
b11011001 )
b11010001 )
b11010011 )
b11000 ,
b1000 +
#200000
0!
1#
1(
0&
#205000
1!
1&
b10010011 )
b10110011 )
b10100011 )
b10100111 )
b10100110 )
b10001100 ,
b1100000 +
0$
#210000
0!
0&
#215000
1!
1&
b100110 )
b1100110 )
b1000110 )
b1001110 )
b1001100 )
b1001101 )
b1000110 ,
b11000 +
1$
#220000
0!
0#
0(
0&
#225000
1!
1&
b11001101 )
b10001101 )
b10011101 )
b10011001 )
b10011011 )
b10011010 )
b11000 ,
b1000 +
0$
#230000
0!
1#
1(
0&
#235000
1!
1&
b11010 )
b111010 )
b110010 )
b110110 )
b110100 )
b110101 )
b1100 ,
b0 +
1$
#240000
0!
0&
#245000
1!
1&
b1110101 )
b1100101 )
b1101101 )
b1101001 )
b1101011 )
b10000110 ,
b110000 +
#250000
0!
0&
#255000
1!
1&
b11101011 )
b11001011 )
b11011011 )
b11010011 )
b11010111 )
b11010110 )
b11000011 ,
b100100 +
1*
1%
0$
#260000
0!
0&
#265000
1!
1&
b10010110 )
b10110110 )
b10100110 )
b10101110 )
b10101100 )
b10101101 )
b1100001 ,
b110 +
1$
#270000
0!
0&
#275000
1!
1&
b101101 )
b1101101 )
b1001101 )
b1011101 )
b1011001 )
b1011011 )
b10110000 ,
b0 +
0*
0%
#280000
0!
0&
#285000
1!
1&
b11011011 )
b10011011 )
b10111011 )
b10110011 )
b10110111 )
b10110110 )
b11011000 ,
b1101000 +
0$
#290000
0!
0&
#295000
1!
1&
b110110 )
b1110110 )
b1100110 )
b1101110 )
b1101100 )
b1101101 )
b1101100 ,
b1001000 +
1$
#300000
0!
0&
#305000
1!
1&
b11101101 )
b11001101 )
b11011101 )
b11011001 )
b11011011 )
b11011010 )
b10110110 ,
b1000010 +
0$
#310000
0!
0&
#315000
1!
1&
b10011010 )
b10111010 )
b10110010 )
b10110110 )
b10110100 )
b10110101 )
b1011011 ,
b110111 +
1*
1%
1$
#320000
0!
0#
0(
0&
#325000
1!
1&
b110101 )
b1110101 )
b1100101 )
b1101101 )
b1101001 )
b1101011 )
b1101010 )
b110111 ,
b10101 +
0$
#330000
0!
1#
1(
0&
#335000
1!
1&
b11101010 )
b11001010 )
b11011010 )
b11010010 )
b11010110 )
b11010100 )
b11011 ,
b1011 +
#340000
0!
0&
#345000
1!
1&
b10010100 )
b10110100 )
b10100100 )
b10101100 )
b10101000 )
b1101 ,
b0 +
#350000
0!
0&
#355000
1!
1&
b101000 )
b1101000 )
b1001000 )
b1011000 )
b1010000 )
b110 ,
0*
0%
#360000
0!
0&
#365000
1!
1&
b11010000 )
b10010000 )
b10110000 )
b10100000 )
b11 ,
1*
1%
#370000
0!
0&
#375000
1!
1&
b100000 )
b1100000 )
b1000000 )
b1000001 )
b1 ,
1$
#380000
0!
0#
0(
0&
#385000
1!
1&
b11000001 )
b10000001 )
b10000011 )
b10000010 )
b0 ,
0*
0%
0$
#390000
0!
1#
1(
0&
#395000
1!
1&
b10 )
b110 )
b100 )
#400000
0!
0&
#405000
1!
1&
b1100 )
b1000 )
b1001 )
1$
#410000
0!
0&
#415000
1!
1&
b11001 )
b10001 )
b10011 )
b10000000 ,
#420000
0!
0&
#425000
1!
1&
b110011 )
b100011 )
b100111 )
b11000000 ,
#430000
0!
0&
#435000
1!
1&
b1100111 )
b1000111 )
b1001111 )
b1001110 )
b11100000 ,
0$
#440000
0!
0&
#445000
1!
1&
b11001110 )
b10001110 )
b10011110 )
b10011100 )
b10011101 )
b1110000 ,
1$
#450000
0!
0&
#455000
1!
1&
b11101 )
b111101 )
b111001 )
b111011 )
b10111000 ,
b1011000 +
#460000
0!
0&
#465000
1!
1&
b1111011 )
b1110011 )
b1110111 )
b1110110 )
b11011100 ,
b10011100 +
0$
#470000
0!
0&
#475000
1!
1&
b11110110 )
b11100110 )
b11101110 )
b11101100 )
b1101110 ,
b1010100 +
#480000
0!
0&
#485000
1!
1&
b11001100 )
b11011100 )
b11011000 )
b11011001 )
b110111 ,
b10101 +
1*
1%
1$
#490000
0!
0&
#495000
1!
1&
b10011001 )
b10111001 )
b10110001 )
b10110011 )
b10110010 )
b10011011 ,
b1100011 +
0$
#500000
0!
0&
#505000
1!
1&
b110010 )
b1110010 )
b1100010 )
b1100110 )
b1100100 )
b1001101 ,
b110100 +
#510000
0!
0&
#515000
1!
1&
b11100100 )
b11000100 )
b11001100 )
b11001000 )
b11001001 )
b100110 ,
b1100 +
0*
0%
1$
#520000
0!
0&
#525000
1!
1&
b10001001 )
b10011001 )
b10010001 )
b10010011 )
b10010010 )
b10010011 ,
b11011 +
1*
1%
0$
#530000
0!
0&
#535000
1!
1&
b10010 )
b110010 )
b100010 )
b100110 )
b100100 )
b1001001 ,
b100100 +
#540000
0!
0&
#545000
1!
1&
b1100100 )
b1000100 )
b1001100 )
b1001000 )
b1001001 )
b100100 ,
b1000 +
0*
0%
1$
#550000
0!
0&
#555000
1!
1&
b11001001 )
b10001001 )
b10011001 )
b10010001 )
b10010011 )
b10010010 ,
b10010 +
#560000
0!
0&
#565000
1!
1&
b10011 )
b110011 )
b100011 )
b100111 )
b100110 )
b11001001 ,
b1101100 +
1*
1%
0$
#570000
0!
0&
#575000
1!
1&
b1100110 )
b1000110 )
b1001110 )
b1001100 )
b1100100 ,
b11000 +
0*
0%
#580000
0!
0#
0(
0&
#585000
1!
1&
b11001100 )
b10001100 )
b10011100 )
b10011000 )
b11000 ,
b1000 +
#590000
0!
1#
1(
0&
#595000
1!
1&
b11000 )
b111000 )
b110000 )
b1100 ,
b0 +
#600000
0!
0&
#605000
1!
1&
b1110000 )
b1100000 )
b110 ,
#610000
0!
0&
#615000
1!
1&
b11100000 )
b11000000 )
b11 ,
1*
1%
#620000
0!
0#
0(
0&
#625000
1!
1&
b10000000 )
b10000001 )
b0 ,
0*
0%
1$
#630000
0!
1#
1(
0&
#635000
1!
1&
b1 )
b11 )
b10000000 ,
#640000
0!
0&
#645000
1!
1&
b111 )
b11000000 ,
#650000
0!
0&
#655000
1!
1&
b1111 )
b1110 )
b11100000 ,
0$
#660000
0!
0#
0(
0&
#665000
1!
1&
b11110 )
b11100 )
b11101 )
b0 ,
1$
#670000
0!
1#
1(
0&
#675000
1!
1&
b111101 )
b111001 )
b111011 )
b111010 )
b10000000 ,
0$
#680000
0!
0&
#685000
1!
1&
b1111010 )
b1110010 )
b1110110 )
b1110100 )
b1000000 ,
#690000
0!
0&
#695000
1!
1&
b11110100 )
b11100100 )
b11101100 )
b11101000 )
b11101001 )
b100000 ,
1$
#700000
0!
0&
#705000
1!
1&
b11001001 )
b11011001 )
b11010001 )
b11010011 )
b11010010 )
b10010000 ,
0$
#710000
0!
0&
#715000
1!
1&
b10010010 )
b10110010 )
b10100010 )
b10100110 )
b10100100 )
b1001000 ,
b100000 +
#720000
0!
0&
#725000
1!
1&
b100100 )
b1100100 )
b1000100 )
b1001100 )
b1001000 )
b100100 ,
b1000 +
#730000
0!
0#
0(
0&
#735000
1!
1&
b11001000 )
b10001000 )
b10011000 )
b10010000 )
b10010001 )
b1000 ,
b0 +
1$
#740000
0!
1#
1(
0&
#745000
1!
1&
b10001 )
b110001 )
b100001 )
b100011 )
b10000100 ,
b100000 +
#750000
0!
0&
#755000
1!
1&
b1100011 )
b1000011 )
b1000111 )
b11000010 ,
b11000 +
#760000
0!
0&
#765000
1!
1&
b11000111 )
b10000111 )
b10001111 )
b10001110 )
b11100001 ,
b1110 +
1*
1%
0$
#770000
0!
0&
#775000
1!
1&
b1110 )
b11110 )
b11100 )
b1110000 ,
b0 +
0*
0%
#780000
0!
0&
#785000
1!
1&
b111100 )
b111000 )
b111000 ,
b11000 +
#790000
0!
0&
#795000
1!
1&
b1111000 )
b1110000 )
b1110001 )
b11100 ,
b1100 +
1$
#800000
0!
0&
#805000
1!
1&
b11110001 )
b11100001 )
b11100011 )
b11100010 )
b10001110 ,
b1110000 +
0$
#810000
0!
0&
#815000
1!
1&
b11000010 )
b11000110 )
b11000100 )
b1000111 ,
b11100 +
1*
1%
#820000
0!
0#
0(
0&
#825000
1!
1&
b10000100 )
b10001100 )
b10001000 )
b11100 ,
b1100 +
0*
0%
#830000
0!
1#
1(
0&
#835000
1!
1&
b1000 )
b11000 )
b10000 )
b1110 ,
b0 +
#840000
0!
0&
#845000
1!
1&
b110000 )
b100000 )
b111 ,
1*
1%
#850000
0!
0&
#855000
1!
1&
b1100000 )
b1000000 )
b11 ,
#860000
0!
0&
#865000
1!
1&
b11000000 )
b10000000 )
b1 ,
#870000
0!
0&
#875000
1!
1&
b0 )
b1 )
b0 ,
0*
0%
1$
#880000
0!
0&
#885000
1!
1&
b11 )
b10 )
b10000000 ,
0$
#890000
0!
0&
#895000
1!
1&
b110 )
b100 )
b101 )
b1000000 ,
1$
#900000
0!
0&
#905000
1!
1&
b1101 )
b1001 )
b1011 )
b10100000 ,
#910000
0!
0&
#915000
1!
1&
b11011 )
b10011 )
b10111 )
b10110 )
b11010000 ,
0$
#920000
0!
0&
#925000
1!
1&
b110110 )
b100110 )
b101110 )
b101100 )
b1101000 ,
b110000 +
#930000
0!
0&
#935000
1!
1&
b1101100 )
b1001100 )
b1011100 )
b1011000 )
b110100 ,
b1100 +
#940000
0!
0&
#945000
1!
1&
b11011000 )
b10011000 )
b10111000 )
b10110000 )
b10110001 )
b11010 ,
b1010 +
1$
#950000
0!
0&
#955000
1!
1&
b110001 )
b1110001 )
b1100001 )
b1100011 )
b10001101 ,
b1101000 +
1*
1%
#960000
0!
0#
0(
0&
#965000
1!
1&
b11100011 )
b11000011 )
b11000111 )
b1101000 ,
b110000 +
0*
0%
#970000
0!
1#
1(
0&
#975000
1!
1&
b10000111 )
b10001111 )
b10110100 ,
b101100 +
#980000
0!
0&
#985000
1!
1&
b1111 )
b11111 )
b11110 )
b11011010 ,
b10000010 +
0$
#990000
0!
0&
#995000
1!
1&
b111110 )
b111100 )
b111101 )
b1101101 ,
b1001110 +
1*
1%
1$
#1000000
0!
0#
0(
0&
#1005000
1!
1&
b1111101 )
b1111001 )
b1111011 )
b1111010 )
b1001110 ,
b111000 +
0*
0%
0$
#1010000
0!
0&
#1015000
1!
1&
b11111010 )
b11110010 )
b11110110 )
b11110100 )
b111000 ,
b11000 +
#1020000
0!
1#
