lab5/Lab5_Team25_Booth_Multiplier_4bit/Lab5_Team25_Booth_Multiplier_4bit.v
`timescale 1ns/1ps

module Booth_Multiplier_4bit(clk, rst_n, start, a, b, p);

    input clk, rst_n;
    input start;
    input signed [3:0] a, b;
    output signed [7:0] p;
    
    parameter WAIT = 2'b00;
    parameter CAL = 2'b01;
    parameter FINISH = 2'b10;

    reg [9:0] P, A, S, next_P;

    reg [2:0] count, next_count;
    wire [9:0] ps, pa;

    reg [1:0] state, next_state;

    reg [7:0] p;

    wire signed [4:0] aaa;

    assign ps = P+S;
    assign pa = P+A;

    assign aaa = a;

    always @(*) begin
        if (state == WAIT) begin
            p = 8'b0;
            if (start == 1'b1) begin
                next_state = CAL;
                next_count = 3'b0;
                A = {aaa, 5'b0};
                S = {-aaa, 5'b0};
                next_P = {5'b0, b, 1'b0};
            end else begin
                next_state = WAIT;
            end
        end else if (state == CAL) begin
            p = 8'b0;
            next_count = count + 1'b1;
            if (P[1:0] == 2'b10) begin
                next_P = {ps[9], ps[9:1]};
            end else if (P[1:0] == 2'b01) begin
                next_P = {pa[9], pa[9:1]};
            end else begin
                next_P = {P[9], P[9:1]};
            end
            if (count == 3'b11) begin
                next_state = FINISH;
                next_count = 3'b0;
            end else begin
                next_state = CAL;
            end
        end else if (state == FINISH) begin
            p = P[8:1];
            next_count = count + 1'b1;
            if (count == 3'b1) begin
                next_state = WAIT;
            end else begin
                next_state = FINISH;
            end
        end
    end

    always @(posedge clk) begin
        if (rst_n == 1'b0) begin
            state <= WAIT;
            count <= 3'b0;
            P <= 8'b0;
        end else begin
            state <= next_state;
            count <= next_count;
            P <= next_P;
        end
    end
    
endmodule

lab5/Lab5_Team25_Booth_Multiplier_4bit/Lab5_Team25_Booth_Multiplier_4bit_t.v
`timescale 1ns/1ps

module q1_t;
    
    reg clk = 0;
    reg rst_n = 0;
    reg start = 0;
    reg [3:0] a, b;

    wire [7:0] p;
    wire done;

    parameter cyc = 10;
    always # (cyc / 2) clk = ~clk;

    Booth_Multiplier_4bit S1(
        .clk(clk),
        .rst_n(rst_n),
        .start(start),
        .a(a),
        .b(b),
        .p(p)
    );

    initial begin
        $dumpfile("Booth_Multiplier.vcd");
        $dumpvars("+all");
    end

    initial begin
        @(negedge clk) 
        rst_n = 0;
        @(negedge clk) 
        rst_n = 1;
        start = 1;
        repeat (10) begin
            {a, b} = $random;
            repeat (7) begin
                @(negedge clk);
            end
        end
        $finish;
    end

endmodule

lab5/Lab5_Team25_Booth_Multiplier_4bit/Booth_Multiplier.vcd
$date
    Nov 24, 2022  20:04:23
$end
$version
    TOOL:	ncsim	15.20-s039
$end
$timescale
    1 ps
$end

$scope module q1_t $end
$var reg       1 !    clk  $end
$var reg       1 "    rst_n  $end
$var reg       1 #    start  $end
$var reg       4 $    a [3:0] $end
$var reg       4 %    b [3:0] $end
$var wire      8 &    p [7:0] $end
$var wire      1 '    done  $end
$var parameter 32 (    cyc  $end

$scope module S1 $end
$var wire      1 )    clk  $end
$var wire      1 *    rst_n  $end
$var wire      1 +    start  $end
$var wire      4 ,    a [3:0] $end
$var wire      4 -    b [3:0] $end
$var reg       8 .    p [7:0] $end
$var parameter  2 /    WAIT  $end
$var parameter  2 0    CAL  $end
$var parameter  2 1    FINISH  $end
$var reg      10 2    P [9:0] $end
$var reg      10 3    A [9:0] $end
$var reg      10 4    S [9:0] $end
$var reg      10 5    next_P [9:0] $end
$var reg       3 6    count [2:0] $end
$var reg       3 7    next_count [2:0] $end
$var wire     10 8    ps [9:0] $end
$var wire     10 9    pa [9:0] $end
$var reg       2 :    state [1:0] $end
$var reg       2 ;    next_state [1:0] $end
$var wire      5 <    aaa [4:0] $end
$upscope $end

$upscope $end

$enddefinitions $end
$dumpvars
b10 1
b1 0
b0 /
b1010 (
0!
0"
0#
bx $
bx %
bx &
z'
0)
0*
0+
bx ,
bx -
bx .
bx 2
bx 3
bx 4
bx 5
bx 6
bx 7
bx 8
bx 9
bx :
bx ;
bx <
$end
#5000
1!
1)
b0 :
b0 6
b0 2
b0 .
b0 ;
b0 &
#10000
0!
0)
#15000
1!
1)
#20000
0!
1"
1#
b100 %
b10 $
b10 ,
b100 -
1+
1*
0)
b1 ;
b0 7
bx00000 3
bx00000 4
b1000 5
b10 <
b1000000 3
b1111000000 4
b1111000000 8
b1000000 9
#25000
1!
1)
b1 :
b1000 2
b1 7
b100 5
b1001000 9
b1111001000 8
#30000
0!
0)
#35000
1!
1)
b1 6
b100 2
b10 7
b10 5
b1000100 9
b1111000100 8
#40000
0!
0)
#45000
1!
1)
b10 6
b10 2
b11 7
b1111100010 5
b1000010 9
b1111000010 8
b1111100001 5
#50000
0!
0)
#55000
1!
1)
b11 6
b1111100001 2
b100 7
b100001 5
b10 ;
b0 7
b100001 9
b1110100001 8
b100 7
b10000 5
b0 7
#60000
0!
0)
#65000
1!
1)
b10 :
b0 6
b10000 2
b1000 .
b1 7
b1010000 9
b1111010000 8
b1000 &
#70000
0!
0)
#75000
1!
1)
b1 6
b10 7
b0 ;
#80000
0!
0)
#85000
1!
1)
b0 :
b10 6
b0 .
b1 ;
b0 7
b1000 5
b0 &
#90000
0!
b1 %
b1000 $
b1000 ,
b1 -
0)
b10 5
b11000 <
b1100000000 3
b100000000 4
b100010000 8
b1100010000 9
#95000
1!
1)
b1 :
b0 6
b10 2
b1 7
b10001000 5
b1100000010 9
b100000010 8
b10000001 5
#100000
0!
0)
#105000
1!
1)
b1 6
b10000001 2
b10 7
b1110000001 5
b1110000001 9
b110000001 8
b1111000000 5
#110000
0!
0)
#115000
1!
1)
b10 6
b1111000000 2
b11 7
b1111100000 5
b1011000000 9
b11000000 8
#120000
0!
0)
#125000
1!
1)
b11 6
b1111100000 2
b100 7
b1111110000 5
b10 ;
b0 7
b1011100000 9
b11100000 8
b100 7
b0 7
#130000
0!
0)
#135000
1!
1)
b10 :
b0 6
b1111110000 2
b11111000 .
b1 7
b1011110000 9
b11110000 8
b11111000 &
#140000
0!
0)
#145000
1!
1)
b1 6
b10 7
b0 ;
#150000
0!
0)
#155000
1!
1)
b0 :
b10 6
b0 .
b1 ;
b0 7
b10 5
b0 &
#160000
0!
b1001 %
b0 $
b0 ,
b1001 -
0)
b10010 5
b0 <
b0 3
b0 4
b1111110000 8
b1111110000 9
#165000
1!
1)
b1 :
b0 6
b10010 2
b1 7
b1111111000 5
b10010 9
b10010 8
b1001 5
#170000
0!
0)
#175000
1!
1)
b1 6
b1001 2
b10 7
b1001 9
b1001 8
b100 5
#180000
0!
0)
#185000
1!
1)
b10 6
b100 2
b11 7
b10 5
b100 9
b100 8
#190000
0!
0)
#195000
1!
1)
b11 6
b10 2
b100 7
b10 ;
b0 7
b10 9
b10 8
b100 7
b1 5
b0 7
#200000
0!
0)
#205000
1!
1)
b10 :
b0 6
b1 2
b1 7
b1 9
b1 8
#210000
0!
0)
#215000
1!
1)
b1 6
b10 7
b0 ;
#220000
0!
0)
#225000
1!
1)
b0 :
b10 6
b1 ;
b0 7
b10010 5
#230000
0!
b11 %
b110 $
b110 ,
b11 -
0)
b110 5
b110 <
b11000000 3
b1101000000 4
b1101000001 8
b11000001 9
#235000
1!
1)
b1 :
b0 6
b110 2
b1 7
b1110100000 5
b11000110 9
b1101000110 8
b1110100011 5
#240000
0!
0)
#245000
1!
1)
b1 6
b1110100011 2
b10 7
b1111010001 5
b1100011 9
b1011100011 8
#250000
0!
0)
#255000
1!
1)
b10 6
b1111010001 2
b11 7
b110001 5
b10010001 9
b1100010001 8
b1001000 5
#260000
0!
0)
#265000
1!
1)
b11 6
b1001000 2
b100 7
b100100 5
b10 ;
b0 7
b100001000 9
b1110001000 8
b100 7
b0 7
#270000
0!
0)
#275000
1!
1)
b10 :
b0 6
b100100 2
b10010 .
b1 7
b11100100 9
b1101100100 8
b10010 &
#280000
0!
0)
#285000
1!
1)
b1 6
b10 7
b0 ;
#290000
0!
0)
#295000
1!
1)
b0 :
b10 6
b0 .
b1 ;
b0 7
b110 5
b0 &
#300000
0!
b1101 %
b0 $
b0 ,
b1101 -
0)
b11010 5
b0 <
b0 3
b0 4
b100100 8
b100100 9
#305000
1!
1)
b1 :
b0 6
b11010 2
b1 7
b10010 5
b11010 9
b11010 8
b1101 5
#310000
0!
0)
#315000
1!
1)
b1 6
b1101 2
b10 7
b1101 9
b1101 8
b110 5
#320000
0!
0)
#325000
1!
1)
b10 6
b110 2
b11 7
b110 9
b110 8
b11 5
#330000
0!
0)
#335000
1!
1)
b11 6
b11 2
b100 7
b1 5
b10 ;
b0 7
b11 9
b11 8
b100 7
b0 7
#340000
0!
0)
#345000
1!
1)
b10 :
b0 6
b1 2
b1 7
b1 9
b1 8
#350000
0!
0)
#355000
1!
1)
b1 6
b10 7
b0 ;
#360000
0!
0)
#365000
1!
1)
b0 :
b10 6
b1 ;
b0 7
b11010 5
#370000
0!
b1000 $
b1000 ,
0)
b11000 <
b1100000000 3
b100000000 4
b100000001 8
b1100000001 9
#375000
1!
1)
b1 :
b0 6
b11010 2
b1 7
b10000000 5
b1100011010 9
b100011010 8
b10001101 5
#380000
0!
0)
#385000
1!
1)
b1 6
b10001101 2
b10 7
b1110001101 5
b1110001101 9
b110001101 8
b1111000110 5
#390000
0!
0)
#395000
1!
1)
b10 6
b1111000110 2
b11 7
b11000110 5
b1011000110 9
b11000110 8
b1100011 5
#400000
0!
0)
#405000
1!
1)
b11 6
b1100011 2
b100 7
b110001 5
b10 ;
b0 7
b1101100011 9
b101100011 8
b100 7
b0 7
#410000
0!
0)
#415000
1!
1)
b10 :
b0 6
b110001 2
b11000 .
b1 7
b1100110001 9
b100110001 8
b11000 &
#420000
0!
0)
#425000
1!
1)
b1 6
b10 7
b0 ;
#430000
0!
0)
#435000
1!
1)
b0 :
b10 6
b0 .
b1 ;
b0 7
b11010 5
b0 &
#440000
0!
b101 %
b110 $
b110 ,
b101 -
0)
b1010 5
b110 <
b11000000 3
b1101000000 4
b1101110001 8
b11110001 9
#445000
1!
1)
b1 :
b0 6
b1010 2
b1 7
b1110111000 5
b11001010 9
b1101001010 8
b1110100101 5
#450000
0!
0)
#455000
1!
1)
b1 6
b1110100101 2
b10 7
b1100101 5
b1100101 9
b1011100101 8
b110010 5
#460000
0!
0)
#465000
1!
1)
b10 6
b110010 2
b11 7
b1101110010 5
b11110010 9
b1101110010 8
b1110111001 5
#470000
0!
0)
#475000
1!
1)
b11 6
b1110111001 2
b100 7
b1111001 5
b10 ;
b0 7
b1111001 9
b1011111001 8
b100 7
b111100 5
b0 7
#480000
0!
0)
#485000
1!
1)
b10 :
b0 6
b111100 2
b11110 .
b1 7
b11111100 9
b1101111100 8
b11110 &
#490000
0!
0)
#495000
1!
1)
b1 6
b10 7
b0 ;
#500000
0!
0)
#505000
1!
1)
b0 :
b10 6
b0 .
b1 ;
b0 7
b1010 5
b0 &
#510000
0!
b10 %
b1 $
b1 ,
b10 -
0)
b100 5
b1 <
b100000 3
b1111100000 4
b11100 8
b1011100 9
#515000
1!
1)
b1 :
b0 6
b100 2
b1 7
b10 5
b100100 9
b1111100100 8
#520000
0!
0)
#525000
1!
1)
b1 6
b10 2
b10 7
b1111110010 5
b100010 9
b1111100010 8
b1111110001 5
#530000
0!
0)
#535000
1!
1)
b10 6
b1111110001 2
b11 7
b10001 5
b10001 9
b1111010001 8
b1000 5
#540000
0!
0)
#545000
1!
1)
b11 6
b1000 2
b100 7
b100 5
b10 ;
b0 7
b101000 9
b1111101000 8
b100 7
b0 7
#550000
0!
0)
#555000
1!
1)
b10 :
b0 6
b100 2
b10 .
b1 7
b100100 9
b1111100100 8
b10 &
#560000
0!
0)
#565000
1!
1)
b1 6
b10 7
b0 ;
#570000
0!
0)
#575000
1!
1)
b0 :
b10 6
b0 .
b1 ;
b0 7
b0 &
#580000
0!
b1 %
b0 $
b0 ,
b1 -
0)
b10 5
b0 <
b0 3
b0 4
b100 8
b100 9
#585000
1!
1)
b1 :
b0 6
b10 2
b1 7
b10 9
b10 8
b1 5
#590000
0!
0)
#595000
1!
1)
b1 6
b1 2
b10 7
b1 9
b1 8
b0 5
#600000
0!
0)
#605000
1!
1)
b10 6
b0 2
b11 7
b0 9
b0 8
#610000
0!
0)
#615000
1!
1)
b11 6
b100 7
b10 ;
b0 7
#620000
0!
0)
#625000
1!
1)
b10 :
b0 6
b1 7
#630000
0!
0)
#635000
1!
1)
b1 6
b10 7
b0 ;
#640000
0!
0)
#645000
1!
1)
b0 :
b10 6
b1 ;
b0 7
b10 5
#650000
0!
b1101 %
b1101 -
0)
b11010 5
#655000
1!
1)
b1 :
b0 6
b11010 2
b1 7
b0 5
b11010 9
b11010 8
b1101 5
#660000
0!
0)
#665000
1!
1)
b1 6
b1101 2
b10 7
b1101 9
b1101 8
b110 5
#670000
0!
0)
#675000
1!
1)
b10 6
b110 2
b11 7
b110 9
b110 8
b11 5
#680000
0!
0)
#685000
1!
1)
b11 6
b11 2
b100 7
b1 5
b10 ;
b0 7
b11 9
b11 8
b100 7
b0 7
#690000
0!
0)
#695000
1!
1)
b10 :
b0 6
b1 2
b1 7
b1 9
b1 8
#700000
0!
0)
#705000
1!
1)
b1 6
b10 7
b0 ;
#710000
0!
0)
#715000
1!
1)
b0 :
b10 6
b1 ;
b0 7
b11010 5
