lab4/Lab4_Team25_Scan_Chain_Design/Lab4_Team25_Scan_Chain_Design.v
`timescale 1ns/1ps

module Scan_Chain_Design(clk, rst_n, scan_in, scan_en, scan_out);
    input clk;
    input rst_n;
    input scan_in;
    input scan_en;
    output reg scan_out;

    reg [7:0] p;
    reg [7:0] sdff;

    always @(*) begin
        p = sdff[3:0]*sdff[7:4];
    end

   // always @(*) begin
   //     scan_out = sdff[0];
   // end

    always @(posedge clk) begin
        if (!rst_n) begin
            sdff <= 8'b00000000;
        end else begin
            if (scan_en) begin
                {sdff, scan_out} <= {scan_in, sdff};
            end else begin
				{sdff, scan_out} <= {1'b0, p};
            end
        end
    end

    always @(negedge clk) begin
        $display(
            "rst_n: %b | scan_in: %b | scan_en: %b | a: %d | b: %d | p: %d | sdff: %b",
            rst_n, scan_in, scan_en, sdff[7:4], sdff[3:0], p, sdff[7:0]
        );
    end

endmodule

lab4/Lab4_Team25_Scan_Chain_Design/test.v
`timescale 1ns / 1ps

module Lab4_Team21_Scan_Chain_Design_t();
    reg clk, rst_n, scan_en, scan_in;
    wire scan_out;

    Scan_Chain_Design m0 (
        .clk(clk),
        .rst_n(rst_n),
        .scan_en(scan_en),
        .scan_in(scan_in),
        .scan_out(scan_out)
    );

    always #10 clk = ~clk;

    reg [3:0] a = 4'b1011;
    reg [3:0] b = 4'b0111;

    initial begin
        $dumpfile("test.vcd");
        $dumpvars("+all");
    end

    initial begin
        clk = 0; rst_n = 0; scan_in = 0; scan_en = 0;
        #20 rst_n = 1; scan_en = 1; scan_in = a[0];
        #20 scan_in = a[1];
        #20 scan_in = a[2];
        #20 scan_in = a[3];
        #20 scan_in = b[0];
        #20 scan_in = b[1];
        #20 scan_in = b[2];
        #20 scan_in = b[3];
        #20 scan_en = 0;
        #20 scan_en = 1;
        #300 
        rst_n = 0; scan_in = 0; scan_en = 0;
        #20 rst_n = 1; scan_en = 1; scan_in = 0;
        #20 scan_in = 0;
        #20 scan_in = 0;
        #20 scan_in = 1;
        #20 scan_in = 1;
        #20 scan_in = 1;
        #20 scan_in = 1;
        #20 scan_in = 1;
        #20 scan_en = 0;
        #20 scan_en = 1;
        #300 $finish;
    end
endmodule

lab4/Lab4_Team25_Scan_Chain_Design/test.vcd
$date
    Nov  9, 2022  23:29:50
$end
$version
    TOOL:	ncsim	15.20-s039
$end
$timescale
    1 ps
$end

$scope module Lab4_Team21_Scan_Chain_Design_t $end
$var reg       1 !    clk  $end
$var reg       1 "    rst_n  $end
$var reg       1 #    scan_en  $end
$var reg       1 $    scan_in  $end
$var wire      1 %    scan_out  $end
$var reg       4 &    a [3:0] $end
$var reg       4 '    b [3:0] $end

$scope module m0 $end
$var wire      1 (    clk  $end
$var wire      1 )    rst_n  $end
$var wire      1 *    scan_in  $end
$var wire      1 +    scan_en  $end
$var reg       1 ,    scan_out  $end
$var reg       8 -    p [7:0] $end
$var reg       8 .    sdff [7:0] $end
$upscope $end

$upscope $end

$enddefinitions $end
$dumpvars
0!
0"
0#
0$
x%
b1011 &
b111 '
0(
0)
0*
0+
x,
bx -
bx .
$end
#10000
1!
1(
b0 .
b0 -
#20000
1"
1#
1$
0!
1*
1+
1)
0(
#30000
1!
1(
0,
b10000000 .
0%
#40000
0!
0(
#50000
1!
1(
b11000000 .
#60000
0$
0!
0*
0(
#70000
1!
1(
b1100000 .
#80000
1$
0!
1*
0(
#90000
1!
1(
b10110000 .
#100000
0!
0(
#110000
1!
1(
b11011000 .
b1101000 -
#120000
0!
0(
#130000
1!
1(
b11101100 .
b10101000 -
#140000
0!
0(
#150000
1!
1(
b11110110 .
b1011010 -
#160000
0$
0!
0*
0(
#170000
1!
1(
b1111011 .
b1001101 -
#180000
0#
0!
0+
0(
#190000
1!
1(
1,
b100110 .
b1100 -
1%
#200000
1#
0!
1+
0(
#210000
1!
1(
0,
b10011 .
b11 -
0%
#220000
0!
0(
#230000
1!
1(
1,
b1001 .
b0 -
1%
#240000
0!
0(
#250000
1!
1(
b100 .
#260000
0!
0(
#270000
1!
1(
0,
b10 .
0%
#280000
0!
0(
#290000
1!
1(
b1 .
#300000
0!
0(
#310000
1!
1(
1,
b0 .
1%
#320000
0!
0(
#330000
1!
1(
0,
0%
#340000
0!
0(
#350000
1!
1(
#360000
0!
0(
#370000
1!
1(
#380000
0!
0(
#390000
1!
1(
#400000
0!
0(
#410000
1!
1(
#420000
0!
0(
#430000
1!
1(
#440000
0!
0(
#450000
1!
1(
#460000
0!
0(
#470000
1!
1(
#480000
0!
0(
#490000
1!
1(
#500000
0"
0#
0!
0+
0)
0(
#510000
1!
1(
#520000
1"
1#
0!
1+
1)
0(
#530000
1!
1(
#540000
0!
0(
#550000
1!
1(
#560000
0!
0(
#570000
1!
1(
#580000
1$
0!
1*
0(
#590000
1!
1(
b10000000 .
#600000
0!
0(
#610000
1!
1(
b11000000 .
#620000
0!
0(
#630000
1!
1(
b11100000 .
#640000
0!
0(
#650000
1!
1(
b11110000 .
#660000
0!
0(
#670000
1!
1(
b11111000 .
b1111000 -
#680000
0#
0!
0+
0(
#690000
1!
1(
b111100 .
b100100 -
#700000
1#
0!
1+
0(
#710000
1!
1(
b10011110 .
b1111110 -
#720000
0!
0(
#730000
1!
1(
b11001111 .
b10110100 -
#740000
0!
0(
#750000
1!
1(
1,
b11100111 .
b1100010 -
1%
#760000
0!
0(
#770000
1!
1(
b11110011 .
b101101 -
#780000
0!
0(
#790000
1!
1(
b11111001 .
b10000111 -
#800000
0!
0(
#810000
1!
1(
b11111100 .
b10110100 -
#820000
0!
0(
#830000
1!
1(
0,
b11111110 .
b11010010 -
0%
#840000
0!
0(
#850000
1!
1(
b11111111 .
b11100001 -
#860000
0!
0(
#870000
1!
1(
1,
1%
