Lab1_Team25_Crossbar_2x2_4bit/Lab1_Team25_Crossbar_2x2_4bit.v
`timescale 1ns/1ps

module And_1x4_4bit(f, a, b);
    input [4-1:0] b;
    input a;
    output [4-1:0] f;

    and a0(f[0], a, b[0]);
    and a1(f[1], a, b[1]);
    and a2(f[2], a, b[2]);
    and a3(f[3], a, b[3]);

endmodule

module Or_4x4_4bit(f, a, b);
    input [4-1:0] a, b;
    output [4-1:0] f;

    or o0(f[0], a[0], b[0]);
    or o1(f[1], a[1], b[1]);
    or o2(f[2], a[2], b[2]);
    or o3(f[3], a[3], b[3]);

endmodule

module Mux_2x1_4bit(in1, in2, sel, y);
    input [4-1:0] in1, in2;
    input sel;
    output [4-1:0] y;

    wire [4-1:0] t0, t1;
    wire seln;

    not tmp0(seln, sel);
    And_1x4_4bit tmp1(t0, seln, in1);
    And_1x4_4bit tmp2(t1, sel, in2);
    Or_4x4_4bit tmp3(y, t0, t1);

endmodule

module Dmux_1x2_4bit(in, sel, y1, y2);
    input [4-1:0] in;
    input sel;
    output [4-1:0] y1, y2;

    wire sel_n;

    not tmp4(sel_n, sel);
    And_1x4_4bit tmp5(y1, sel_n, in);
    And_1x4_4bit tmp6(y2, sel, in);

endmodule

module Crossbar_2x2_4bit(in1, in2, control, out1, out2);
    input [4-1:0] in1, in2;
    input control;
    output [4-1:0] out1, out2;

    wire [4-1:0] mid1, mid2, mid3, mid4;
    wire control_n;

    not b0(control_n, control);
    Dmux_1x2_4bit turn1(in1, control, mid1, mid2);
    Dmux_1x2_4bit turn2(in2, control_n, mid3, mid4);
    Mux_2x1_4bit turn3(mid1, mid3, control, out1);
    Mux_2x1_4bit turn4(mid2, mid4, control_n, out2);

endmodule

Lab1_Team25_Crossbar_2x2_4bit/Lab1_Team25_Crossbar_2x2_4bit_t.v
`timescale 1ns/1ps

module Crossbar_2x2_4bit_t;
reg [3:0] in1 = 4'b0001;
reg [3:0] in2 = 4'b0101;
wire [3:0] out1, out2;
reg control = 1'b0;

Crossbar_2x2_4bit m1(
    .in1 (in1),
    .in2 (in2),
    .control (control),
    .out1 (out1),
    .out2 (out2)
);

initial begin
    $dumpfile("Crossbar_2x2.vcd");
    $dumpvars("+all");
end

initial begin
    repeat(2 ** 3) begin
        #1 control = 1'b1 - control;
        in1 = in1 + 4'b1;
        in2 = in2 + 4'b1;
    end
    #1 $finish;
end 

endmodule

Lab1_Team25_Crossbar_2x2_4bit/Crossbar_2x2.vcd
$date
    Sep 25, 2022  16:57:21
$end
$version
    TOOL:	ncsim	15.20-s039
$end
$timescale
    1 ps
$end

$scope module Crossbar_2x2_4bit_t $end
$var reg       4 !    in1 [3:0] $end
$var reg       4 "    in2 [3:0] $end
$var wire      1 #    out1 [3] $end
$var wire      1 $    out1 [2] $end
$var wire      1 %    out1 [1] $end
$var wire      1 &    out1 [0] $end
$var wire      1 '    out2 [3] $end
$var wire      1 (    out2 [2] $end
$var wire      1 )    out2 [1] $end
$var wire      1 *    out2 [0] $end
$var reg       1 +    control  $end

$scope module m1 $end
$var wire      1 ,    in1 [3] $end
$var wire      1 -    in1 [2] $end
$var wire      1 .    in1 [1] $end
$var wire      1 /    in1 [0] $end
$var wire      1 0    in2 [3] $end
$var wire      1 1    in2 [2] $end
$var wire      1 2    in2 [1] $end
$var wire      1 3    in2 [0] $end
$var wire      1 4    control  $end
$var wire      1 #    out1 [3] $end
$var wire      1 $    out1 [2] $end
$var wire      1 %    out1 [1] $end
$var wire      1 &    out1 [0] $end
$var wire      1 '    out2 [3] $end
$var wire      1 (    out2 [2] $end
$var wire      1 )    out2 [1] $end
$var wire      1 *    out2 [0] $end
$var wire      1 5    mid1 [3] $end
$var wire      1 6    mid1 [2] $end
$var wire      1 7    mid1 [1] $end
$var wire      1 8    mid1 [0] $end
$var wire      1 9    mid2 [3] $end
$var wire      1 :    mid2 [2] $end
$var wire      1 ;    mid2 [1] $end
$var wire      1 <    mid2 [0] $end
$var wire      1 =    mid3 [3] $end
$var wire      1 >    mid3 [2] $end
$var wire      1 ?    mid3 [1] $end
$var wire      1 @    mid3 [0] $end
$var wire      1 A    mid4 [3] $end
$var wire      1 B    mid4 [2] $end
$var wire      1 C    mid4 [1] $end
$var wire      1 D    mid4 [0] $end
$var wire      1 E    control_n  $end

$scope module turn1 $end
$var wire      1 ,    in [3] $end
$var wire      1 -    in [2] $end
$var wire      1 .    in [1] $end
$var wire      1 /    in [0] $end
$var wire      1 4    sel  $end
$var wire      1 5    y1 [3] $end
$var wire      1 6    y1 [2] $end
$var wire      1 7    y1 [1] $end
$var wire      1 8    y1 [0] $end
$var wire      1 9    y2 [3] $end
$var wire      1 :    y2 [2] $end
$var wire      1 ;    y2 [1] $end
$var wire      1 <    y2 [0] $end
$var wire      1 E    sel_n  $end

$scope module tmp5 $end
$var wire      1 ,    b [3] $end
$var wire      1 -    b [2] $end
$var wire      1 .    b [1] $end
$var wire      1 /    b [0] $end
$var wire      1 E    a  $end
$var wire      1 5    f [3] $end
$var wire      1 6    f [2] $end
$var wire      1 7    f [1] $end
$var wire      1 8    f [0] $end
$upscope $end


$scope module tmp6 $end
$var wire      1 ,    b [3] $end
$var wire      1 -    b [2] $end
$var wire      1 .    b [1] $end
$var wire      1 /    b [0] $end
$var wire      1 4    a  $end
$var wire      1 9    f [3] $end
$var wire      1 :    f [2] $end
$var wire      1 ;    f [1] $end
$var wire      1 <    f [0] $end
$upscope $end

$upscope $end


$scope module turn2 $end
$var wire      1 0    in [3] $end
$var wire      1 1    in [2] $end
$var wire      1 2    in [1] $end
$var wire      1 3    in [0] $end
$var wire      1 E    sel  $end
$var wire      1 =    y1 [3] $end
$var wire      1 >    y1 [2] $end
$var wire      1 ?    y1 [1] $end
$var wire      1 @    y1 [0] $end
$var wire      1 A    y2 [3] $end
$var wire      1 B    y2 [2] $end
$var wire      1 C    y2 [1] $end
$var wire      1 D    y2 [0] $end
$var wire      1 F    sel_n  $end

$scope module tmp5 $end
$var wire      1 0    b [3] $end
$var wire      1 1    b [2] $end
$var wire      1 2    b [1] $end
$var wire      1 3    b [0] $end
$var wire      1 F    a  $end
$var wire      1 =    f [3] $end
$var wire      1 >    f [2] $end
$var wire      1 ?    f [1] $end
$var wire      1 @    f [0] $end
$upscope $end


$scope module tmp6 $end
$var wire      1 0    b [3] $end
$var wire      1 1    b [2] $end
$var wire      1 2    b [1] $end
$var wire      1 3    b [0] $end
$var wire      1 E    a  $end
$var wire      1 A    f [3] $end
$var wire      1 B    f [2] $end
$var wire      1 C    f [1] $end
$var wire      1 D    f [0] $end
$upscope $end

$upscope $end


$scope module turn3 $end
$var wire      1 5    in1 [3] $end
$var wire      1 6    in1 [2] $end
$var wire      1 7    in1 [1] $end
$var wire      1 8    in1 [0] $end
$var wire      1 =    in2 [3] $end
$var wire      1 >    in2 [2] $end
$var wire      1 ?    in2 [1] $end
$var wire      1 @    in2 [0] $end
$var wire      1 4    sel  $end
$var wire      1 #    y [3] $end
$var wire      1 $    y [2] $end
$var wire      1 %    y [1] $end
$var wire      1 &    y [0] $end
$var wire      1 G    t0 [3] $end
$var wire      1 H    t0 [2] $end
$var wire      1 I    t0 [1] $end
$var wire      1 J    t0 [0] $end
$var wire      1 K    t1 [3] $end
$var wire      1 L    t1 [2] $end
$var wire      1 M    t1 [1] $end
$var wire      1 N    t1 [0] $end
$var wire      1 E    seln  $end

$scope module tmp1 $end
$var wire      1 5    b [3] $end
$var wire      1 6    b [2] $end
$var wire      1 7    b [1] $end
$var wire      1 8    b [0] $end
$var wire      1 E    a  $end
$var wire      1 G    f [3] $end
$var wire      1 H    f [2] $end
$var wire      1 I    f [1] $end
$var wire      1 J    f [0] $end
$upscope $end


$scope module tmp2 $end
$var wire      1 =    b [3] $end
$var wire      1 >    b [2] $end
$var wire      1 ?    b [1] $end
$var wire      1 @    b [0] $end
$var wire      1 4    a  $end
$var wire      1 K    f [3] $end
$var wire      1 L    f [2] $end
$var wire      1 M    f [1] $end
$var wire      1 N    f [0] $end
$upscope $end


$scope module tmp3 $end
$var wire      1 G    a [3] $end
$var wire      1 H    a [2] $end
$var wire      1 I    a [1] $end
$var wire      1 J    a [0] $end
$var wire      1 K    b [3] $end
$var wire      1 L    b [2] $end
$var wire      1 M    b [1] $end
$var wire      1 N    b [0] $end
$var wire      1 #    f [3] $end
$var wire      1 $    f [2] $end
$var wire      1 %    f [1] $end
$var wire      1 &    f [0] $end
$upscope $end

$upscope $end


$scope module turn4 $end
$var wire      1 9    in1 [3] $end
$var wire      1 :    in1 [2] $end
$var wire      1 ;    in1 [1] $end
$var wire      1 <    in1 [0] $end
$var wire      1 A    in2 [3] $end
$var wire      1 B    in2 [2] $end
$var wire      1 C    in2 [1] $end
$var wire      1 D    in2 [0] $end
$var wire      1 E    sel  $end
$var wire      1 '    y [3] $end
$var wire      1 (    y [2] $end
$var wire      1 )    y [1] $end
$var wire      1 *    y [0] $end
$var wire      1 O    t0 [3] $end
$var wire      1 P    t0 [2] $end
$var wire      1 Q    t0 [1] $end
$var wire      1 R    t0 [0] $end
$var wire      1 S    t1 [3] $end
$var wire      1 T    t1 [2] $end
$var wire      1 U    t1 [1] $end
$var wire      1 V    t1 [0] $end
$var wire      1 F    seln  $end

$scope module tmp1 $end
$var wire      1 9    b [3] $end
$var wire      1 :    b [2] $end
$var wire      1 ;    b [1] $end
$var wire      1 <    b [0] $end
$var wire      1 F    a  $end
$var wire      1 O    f [3] $end
$var wire      1 P    f [2] $end
$var wire      1 Q    f [1] $end
$var wire      1 R    f [0] $end
$upscope $end


$scope module tmp2 $end
$var wire      1 A    b [3] $end
$var wire      1 B    b [2] $end
$var wire      1 C    b [1] $end
$var wire      1 D    b [0] $end
$var wire      1 E    a  $end
$var wire      1 S    f [3] $end
$var wire      1 T    f [2] $end
$var wire      1 U    f [1] $end
$var wire      1 V    f [0] $end
$upscope $end


$scope module tmp3 $end
$var wire      1 O    a [3] $end
$var wire      1 P    a [2] $end
$var wire      1 Q    a [1] $end
$var wire      1 R    a [0] $end
$var wire      1 S    b [3] $end
$var wire      1 T    b [2] $end
$var wire      1 U    b [1] $end
$var wire      1 V    b [0] $end
$var wire      1 '    f [3] $end
$var wire      1 (    f [2] $end
$var wire      1 )    f [1] $end
$var wire      1 *    f [0] $end
$upscope $end

$upscope $end

$upscope $end

$upscope $end

$enddefinitions $end
$dumpvars
b1 !
b101 "
0#
0$
0%
1&
0'
1(
0)
1*
0+
0,
0-
0.
1/
00
11
02
13
04
05
06
07
18
09
0:
0;
0<
0=
0>
0?
0@
0A
1B
0C
1D
1E
0F
0G
0H
0I
1J
0K
0L
0M
0N
0O
0P
0Q
0R
0S
1T
0U
1V
$end
#1000
1+
b10 !
b110 "
12
03
1.
0/
14
0E
1;
08
0D
1F
0T
0V
0B
0J
0&
0*
0(
1Q
1>
1?
1M
1L
1)
1$
1%
#2000
0+
b11 !
b111 "
13
1/
04
1E
0L
0M
0;
0@
0Q
1%
0$
0F
1B
1C
1D
17
18
1J
1I
1V
1U
1T
0>
0?
1(
1*
1&
#3000
1+
b100 !
b1000 "
10
01
02
03
1-
0.
0/
14
0E
1:
08
07
0D
0C
0B
1F
0T
0U
0V
0I
0J
0&
0%
0*
0)
1(
1P
1=
1K
1#
#4000
0+
b101 !
b1001 "
13
1/
04
1E
0K
0:
0@
0P
0#
0F
1A
1D
16
18
1J
1H
1V
1S
0=
0(
1'
1*
1$
1&
#5000
1+
b110 !
b1010 "
12
03
1.
0/
14
0E
1:
1;
08
0D
1F
0S
0V
0A
0H
0J
06
0&
0$
0*
0'
1P
1Q
1=
1?
1M
1K
1)
1(
1#
1%
#6000
0+
b111 !
b1011 "
13
1/
04
1E
0K
0M
0:
0;
0@
0Q
0P
1%
0#
0F
1A
1C
1D
16
17
18
1J
1I
1H
1V
1U
1S
0=
0?
0(
1'
1*
1$
1&
#7000
1+
b1000 !
b1100 "
11
02
03
1,
0-
0.
0/
14
0E
19
08
07
06
0D
0C
1F
0S
0U
0V
0A
0H
0I
0J
0&
0%
1$
0*
0)
1'
1O
1=
1>
1L
1K
1#
#8000
0+
b1001 !
b1101 "
13
1/
04
1E
0K
0L
09
0@
0O
0$
1#
0F
1A
1B
1D
15
18
1J
1G
1V
1T
1S
0=
0>
1(
1*
1&
