lab2/yju_basic_lab/Majority/Lab2_Majority.v
`timescale 1ns/1ps

//-----------------
module myNot(out, a);
input a;
output out;

nand (out, a, a);

endmodule

//-----------------
module myAnd (out, a, b);
input a, b;
output out;

wire w1;

nand (w1, a, b);
myNot g0(out, w1);

endmodule

//-----------------
module myOr (out, a, b);
input a, b;
output out;

wire w1, w2;

myNot g0(w1, a);
myNot g1(w2, b);
nand (out, w1, w2);

endmodule

//-----------------
module myNor(out, a, b);
input a, b;
output out;

wire w1;
myOr g0(w1, a, b);
myNot g1(out, w1);

endmodule

//-----------------
module myXor(out, a, b);
input a, b;
output out;

wire na, nb, w1, w2;

myNot g0(na, a);
myNot g1(nb, b);
myAnd g2(w1, a, nb);
myAnd g3(w2, na, b);
myOr g4(out, w1, w2);

endmodule

//-----------------
module myXnor(out, a, b);
input a, b;
output out;

wire w1;

myXor g0(w1, a, b);
myNot g1(out, w1);
endmodule

//-----------------
module MUX_2x1(out, a, b, sel);

input a, b, sel;
output out;

wire w1, w2, nsel;

myNot g0(nsel, sel);
myAnd g1(w1, a, nsel);
myAnd g2(w2, b, sel);
myOr g3(out, w1, w2);

endmodule

//-----------------
module Majority(a, b, c, out);

input a, b, c;
output out;

wire w1, w2, w3, w4, w5;

myAnd g0(w1, a, b);
myAnd g1(w2, a, c);
myAnd g2(w3, b, c);
myOr g3(w4, w1, w2);
myOr g4(out, w4, w3);

endmodule

lab2/lsc_basic_lab/Majority_t.v
`timescale 1ns/1ps

module Majority_t;
    reg a = 1'b0;
    reg b = 1'b0;
    reg c = 1'b0;
    wire out;

    Majority major(
        .a (a),
        .b (a),
        .c (c), 
        .out (out)
    );

    initial begin
        $dumpfile("Majority.vcd");
        $dumpvars;
    end

    initial begin
        repeat (2 ** 3) begin
            #1 {a, b, c} = {a, b, c} + 1'b1;
        end
        #1 $finish;
    end
endmodule

lab2/yju_basic_lab/Majority/Majority.vcd
$date
    Oct  6, 2022  15:56:38
$end
$version
    TOOL:	ncsim	15.20-s039
$end
$timescale
    1 ps
$end

$scope module Majority_t $end
$var reg       1 !    a  $end
$var reg       1 "    b  $end
$var reg       1 #    c  $end
$var wire      1 $    out  $end

$scope module major $end
$var wire      1 %    a  $end
$var wire      1 %    b  $end
$var wire      1 &    c  $end
$var wire      1 $    out  $end
$var wire      1 '    w1  $end
$var wire      1 (    w2  $end
$var wire      1 )    w3  $end
$var wire      1 *    w4  $end
$var wire      1 +    w5  $end

$scope module g0 $end
$var wire      1 %    a  $end
$var wire      1 %    b  $end
$var wire      1 '    out  $end
$var wire      1 ,    w1  $end

$scope module g0 $end
$var wire      1 ,    a  $end
$var wire      1 '    out  $end
$upscope $end

$upscope $end


$scope module g1 $end
$var wire      1 %    a  $end
$var wire      1 &    b  $end
$var wire      1 (    out  $end
$var wire      1 -    w1  $end

$scope module g0 $end
$var wire      1 -    a  $end
$var wire      1 (    out  $end
$upscope $end

$upscope $end


$scope module g2 $end
$var wire      1 %    a  $end
$var wire      1 &    b  $end
$var wire      1 )    out  $end
$var wire      1 .    w1  $end

$scope module g0 $end
$var wire      1 .    a  $end
$var wire      1 )    out  $end
$upscope $end

$upscope $end


$scope module g3 $end
$var wire      1 '    a  $end
$var wire      1 (    b  $end
$var wire      1 *    out  $end
$var wire      1 /    w1  $end
$var wire      1 0    w2  $end

$scope module g0 $end
$var wire      1 '    a  $end
$var wire      1 /    out  $end
$upscope $end


$scope module g1 $end
$var wire      1 (    a  $end
$var wire      1 0    out  $end
$upscope $end

$upscope $end


$scope module g4 $end
$var wire      1 *    a  $end
$var wire      1 )    b  $end
$var wire      1 $    out  $end
$var wire      1 1    w1  $end
$var wire      1 2    w2  $end

$scope module g0 $end
$var wire      1 *    a  $end
$var wire      1 1    out  $end
$upscope $end


$scope module g1 $end
$var wire      1 )    a  $end
$var wire      1 2    out  $end
$upscope $end

$upscope $end

$upscope $end

$upscope $end


$scope module MUX_2x1 $end
$var wire      1 +    a  $end
$var wire      1 +    b  $end
$var wire      1 +    sel  $end
$var wire      1 3    out  $end
$var wire      1 4    w1  $end
$var wire      1 5    w2  $end
$var wire      1 6    nsel  $end

$scope module g0 $end
$var wire      1 +    a  $end
$var wire      1 6    out  $end
$upscope $end


$scope module g1 $end
$var wire      1 +    a  $end
$var wire      1 6    b  $end
$var wire      1 4    out  $end
$var wire      1 7    w1  $end

$scope module g0 $end
$var wire      1 7    a  $end
$var wire      1 4    out  $end
$upscope $end

$upscope $end


$scope module g2 $end
$var wire      1 +    a  $end
$var wire      1 +    b  $end
$var wire      1 5    out  $end
$var wire      1 6    w1  $end

$scope module g0 $end
$var wire      1 6    a  $end
$var wire      1 5    out  $end
$upscope $end

$upscope $end


$scope module g3 $end
$var wire      1 4    a  $end
$var wire      1 5    b  $end
$var wire      1 3    out  $end
$var wire      1 8    w1  $end
$var wire      1 9    w2  $end

$scope module g0 $end
$var wire      1 4    a  $end
$var wire      1 8    out  $end
$upscope $end


$scope module g1 $end
$var wire      1 5    a  $end
$var wire      1 9    out  $end
$upscope $end

$upscope $end

$upscope $end


$scope module myXnor $end
$var wire      1 +    a  $end
$var wire      1 +    b  $end
$var wire      1 :    out  $end
$var wire      1 ;    w1  $end

$scope module g0 $end
$var wire      1 +    a  $end
$var wire      1 +    b  $end
$var wire      1 ;    out  $end
$var wire      1 6    na  $end
$var wire      1 6    nb  $end
$var wire      1 4    w1  $end
$var wire      1 <    w2  $end

$scope module g0 $end
$var wire      1 +    a  $end
$var wire      1 6    out  $end
$upscope $end


$scope module g1 $end
$var wire      1 +    a  $end
$var wire      1 6    out  $end
$upscope $end


$scope module g2 $end
$var wire      1 +    a  $end
$var wire      1 6    b  $end
$var wire      1 4    out  $end
$var wire      1 7    w1  $end

$scope module g0 $end
$var wire      1 7    a  $end
$var wire      1 4    out  $end
$upscope $end

$upscope $end


$scope module g3 $end
$var wire      1 6    a  $end
$var wire      1 +    b  $end
$var wire      1 <    out  $end
$var wire      1 =    w1  $end

$scope module g0 $end
$var wire      1 =    a  $end
$var wire      1 <    out  $end
$upscope $end

$upscope $end


$scope module g4 $end
$var wire      1 4    a  $end
$var wire      1 <    b  $end
$var wire      1 ;    out  $end
$var wire      1 8    w1  $end
$var wire      1 >    w2  $end

$scope module g0 $end
$var wire      1 4    a  $end
$var wire      1 8    out  $end
$upscope $end


$scope module g1 $end
$var wire      1 <    a  $end
$var wire      1 >    out  $end
$upscope $end

$upscope $end

$upscope $end


$scope module g1 $end
$var wire      1 ;    a  $end
$var wire      1 :    out  $end
$upscope $end

$upscope $end


$scope module myNor $end
$var wire      1 +    a  $end
$var wire      1 +    b  $end
$var wire      1 9    out  $end
$var wire      1 5    w1  $end

$scope module g0 $end
$var wire      1 +    a  $end
$var wire      1 +    b  $end
$var wire      1 5    out  $end
$var wire      1 6    w1  $end
$var wire      1 6    w2  $end

$scope module g0 $end
$var wire      1 +    a  $end
$var wire      1 6    out  $end
$upscope $end


$scope module g1 $end
$var wire      1 +    a  $end
$var wire      1 6    out  $end
$upscope $end

$upscope $end


$scope module g1 $end
$var wire      1 5    a  $end
$var wire      1 9    out  $end
$upscope $end

$upscope $end

$enddefinitions $end
$dumpvars
0!
0"
0#
0$
0%
0&
0'
0(
0)
0*
z+
1,
1-
1.
1/
10
11
12
x3
x4
x5
x6
x7
x8
x9
x:
x;
x<
x=
x>
$end
#1000
1#
1&
#2000
0#
1"
0&
#3000
1#
1&
#4000
0#
0"
1!
1%
0&
0,
1'
0/
1*
01
1$
#5000
1#
1&
0.
0-
1(
1)
02
00
#6000
0#
1"
0&
1.
1-
0(
0)
12
10
#7000
1#
1&
0.
0-
1(
1)
02
00
#8000
0#
0"
0!
0%
0&
1.
1-
1,
0'
0(
0)
12
10
1/
0*
11
0$
