lab3/Lab3_Team25_FIFO/Lab3_Team25_FIFO_8.v
`timescale 1ns/1ps

module FIFO_8(clk, rst_n, wen, ren, din, dout, error);

    input clk;
    input rst_n;
    input wen, ren;
    input [8-1:0] din;
    output [8-1:0] dout;
    output error;

    reg [8-1:0] FIFO [0:128-1];
    reg [8-1:0] dout = 0;
    reg error;
    reg [4-1:0] head, tail;

    reg [4-1:0] next_head, next_tail;

    reg [8-1:0] do_car;

    always @(*) begin
        next_head = head + 1;
        next_tail = tail + 1;
        if (head === 4'b1000) begin
            next_head = 0;
        end
        if (tail === 4'b1000) begin
            next_tail = 0;
        end
    end

    always @(posedge clk) begin
        //$display("head next_head %b %b", head, next_head);
        //$display("tail next_tail %b %b", tail, next_tail);
        //$display("FIFO %b", FIFO [tail-1]);
        if (!rst_n) begin
            head <= 0;
            tail <= 0;
            dout <= 0;
            error <= 0;
        end 
        else if (ren) begin
            if ((head === tail)) begin
                head <= head;
                error <= 1;
                tail <= tail;
                dout <= do_car;
            end else begin
                error <= 0;
                dout <= FIFO[head];
                head <= next_head;
                tail <= tail;
            end
        end 
        else if (wen) begin
            if (head === next_tail) begin
                head <= head;
                tail <= tail;
                error <= 1;
                dout <= do_car;
            end else begin
                error <= 0;
                dout <= do_car;
                FIFO[tail] <= din;
                head <= head;
                tail <= next_tail;
            end
        end 
        else begin
            dout <= do_car;
            error <= error;
            head <= head;
            tail <= tail;
        end
    end

endmodule

lab3/Lab3_Team25_FIFO/Lab3_Team25_FIFO_8_t.v
`timescale 1ns/1ps

module FIFO_8_t;
    
    reg clk = 0;
    reg rst_n = 0;
    reg ren = 1'b0;
    reg wen = 1'b0;
    reg [7:0] din = 8'd0;
    wire [7:0] dout;
    wire error;

    parameter cyc = 10;

    // generate clock.
    always#(cyc/2)clk = !clk;

    FIFO_8 fifo(
        .clk (clk),
        .ren (ren),
        .wen (wen),
        .din (din),
        .dout (dout),
        .error (error),
        .rst_n (rst_n)
    );

    initial begin
        $dumpfile("fifo.vcd");
        $dumpvars("+all");
    end
        
    initial begin
        @(negedge clk)
        rst_n = 0;
        din = 8'd87;
        ren = 1'b0;
        wen = 1'b1;
        @(negedge clk)
        rst_n = 1;
        din = 8'd87;
        ren = 1'b1;
        wen = 1'b1;
        @(negedge clk)
        rst_n = 1;
        din = 8'd87;
        ren = 1'b0;
        wen = 1'b1;
        @(negedge clk)
        rst_n = 1;
        din = 8'd85;
        ren = 1'b0;
        wen = 1'b1;
        @(negedge clk)
        rst_n = 1;
        din = 8'd0;
        ren = 1'b0;
        wen = 1'b1;
        @(negedge clk)
        rst_n = 1;
        din = 8'd77;
        ren = 1'b0;
        wen = 1'b1;
        @(negedge clk)
        rst_n = 1;
        din = 8'd77;
        ren = 1'b0;
        wen = 1'b1;
        @(negedge clk)
        rst_n = 1;
        din = 8'd66;
        ren = 1'b0;
        wen = 1'b1;
        @(negedge clk)
        rst_n = 1;
        din = 8'd89;
        ren = 1'b0;
        wen = 1'b1;
        @(negedge clk)
        rst_n = 1;
        din = 8'd89;
        ren = 1'b0;
        wen = 1'b1;
        @(negedge clk)
        rst_n = 1;
        din = 8'd66;
        ren = 1'b0;
        wen = 1'b1;
        @(negedge clk)
        rst_n = 1;
        din = 8'd0;
        ren = 1'b0;
        wen = 1'b0;
        @(negedge clk)
        rst_n = 1;
        din = 8'd10;
        ren = 1'b1;
        wen = 1'b1;
        @(negedge clk)
        rst_n = 1;
        din = 8'd10;
        ren = 1'b1;
        wen = 1'b1;
        @(negedge clk)
        rst_n = 1;
        din = 8'd10;
        ren = 1'b1;
        wen = 1'b1;
        @(negedge clk)
        rst_n = 1;
        din = 8'd10;
        ren = 1'b1;
        wen = 1'b1;
        @(negedge clk)
        rst_n = 1;
        din = 8'd10;
        ren = 1'b1;
        wen = 1'b1;
        @(negedge clk)
        rst_n = 1;
        din = 8'd10;
        ren = 1'b1;
        wen = 1'b1;
        @(negedge clk)
        rst_n = 1;
        din = 8'd10;
        ren = 1'b1;
        wen = 1'b1;
        @(negedge clk)
        rst_n = 1;
        din = 8'd10;
        ren = 1'b1;
        wen = 1'b1;
        @(negedge clk)
        rst_n = 1;
        din = 8'd10;
        ren = 1'b1;
        wen = 1'b1;
        @(negedge clk)
        rst_n = 1;
        din = 8'd10;
        ren = 1'b1;
        wen = 1'b1;
        $finish;
    end
endmodule

lab3/Lab3_Team25_FIFO/fifo.vcd
$date
    Oct 14, 2022  01:06:57
$end
$version
    TOOL:	ncsim	15.20-s039
$end
$timescale
    1 ps
$end

$scope module FIFO_8_t $end
$var reg       1 !    clk  $end
$var reg       1 "    rst_n  $end
$var reg       1 #    ren  $end
$var reg       1 $    wen  $end
$var reg       8 %    din [7:0] $end
$var wire      8 &    dout [7:0] $end
$var wire      1 '    error  $end
$var parameter 32 (    cyc  $end

$scope module fifo $end
$var wire      1 )    clk  $end
$var wire      1 *    rst_n  $end
$var wire      1 +    wen  $end
$var wire      1 ,    ren  $end
$var wire      8 -    din [7:0] $end
$var reg       8 .    dout [7:0] $end
$var reg       1 /    error  $end
$var reg       3 0    head [2:0] $end
$var reg       3 1    tail [2:0] $end
$var wire      3 2    next_head [2:0] $end
$var wire      3 3    next_tail [2:0] $end
$var reg       8 4    do_car [7:0] $end
$upscope $end

$upscope $end

$enddefinitions $end
$dumpvars
b1010 (
0!
0"
0#
0$
b0 %
bx &
x'
0)
0*
0+
0,
b0 -
bx .
x/
bx 0
bx 1
bx 2
bx 3
bx 4
$end
#5000
1!
1)
b0 0
b0 1
b0 .
0/
b1 3
b1 2
0'
b0 &
#10000
0!
b1010111 %
1$
1+
b1010111 -
0)
#15000
1!
1)
#20000
0!
1"
1#
1,
1*
0)
#25000
1!
1)
1/
bx .
bx &
1'
#30000
0!
0#
0,
0)
#35000
1!
1)
0/
b1 1
b10 3
0'
#40000
0!
b1010101 %
b1010101 -
0)
#45000
1!
1)
b10 1
b11 3
#50000
0!
b0 %
b0 -
0)
#55000
1!
1)
b11 1
b100 3
#60000
0!
b1001101 %
b1001101 -
0)
#65000
1!
1)
b100 1
b101 3
#70000
0!
b1000010 %
b1000010 -
0)
#75000
1!
1)
b101 1
b110 3
#80000
0!
b1011001 %
b1011001 -
0)
#85000
1!
1)
b110 1
b111 3
#90000
0!
0)
#95000
1!
1)
b111 1
b0 3
#100000
0!
b1000010 %
b1000010 -
0)
#105000
1!
1)
1/
1'
#110000
0!
b0 %
0$
0+
b0 -
0)
#115000
1!
1)
#120000
0!
b1010 %
1#
1$
1+
1,
b1010 -
0)
#125000
1!
1)
0/
b1010111 .
b1 0
b10 2
b1010111 &
0'
#130000
0!
0)
#135000
1!
1)
b1010101 .
b10 0
b11 2
b1010101 &
#140000
0!
0)
#145000
1!
1)
b0 .
b11 0
b100 2
b0 &
#150000
0!
0)
#155000
1!
1)
b1001101 .
b100 0
b101 2
b1001101 &
#160000
0!
0)
#165000
1!
1)
b1000010 .
b101 0
b110 2
b1000010 &
#170000
0!
0)
#175000
1!
1)
b1011001 .
b110 0
b111 2
b1011001 &
#180000
0!
0)
#185000
1!
1)
b111 0
b0 2
#190000
0!
0)
#195000
1!
1)
1/
bx .
bx &
1'
